Workbook

Sheet 兩期比較
A1: 賀毅科技股份有限公司
A2: 損益表實際數-兩期比較
B5: 2017 | T5: 2017 | U5: 2016 | AM5: 2016 | AN5: 2015 | BF5: 2015 | BG5: 2014 | BY5: 2014 | BZ5: 2013 | CR5: 2013 | CS5: 2012 | DL5: 2013 vs 2012 | DM5: 2013 vs 2012 | DN5: 2014 vs 2013 | DO5: 2014 vs 2013 | DP5: 2015 vs 2014 | DQ5: 2015 vs 2014 | DR5: 2016 vs 2015 | DS5: 2016 vs 2015 | DT5: 2017 vs 2016 | DU5: 2017 vs 2016
B6: Jan | C6: Feb | D6: Mar | E6: Q1 | F6: Apr | G6: May | H6: Jun | I6: Q2 | J6: Jul | K6: Aug | L6: Sep | M6: Q3 | N6: Oct | O6: Nov | P6: Dec | Q6: Q4 | R6: HF | S6: Q1~Q3 | T6: 全年合計 | U6: Jan | V6: Feb | W6: Mar | X6: Q1 | Y6: Apr | Z6: May | AA6: Jun | AB6: Q2 | AC6: Jul | AD6: Aug | AE6: Sep | AF6: Q3 | AG6: Oct | AH6: Nov | AI6: Dec | AJ6: Q4 | AK6: HF | AL6: Q1~Q3 | AM6: 全年合計 | AN6: Jan | AO6: Feb | AP6: Mar | AQ6: Q1 | AR6: Apr | AS6: May | AT6: Jun | AU6: Q2 | AV6: Jul | AW6: Aug | AX6: Sep | AY6: Q3 | AZ6: Oct | BA6: Nov | BB6: Dec | BC6: Q4 | BD6: HF | BE6: Q1~Q3 | BF6: 全年合計 | BG6: Jan | BH6: Feb | BI6: Mar | BJ6: Q1 | BK6: Apr | BL6: May | BM6: Jun | BN6: Q2 | BO6: Jul | BP6: Aug | BQ6: Sep | BR6: Q3 | BS6: Oct | BT6: Nov | BU6: Dec | BV6: Q4 | BW6: HF | BX6: Q1~Q3 | BY6: 全年合計 | BZ6: Jan | CA6: Feb | CB6: Mar | CC6: Q1 | CD6: Apr | CE6: May | CF6: Jun | CG6: Q2 | CH6: Jul | CI6: Aug | CJ6: Sep | CK6: Q3 | CL6: Oct | CM6: Nov | CN6: Dec | CO6: Q4 | CP6: HF | CQ6: Q1-Q3 | CR6: 全年合計 | CS6: Jan | CT6: Feb | CU6: Mar | CV6: Q1 | CW6: Apr | CX6: May | CY6: Jun | CZ6: Q2 | DA6: Jul | DB6: Aug | DC6: Sep | DD6: Q3 | DE6: Oct | DF6: Nov | DG6: Dec | DH6: Q4 | DI6: HF | DJ6: Q1-Q3 | DK6: 全年合計 | DL6: 兩期差異 | DM6: 變動率 | DN6: 兩期差異 | DO6: 變動率 | DP6: 兩期差異 | DQ6: 變動率 | DR6: 兩期差異 | DS6: 變動率 | DT6: 兩期差異 | DU6: 變動率
A7: 營業收入
A8: POS BU1 | B8: ='2017 預算'!C8 -> 4501975 | C8: ='2017 預算'!F8 -> 4505830 | D8: ='2017 預算'!I8 -> 28499391 | E8: =SUM(B8:D8) -> 37507196 | F8: ='2017 預算'!O8 -> 4764667 | G8: ='2017 預算'!R8 -> 12977409 | H8: ='2017 預算'!U8 -> 14460790 | I8: =SUM(F8:H8) -> 32202866 | J8: ='2017 預算'!AA8 -> 5214450 | K8: ='2017 預算'!AD8 -> 9660426 | L8: ='2017 預算'!AG8 -> 0 | M8: =SUM(J8:L8) -> 14874876 | N8: ='2017 預算'!AM8 -> 0 | O8: ='2017 預算'!AP8 -> 0 | P8: ='2017 預算'!AS8 -> 0 | Q8: =SUM(N8:P8) -> 0 | R8: =E8+I8 -> 69710062 | S8: =E8+I8+M8 -> 84584938 | T8: =E8+I8+M8+Q8 -> 84584938 | U8: 7568868 | V8: 7155302 | W8: 22046986 | X8: 36771156 | Y8: 11551044 | Z8: 14260246 | AA8: 21719958 | AB8: 47531248 | AC8: 13786404 | AD8: 21656673 | AE8: 15427205 | AF8: 50870282 | AG8: 4186210 | AH8: 5821279 | AI8: 30182961 | AJ8: 40190450 | AK8: 84302404 | AL8: 135172686 | AM8: 175363136 | AN8: 12425392 | AO8: 6060616 | AP8: 18291729 | AQ8: 36777737 | AR8: 8808531 | AS8: 7925551 | AT8: 18886402 | AU8: 35620484 | AV8: 13325525 | AW8: 7233105 | AX8: 10558033 | AY8: 15698327 | AZ8: 19482901 | BA8: 6159809 | BB8: 26911870 | BC8: 33407056 | BD8: 52300785 | BE8: 67999112 | BF8: =148961797-911580+9687205-1667958 -> 156069464 | BG8: 6422490 | BH8: 6090616 | BI8: 15870998 | BJ8: 28384104 | BK8: 3757141 | BL8: 9765509 | BM8: 11582309 | BN8: 25104959 | BO8: 2245168 | BP8: 6467856 | BQ8: 13721380 | BR8: 22434404 | BS8: 5707503 | BT8: 7608321 | BU8: 13505294 | BV8: 26821118 | BW8: 53489063 | BX8: 75923467 | BY8: =234221549 -> 234221549 | BZ8: 11225175 | CA8: 2996876 | CB8: 5700706 | CC8: 19922757 | CD8: 11202404 | CE8: 5034671 | CF8: 21070553 | CG8: 37307628 | CH8: 6330444 | CI8: 6376788 | CJ8: 11013477 | CK8: 23720709 | CL8: 8155671 | CM8: 13696999 | CN8: 12587867 | CO8: 34440537 | CP8: 57230385 | CQ8: 80951094 | CR8: =235997450-243098 -> 235754352 | CS8: 3024966 | CT8: 8161276 | CU8: 12362451 | CV8: =SUM(CS8:CU8) -> 23548693 | CW8: 6154342 | CX8: 8824445 | CY8: 13820153 | CZ8: =SUM(CW8:CY8) -> 28798940 | DA8: =7680132-1561 -> 7678571 | DB8: 8540673 | DC8: 7199353 | DD8: =SUM(DA8:DC8) -> 23418597 | DE8: 4184659 | DF8: 4063796 | DG8: 12017888 | DH8: =SUM(DE8:DG8) -> 20266343 | DI8: =CV8+CZ8 -> 52347633 | DJ8: =CV8+CZ8+DD8 -> 75766230 | DK8: =DH8+DJ8 -> 96032573 | DL8: =CR8-DK8 -> 139721779 | DM8: =DL8/DK8 -> 1.4549415 | DN8: =BY8-CR8 -> -1532803 | DO8: =DN8/CR8 -> -0.0065016955 | DP8: =BF8-BY8 -> -78152085 | DQ8: =DP8/BY8 -> -0.33366736 | DR8: =AM8-BE8 -> 107364024 | DS8: =DR8/BF8 -> 0.6879246 | DT8: =C8-V8 -> -2649472 | DU8: =DT8/BH8 -> -0.43500887
A9: POS BU2 | B9: ='2017 預算'!C9 -> 0 | C9: ='2017 預算'!F9 -> 0 | D9: ='2017 預算'!I9 -> 0 | E9: =SUM(B9:D9) -> 0 | F9: ='2017 預算'!O9 -> 0 | G9: ='2017 預算'!R9 -> 0 | H9: ='2017 預算'!U9 -> 0 | I9: =SUM(F9:H9) -> 0 | J9: ='2017 預算'!AA9 -> 0 | K9: ='2017 預算'!AD9 -> 0 | L9: ='2017 預算'!AG9 -> 0 | M9: =SUM(J9:L9) -> 0 | N9: ='2017 預算'!AM9 -> 0 | O9: ='2017 預算'!AP9 -> 0 | P9: ='2017 預算'!AS9 -> 0 | Q9: =SUM(N9:P9) -> 0 | R9: =E9+I9 -> 0 | S9: =E9+I9+M9 -> 0 | T9: =E9+I9+M9+Q9 -> 0 | U9: 47882 | V9: 200000 | W9: 617337 | X9: 865219 | Y9: 69571 | Z9: 1347767 | AA9: 1089519 | AB9: 2506857 | AC9: 0 | AD9: 0 | AE9: 0 | AF9: 0 | AG9: 0 | AH9: 0 | AI9: 0 | AJ9: 0 | AK9: 3372076 | AL9: 3372076 | AM9: 3372076 | AN9: 0 | AO9: 0 | AP9: 2000 | AQ9: 2000 | AR9: -28216 | AS9: 160200 | AT9: 0 | AU9: 131984 | AV9: 7155 | AW9: 0 | AX9: 102990 | AY9: 2412808 | AZ9: 607144 | BA9: 168035 | BB9: 648650 | BC9: 2941828 | BD9: 4332569 | BE9: 6745377 | BF9: 1667958 | BG9: 1147616 | BH9: 5294 | BJ9: 1152910 | BK9: 201971 | BL9: 846160 | BM9: 1008235 | BN9: 2056366 | BO9: 515313 | BP9: 1540385 | BR9: 2055698 | BS9: 725640 | BT9: 139040 | BU9: 1828602 | BV9: 2693282 | BW9: 3209276 | BX9: 5264974 | BY9: 7958256 | BZ9: 2815145 | CA9: 1588836 | CB9: 4745076 | CC9: 9149057 | CD9: 1736630 | CE9: 1331798 | CF9: 1322372 | CG9: 4390800 | CH9: 1018802 | CI9: 917921 | CJ9: 1625950 | CK9: 3562673 | CL9: 1890820 | CM9: 1110129 | CN9: 1423862 | CO9: 4424811 | CP9: 13539857 | CQ9: 17102530 | CR9: 21527341 | CS9: 361348 | CT9: 6001628 | CU9: 4814710 | CV9: =SUM(CS9:CU9) -> 11177686 | CW9: 1289405 | CX9: 7267230 | CY9: 2328392 | CZ9: =SUM(CW9:CY9) -> 10885027 | DA9: 5152007 | DB9: 1590517 | DC9: 1209432 | DD9: =SUM(DA9:DC9) -> 7951956 | DE9: 1165690 | DF9: 1478391 | DG9: 3472989 | DH9: =SUM(DE9:DG9) -> 6117070 | DI9: =CV9+CZ9 -> 22062713 | DJ9: =CV9+CZ9+DD9 -> 30014669 | DK9: =DH9+DJ9 -> 36131739 | DL9: =CR9-DK9 -> -14604398 | DM9: =DL9/DK9 -> -0.40419859 | DN9: =BY9-CR9 -> -13569085 | DO9: =DN9/CR9 -> -0.63031867 | DP9: =BF9-BY9 -> -6290298 | DQ9: =DP9/BY9 -> -0.79041162 | DR9: =AM9-BE9 -> -3373301 | DS9: =DR9/BF9 -> -2.0224136 | DT9: =C9-V9 -> -200000 | DU9: =DT9/BH9 -> -37.778617
A10: POS BU3-SE | B10: ='2017 預算'!C10 -> 51078473 | C10: ='2017 預算'!F10 -> 42980961 | D10: ='2017 預算'!I10 -> 30561593 | E10: =SUM(B10:D10) -> 124621027 | F10: ='2017 預算'!O10 -> 59543429 | G10: ='2017 預算'!R10 -> 37166163 | H10: ='2017 預算'!U10 -> 69467942 | I10: =SUM(F10:H10) -> 166177534 | J10: ='2017 預算'!AA10 -> 85004893 | K10: ='2017 預算'!AD10 -> 65629388 | L10: ='2017 預算'!AG10 -> 0 | M10: =SUM(J10:L10) -> 150634281 | N10: ='2017 預算'!AM10 -> 0 | O10: ='2017 預算'!AP10 -> 0 | P10: ='2017 預算'!AS10 -> 0 | Q10: =SUM(N10:P10) -> 0 | R10: =E10+I10 -> 290798561 | S10: =E10+I10+M10 -> 441432842 | T10: =E10+I10+M10+Q10 -> 441432842 | U10: 28946283 | V10: 33831112 | W10: 45177730 | X10: 107955125 | Y10: 30265898 | Z10: 44866539 | AA10: 32987432 | AB10: 108119869 | AC10: 33576273 | AD10: 43602105 | AE10: 35726953 | AF10: 112905331 | AG10: 38830959 | AH10: 58240463 | AI10: 58004207 | AJ10: 155075629 | AK10: 216074994 | AL10: 328980325 | AM10: 484055954 | AN10: 7671588 | AO10: 22355849 | AP10: 42802355 | AQ10: 72829792 | AR10: 40297963 | AS10: 25044659 | AT10: 40268975 | AU10: 105611597 | AV10: 15892559 | AW10: 17462298 | AX10: 20498946 | AY10: 53853803 | AZ10: 4730170 | BA10: 18339741 | BB10: 54328086 | BC10: 77397997 | BD10: 177529809 | BE10: 231383612 | BF10: =308781609+911580 -> 309693189 | BG10: 0 | BH10: 51516 | BI10: 40902 | BJ10: 92418 | BK10: 258862 | BL10: 593364 | BN10: 852226 | BP10: 0 | BQ10: 292986 | BR10: 292986 | BS10: 164416 | BT10: 6590499 | BU10: 11434896 | BV10: 18189811 | BW10: 944644 | BX10: 1237630 | BY10: 19427441 | BZ10: 6988375 | CA10: 200790 | CB10: 4516513 | CC10: 11705678 | CD10: 6113021 | CE10: 6432539 | CF10: 4156199 | CG10: 16701759 | CH10: 6931568 | CI10: 2523453 | CJ10: 253841 | CK10: 9708862 | CL10: 187616 | CM10: 0 | CN10: 1711568 | CO10: 1899184 | CP10: 28407437 | CQ10: 38116299 | CR10: 40015483 | CS10: 8379295 | CT10: 7870561 | CU10: 3387827 | CV10: =SUM(CS10:CU10) -> 19637683 | CW10: 6860711 | CX10: 928044 | CY10: 370 | CZ10: =SUM(CW10:CY10) -> 7789125 | DA10: 8890848 | DB10: 1694 | DC10: 3305503 | DD10: =SUM(DA10:DC10) -> 12198045 | DE10: 3638545 | DF10: 3263583 | DG10: 715729 | DH10: =SUM(DE10:DG10) -> 7617857 | DI10: =CV10+CZ10 -> 27426808 | DJ10: =CV10+CZ10+DD10 -> 39624853 | DK10: =DH10+DJ10 -> 47242710 | DL10: =CR10-DK10 -> -7227227 | DM10: =DL10/DK10 -> -0.15298079 | DN10: =BY10-CR10 -> -20588042 | DO10: =DN10/CR10 -> -0.5145019 | DP10: =BF10-BY10 -> 290265748 | DQ10: =DP10/BY10 -> 14.941018 | DR10: =AM10-BE10 -> 252672342 | DS10: =DR10/BF10 -> 0.81587956 | DT10: =C10-V10 -> 9149849 | DU10: =DT10/BH10 -> 177.61179
A11: POS BU4-AB | B11: ='2017 預算'!C11 -> 4662544 | C11: ='2017 預算'!F11 -> 5540923 | D11: ='2017 預算'!I11 -> 4643464 | E11: =SUM(B11:D11) -> 14846931 | F11: ='2017 預算'!O11 -> 3036598 | G11: ='2017 預算'!R11 -> 3094664 | H11: ='2017 預算'!U11 -> 3477355 | I11: =SUM(F11:H11) -> 9608617 | J11: ='2017 預算'!AA11 -> 8018284 | K11: ='2017 預算'!AD11 -> 6841562 | L11: ='2017 預算'!AG11 -> 0 | M11: =SUM(J11:L11) -> 14859846 | N11: ='2017 預算'!AM11 -> 0 | O11: ='2017 預算'!AP11 -> 0 | P11: ='2017 預算'!AS11 -> 0 | Q11: =SUM(N11:P11) -> 0 | R11: =E11+I11 -> 24455548 | S11: =E11+I11+M11 -> 39315394 | T11: =E11+I11+M11+Q11 -> 39315394 | U11: 336518 | V11: 0 | W11: 917455 | X11: 1253973 | Y11: 165929 | Z11: 194449 | AA11: 184496 | AB11: 544874 | AC11: 3121546 | AD11: 2726096 | AE11: 2871440 | AF11: 8719082 | AG11: 5646258 | AH11: 4131420 | AI11: 5177125 | AJ11: 14954803 | AK11: 1798847 | AL11: 10517929 | AM11: 25472732 | DT11: =C11-V11 -> 5540923 | DU11: =DT11/BH11 -> #DIV/0!
A12: 維修收入 | B12: ='2017 預算'!C12 -> 3959 | C12: ='2017 預算'!F12 -> 43786 | D12: ='2017 預算'!I12 -> 27522 | E12: =SUM(B12:D12) -> 75267 | F12: ='2017 預算'!O12 -> 20986 | G12: ='2017 預算'!R12 -> 43107 | H12: ='2017 預算'!U12 -> 81879 | I12: =SUM(F12:H12) -> 145972 | J12: ='2017 預算'!AA12 -> 3539 | K12: ='2017 預算'!AD12 -> 3539 | L12: ='2017 預算'!AG12 -> 0 | M12: =SUM(J12:L12) -> 7078 | N12: ='2017 預算'!AM12 -> 0 | O12: ='2017 預算'!AP12 -> 0 | P12: ='2017 預算'!AS12 -> 0 | Q12: =SUM(N12:P12) -> 0 | R12: =E12+I12 -> 221239 | S12: =E12+I12+M12 -> 228317 | T12: =E12+I12+M12+Q12 -> 228317 | U12: 56092 | V12: 17262 | W12: 39190 | X12: 112544 | Y12: 20812 | Z12: 20562 | AA12: 44666 | AB12: 86040 | AC12: 22597 | AD12: 18552 | AE12: 20564 | AF12: 61713 | AG12: 14160 | AH12: 26848 | AI12: 3539 | AJ12: 44547 | AK12: 198584 | AL12: 260297 | AM12: 304844 | AN12: 24444 | AO12: 0 | AP12: 2290 | AQ12: 26734 | AR12: 5298 | AS12: 30941 | AT12: 15609 | AU12: 51848 | AV12: 55189 | AW12: 12330 | AX12: 0 | AY12: 67519 | AZ12: 67324 | BA12: 32786 | BB12: 27151 | BC12: 127261 | BD12: 78582 | BE12: 146101 | BF12: 273362 | BG12: 3400 | BH12: 1544 | BI12: 114383 | BJ12: 119327 | BK12: -93751 | BL12: 1200 | BN12: -92551 | BO12: 16392 | BP12: 19966 | BR12: 36358 | BS12: 28734 | BT12: 0 | BU12: 2200 | BV12: 30934 | BW12: 26776 | BX12: 63134 | BY12: 94068 | BZ12: 16138 | CA12: 24772 | CB12: 10496 | CC12: 51406 | CD12: 7827 | CE12: 29615 | CF12: 27200 | CG12: 64642 | CH12: 46077 | CI12: 19847 | CJ12: 10952 | CK12: 76876 | CL12: 9334 | CM12: 5070 | CN12: 35770 | CO12: 50174 | CP12: 116048 | CQ12: 192924 | CR12: 243098 | CS12: 159175 | CT12: 20120 | CU12: 92201 | CV12: =SUM(CS12:CU12) -> 271496 | CW12: 48886 | CX12: 12677 | CY12: 26804 | CZ12: =SUM(CW12:CY12) -> 88367 | DA12: 59329 | DB12: =18410+465664 -> 484074 | DC12: 31580 | DD12: =SUM(DA12:DC12) -> 574983 | DE12: 18910 | DF12: 31199 | DG12: 11854 | DH12: =SUM(DE12:DG12) -> 61963 | DI12: =CV12+CZ12 -> 359863 | DJ12: =CV12+CZ12+DD12 -> 934846 | DK12: =DH12+DJ12 -> 996809 | DL12: =CR12-DK12 -> -753711 | DM12: =DL12/DK12 -> -0.75612379 | DN12: =BY12-CR12 -> -149030 | DO12: =DN12/CR12 -> -0.61304494 | DP12: =BF12-BY12 -> 179294 | DQ12: =DP12/BY12 -> 1.9060042 | DR12: =AM12-BE12 -> 158743 | DS12: =DR12/BF12 -> 0.58070617 | DT12: =C12-V12 -> 26524 | DU12: =DT12/BH12 -> 17.178756
A13: 營業收入合計 | B13: =SUM(B8:B12) -> 60246951 | C13: =SUM(C8:C12) -> 53071500 | D13: =SUM(D8:D12) -> 63731970 | E13: =SUM(B13:D13) -> 177050421 | F13: =SUM(F8:F12) -> 67365680 | G13: =SUM(G8:G12) -> 53281343 | H13: =SUM(H8:H12) -> 87487966 | I13: =SUM(I8:I12) -> 2.0813499e+08 | J13: =SUM(J8:J12) -> 98241166 | K13: =SUM(K8:K12) -> 82134915 | L13: =SUM(L8:L12) -> 0 | M13: =SUM(M8:M12) -> 180376081 | ... S13: =SUM(S8:S12) -> 5.6556149e+08 | T13: =E13+I13+M13+Q13 -> 5.6556149e+08 | U13: 36955643 | V13: 41203676 | W13: 68798698 | X13: 146958017 | Y13: 42073254 | Z13: 60689563 | AA13: 56026071 | AB13: 158788888 | AC13: 50506820 | AD13: 68003426 | AE13: 54046162 | AF13: 172556408 | AG13: 48677587 | AH13: 68220010 | AI13: 93367832 | AJ13: 210265429 | AK13: 305746905 | AL13: 478303313 | AM13: 688568742 | AN13: 20121424 | AO13: 28416465 | AP13: 61098374 | AQ13: 109636263 | AR13: 49083576 | AS13: 33161351 | AT13: 59170986 | AU13: 141415913 | AV13: 29280428 | AW13: 24707733 | AX13: 31159969 | AY13: 85148130 | AZ13: 24887539 | BA13: 24700371 | BB13: 81915757 | BC13: 131503667 | BD13: 251052176 | BE13: 336200306 | BF13: 467703973 | BG13: 15348219 | BH13: 13938223 | BI13: 24821394 | BJ13: 54107836 | BK13: 11791659 | BL13: 33172666 | BM13: 33810586 | BN13: 78774911 | BO13: 20106580 | BP13: 20272573 | BQ13: 23031798 | BR13: 63410951 | BS13: 10158595 | BT13: 20830745 | BU13: 34324208 | BV13: 65313548 | BW13: 132882747 | BX13: 196293698 | BY13: 261607246 | BZ13: 39991069 | CA13: 16193946 | CB13: 25159481 | CC13: 81344496 | CD13: 28150265 | CE13: 26063114 | CF13: 34956546 | CG13: 89169925 | CH13: 23865164 | CI13: 20353037 | CJ13: 21146738 | CK13: 65364939 | CL13: 13204931 | CM13: 25585809 | CN13: 22870174 | CO13: 61660914 | CP13: 170514421 | CQ13: 235879360 | CR13: 297540274 | CS13: =SUM(CS8:CS12) -> 11924784 | CT13: =SUM(CT8:CT12) -> 22053585 | CU13: =SUM(CU8:CU12) -> 20657189 | CV13: =SUM(CS13:CU13) -> 54635558 | CW13: =SUM(CW8:CW12) -> 14353344 | CX13: =SUM(CX8:CX12) -> 17032396 | CY13: =SUM(CY8:CY12) -> 16175719 | CZ13: =SUM(CW13:CY13) -> 47561459 | DA13: =SUM(DA8:DA12) -> 21780755 | DB13: =SUM(DB8:DB12) -> 10616958 | DC13: =SUM(DC8:DC12) -> 11745868 | DD13: =SUM(DA13:DC13) -> 44143581 | DE13: =SUM(DE8:DE12) -> 9007804 | DF13: =SUM(DF8:DF12) -> 8836969 | DG13: =SUM(DG8:DG12) -> 16218460 | DH13: =SUM(DE13:DG13) -> 34063233 | DI13: =CV13+CZ13 -> 102197017 | DJ13: =CV13+CZ13+DD13 -> 146340598 | DK13: =DH13+DJ13 -> 180403831 | DL13: =CR13-DK13 -> 117136443 | DM13: =DL13/DK13 -> 0.64930131 | DN13: =BY13-CR13 -> -35933028 | DO13: =DN13/CR13 -> -0.12076694 | DP13: =BF13-BY13 -> 206096727 | DQ13: =DP13/BY13 -> 0.7878097 | DR13: =AM13-BE13 -> 352368436 | DS13: =DR13/BF13 -> 0.75340056 | DT13: =C13-V13 -> 11867824 | DU13: =DT13/BH13 -> 0.8514589
A14: 營業成本 | B14: ='2017 預算'!C14 -> 55646869 | C14: ='2017 預算'!F14 -> 52320171 | D14: ='2017 預算'!I14 -> 53472402 | E14: =SUM(B14:D14) -> 161439442 | F14: ='2017 預算'!O14 -> 59947315 | G14: ='2017 預算'!R14 -> 46938901 | H14: ='2017 預算'!U14 -> 76556480 | I14: =SUM(F14:H14) -> 183442696 | J14: ='2017 預算'!AA14 -> 87191630 | K14: ='2017 預算'!AD14 -> 70950644 | L14: ='2017 預算'!AG14 -> 0 | M14: =SUM(J14:L14) -> 158142274 | N14: ='2017 預算'!AM14 -> 0 | O14: ='2017 預算'!AP14 -> 0 | P14: ='2017 預算'!AS14 -> 0 | Q14: =SUM(N14:P14) -> 0 | R14: =E14+I14 -> 344882138 | S14: =E14+I14+M14 -> 503024412 | T14: =E14+I14+M14+Q14 -> 503024412 | U14: 31243974 | V14: 39556792 | W14: 52692537 | X14: 123493303 | Y14: 34206151 | Z14: 45727500 | AA14: 41354713 | AB14: 121288364 | AC14: 41942955 | AD14: 55560009 | AE14: 46024712 | AF14: 143527676 | AG14: 43268327 | AH14: 55123597 | AI14: =76583648+99025 -> 76682673 | AJ14: =174975572+99025 -> 175074597 | AK14: 244781667 | AL14: =388309343 -> 388309343 | AM14: =563284915+99025 -> 563383940 | AN14: 16692801 | AO14: 27049095 | AP14: 52912401 | AQ14: 96654297 | AR14: 41243729 | AS14: 27959377 | AT14: 48091078 | AU14: 117294184 | AV14: 25227381 | AW14: 22845429 | AX14: 26427403 | AY14: 74500213 | AZ14: 22033948 | BA14: 21944427 | BB14: 58869666 | BC14: 102848041 | BD14: 213948481 | BE14: 288448694 | BF14: 391296735 | BG14: 10931860 | BH14: 13807347 | BI14: 18299301 | BJ14: 43038508 | BK14: 8610490 | BL14: 25147200 | BM14: 28498589 | BN14: 62256279 | BO14: 14570867 | BP14: 15557467 | BQ14: 16721204 | BR14: 46849538 | BS14: 8444860 | BT14: 19319096 | BU14: 23017369 | BV14: 50781325 | BW14: 105294787 | BX14: 152144325 | BY14: 202925650 | BZ14: 31221524 | CA14: 13904326 | CB14: 18049345 | CC14: 63175195 | CD14: 22365591 | CE14: 22511921 | CF14: 26637307 | CG14: 71514819 | CH14: 18548359 | CI14: 14179951 | CJ14: 20303116 | CK14: 53031426 | CL14: 16862329 | CM14: 21667624 | CN14: 13670900 | CO14: 52200853 | CP14: 134690014 | CQ14: 187721440 | CR14: 239922293 | CS14: 19195795 | CT14: 28091041 | CU14: =[1]TWN_IS!F88 -> 24033698 | CV14: =SUM(CS14:CU14) -> 71320534 | CW14: 18464912 | CX14: 24205476 | CY14: 23689240 | CZ14: =SUM(CW14:CY14) -> 66359628 | DA14: 20158024 | DB14: 18073992 | DC14: 22353248 | DD14: =SUM(DA14:DC14) -> 60585264 | DE14: 20398077 | DF14: 14796955 | DG14: 17035791 | DH14: =SUM(DE14:DG14) -> 52230823 | DI14: =CV14+CZ14 -> 137680162 | DJ14: =CV14+CZ14+DD14 -> 198265426 | DK14: =DH14+DJ14 -> 250496249 | DL14: =CR14-DK14 -> -10573956 | DM14: =DL14/DK14 -> -0.042212033 | DN14: =BY14-CR14 -> -36996643 | DO14: =DN14/CR14 -> -0.15420261 | DP14: =BF14-BY14 -> 188371085 | DQ14: =DP14/BY14 -> 0.92827637 | DR14: =AM14-BE14 -> 274935246 | DS14: =DR14/BF14 -> 0.70262596 | DT14: =C14-V14 -> 12763379 | DU14: =DT14/BH14 -> 0.9243904
A15: ▲ 營業毛利： | B15: =B13-B14 -> 4600082 | C15: =C13-C14 -> 751329 | D15: =D13-D14 -> 10259568 | E15: =SUM(B15:D15) -> 15610979 | F15: =F13-F14 -> 7418365 | G15: =G13-G14 -> 6342441.8 | H15: =H13-H14 -> 10931486 | I15: =I13-I14 -> 24692293 | J15: =J13-J14 -> 11049536 | K15: =K13-K14 -> 11184271 | L15: =L13-L14 -> 0 | M15: =M13-M14 -> 22233807 | ... S15: =S13-S14 -> 62537079 | T15: =E15+I15+M15+Q15 -> 62537079 | U15: 5711669 | V15: 1646884 | W15: 16106161 | X15: 23464714 | Y15: 7867103 | Z15: 14962063 | AA15: 14671358 | AB15: 37500524 | AC15: 8563865 | AD15: 12443417 | AE15: 8021450 | AF15: 29028732 | AG15: 5409260 | AH15: 13096413 | AI15: =AI13-AI14 -> 16685159 | AJ15: =AJ13-AJ14 -> 35190832 | AK15: =AK13-AK14 -> 60965238 | AL15: =AL13-AL14 -> 89993970 | AM15: =AM13-AM14 -> 125184802 | AN15: 3428623 | AO15: 1367370 | AP15: 8185973 | AQ15: 12981966 | AR15: 7839847 | AS15: 5201974 | AT15: 11079908 | AU15: 24121729 | AV15: 4053047 | AW15: 1862304 | AX15: 4732566 | AY15: 10647917 | AZ15: 2853591 | BA15: 2755944 | BB15: 23046091 | BC15: 28655626 | BD15: 37103695 | BE15: 47751612 | BF15: 76407238 | BG15: 4416359 | BH15: 130876 | BI15: 6522093 | BJ15: 11069328 | BK15: 3181169 | BL15: 8025466 | BM15: 5311997 | BN15: 16518632 | BO15: 5535713 | BP15: 4715106 | BQ15: 6310594 | BR15: 16561413 | BS15: 1713735 | BT15: 1511649 | BU15: 11306839 | BV15: 14532223 | BW15: 27587960 | BX15: 44149373 | BY15: 58681596 | BZ15: 8769545 | CA15: 2289620 | CB15: 7110136 | CC15: 18169301 | CD15: 5784674 | CE15: 3551193 | CF15: 8319239 | CG15: 17655106 | CH15: 5316805 | CI15: 6173086 | CJ15: 843622 | CK15: 12333513 | CL15: -3657398 | CM15: 3918185 | CN15: 9199274 | CO15: 9460061 | CP15: 35824407 | CQ15: 48157920 | CR15: 57617981 | CS15: =CS13-CS14 -> -7271011 | CT15: =CT13-CT14 -> -6037456 | CU15: =CU13-CU14 -> -3376509 | CV15: =CV13-CV14 -> -16684976 | CW15: =CW13-CW14 -> -4111568 | CX15: =CX13-CX14 -> -7173080 | CY15: =CY13-CY14 -> -7513521 | CZ15: =CZ13-CZ14 -> -18798169 | ... DG15: =DG13-DG14 -> -817331 | DH15: =SUM(DE15:DG15) -> -18167590 | DI15: =CV15+CZ15 -> -35483145 | DJ15: =CV15+CZ15+DD15 -> -51924828 | DK15: =DH15+DJ15 -> -70092418 | DL15: =CR15-DK15 -> 127710399 | DM15: =DL15/DK15 -> -1.8220287 | DN15: =BY15-CR15 -> 1063615 | DO15: =DN15/CR15 -> 0.018459776 | DP15: =BF15-BY15 -> 17725642 | DQ15: =DP15/BY15 -> 0.30206476 | DR15: =AM15-BE15 -> 77433190 | DS15: =DR15/BF15 -> 1.0134274 | DT15: =C15-V15 -> -895555 | DU15: =DT15/BH15 -> -6.8427748
A16: 毛利率 | B16: =B15/B13*100 -> 7.6353773 | C16: =C15/C13*100 -> 1.415692 | D16: =D15/D13*100 -> 16.097993 | E16: =E15/E13*100 -> 8.8172504 | F16: =F15/F13*100 -> 11.012084 | G16: =G15/G13*100 -> 11.903682 | H16: =H15/H13*100 -> 12.494845 | I16: =I15/I13*100 -> 11.863595 | ... T16: =T15/T13*100 -> 11.057521 | U16: 15.455472 | V16: 3.9969346 | W16: 23.410561 | X16: 15.966951 | Y16: 18.698585 | Z16: 24.653437 | AA16: 26.186662 | AB16: 23.616592 | AC16: 16.955859 | AD16: 18.298221 | AE16: 14.841849 | AF16: 16.822749 | AG16: 11.112424 | AH16: 19.197319 | AI16: =AI15/AI13*100 -> 17.870351 | AJ16: =AJ15/AJ13*100 -> 16.736385 | AK16: =AK15/AK13*100 -> 19.939773 | AL16: =AL15/AL13*100 -> 18.815251 | AM16: =AM15/AM13*100 -> 18.180436 | AN16: 0.17039664 | AO16: 0.048118934 | AP16: 0.13398021 | AQ16: 0.11840942 | AR16: 0.15972445 | AS16: 0.15686858 | AT16: 0.18725238 | AU16: 0.17057295 | AV16: 0.13842171 | AW16: 0.075373325 | AX16: 0.15187968 | AY16: 0.12505168 | AZ16: 0.11465943 | BA16: 0.111575 | BB16: 0.28133892 | BC16: 0.21790743 | BD16: 0.14779276 | BE16: 0.14203322 | BF16: 0.16336666 | BG16: 0.28774407 | BH16: 0.0093897192 | BI16: 0.26276095 | BJ16: 0.20457902 | BK16: 0.26978129 | BL16: 0.24193009 | BM16: 0.15711047 | BN16: 0.20969407 | BO16: 0.27531848 | BP16: 0.23258547 | BQ16: 0.27399485 | BR16: 0.26117591 | BS16: 0.16869803 | BT16: 0.072568168 | BU16: 0.32941296 | BV16: 0.22249937 | BW16: 0.2076113 | BX16: 0.22491488 | BY16: 0.22431181 | BZ16: 0.21928759 | CA16: 0.1413874 | CB16: 0.28260265 | CC16: 0.22336239 | CD16: 0.2054927 | CE16: 0.1362536 | CF16: 0.23798802 | CG16: 0.19799395 | CH16: 0.22278519 | CI16: 0.30330049 | CJ16: 0.039893718 | CK16: 0.18868698 | CL16: -0.27697214 | CM16: 0.15313899 | CN16: 0.40223892 | CO16: 0.15342071 | CP16: 0.21009605 | CQ16: 0.20416335 | CR16: 0.19364767 | CS16: =CS15/CS13 -> -0.60973943 | CT16: =CT15/CT13 -> -0.27376302 | CU16: =CU15/CU13 -> -0.16345443 | CV16: =CV15/CV13 -> -0.30538676 | CW16: =CW15/CW13 -> -0.28645367 | CX16: =CX15/CX13 -> -0.42114333 | CY16: =CY15/CY13 -> -0.46449379 | CZ16: =CZ15/CZ13 -> -0.39523954 | ... DK16: =DK15/DK13 -> -0.38853065 | DL16: =CR16-DK16 -> 0.58217832 | DN16: =BY16-CR16 -> 0.030664144 | DP16: =BF16-BY16 -> -0.06094515 | DR16: =AM16-BE16 -> 18.038403 | DT16: =C16-V16 -> -2.5812426
A17: 毛利率(排除存貨評價) | B17: =(B15+B50)/B13*100 -> 12.406986 | C17: =(C15+C50)/C13*100 -> 6.6227636 | D17: =(D15+D50)/D13*100 -> 4.398127 | E17: =(E15+E50)/E13*100 -> 7.7902351 | F17: =(F15+F50)/F13*100 -> 10.13342 | G17: =(G15+G50)/G13*100 -> 13.882724 | H17: =(H15+H50)/H13*100 -> 10.813789 | I17: =(I15+I50)/I13*100 -> 11.379208 | ... T17: =(T15+T50)/T13*100 -> 10.202775 | U17: 15.504203 | V17: 12.23592 | W17: 23.050571 | X17: 18.120699 | Y17: 17.390911 | Z17: 18.471858 | AA17: 24.184503 | AB17: 20.20106 | AC17: 20.778053 | AD17: 13.413348 | AE17: 14.382794 | AF17: 15.872617 | AG17: 14.172981 | AH17: 13.110516 | AI17: 16.265261 | AJ17: 14.757339 | AK17: 19.201129 | AL17: 18.00031 | AM17: 17.010017 | AN17: 0.20416587 | AO17: 0.10294567 | AP17: 0.16580122 | AQ17: 0.1565508 | AR17: 0.13252578 | AS17: 0.11589751 | AT17: 0.19647016 | AU17: 0.15538202 | AV17: 0.16878718 | AW17: 0.16450445 | AX17: 0.19989699 | AY17: 0.17892909 | AZ17: 0.24106236 | BA17: 0.15193687 | BB17: 0.18672155 | BC17: 0.19047213 | BD17: 0.15589243 | BE17: 0.16172684 | BF17: 0.16980911 | BG17: 0.26375347 | BH17: 0.20182271 | BI17: 0.28511251 | BJ17: 0.25759829 | BK17: 0.28554014 | BL17: 0.23074908 | BM17: 0.24538193 | BN17: 0.24523114 | BR17: 0.25080501 | BS17: 0.229654 | BT17: 0.18004205 | BU17: 0.19447706 | BV17: 0.19534451 | BW17: 0.25026685 | BX17: 0.2504407 | BY17: 0.23668524 | BZ17: 0.22552895 | CA17: 0.16916939 | CB17: 0.22102634 | CC17: 0.21291634 | CD17: 0.2377633 | CE17: 0.22501943 | CF17: 0.24001178 | CG17: 0.2349199 | CK17: 0.23961398 | CL17: 0.16594513 | CM17: 0.1974323 | CN17: 0.28282911 | CO17: 0.22236307 | CP17: 0.22442302 | CQ17: 0.22863262 | CR17: 0.22733334 | DK17: =(DK15+DK50)/DK13 -> -0.39945094 | DL17: =CR17-DK17 -> 0.62678428 | DN17: =BY17-CR17 -> 0.0093518983 | DP17: =BF17-BY17 -> -0.066876132 | DR17: =AM17-BE17 -> 16.84829 | DT17: =C17-V17 -> -5.6131568
A18: 營業費用
A19: 銷售費用 | B19: ='2017 預算'!C18 -> 2682181 | C19: ='2017 預算'!F18 -> 3034578 | D19: ='2017 預算'!I18 -> 2064980 | E19: =SUM(B19:D19) -> 7781739 | F19: ='2017 預算'!O18 -> 2828716 | G19: ='2017 預算'!R18 -> 2899107 | H19: ='2017 預算'!U18 -> 3746561 | I19: =SUM(F19:H19) -> 9474384 | J19: ='2017 預算'!AA18 -> 3694714 | K19: ='2017 預算'!AD18 -> 3586817 | L19: ='2017 預算'!AG18 -> 0 | M19: =SUM(J19:L19) -> 7281531 | N19: ='2017 預算'!AM18 -> 0 | O19: ='2017 預算'!AP18 -> 0 | P19: ='2017 預算'!AS18 -> 0 | Q19: =SUM(N19:P19) -> 0 | R19: =E19+I19 -> 17256123 | S19: =E19+I19+M19 -> 24537654 | T19: =E19+I19+M19+Q19 -> 24537654 | U19: 2459333 | V19: 2826212 | W19: 2965358 | X19: 8250903 | Y19: 3069079 | Z19: 2976654 | AA19: 2698890 | AB19: 8744623 | AC19: 2959846 | AD19: 2138563 | AE19: 1289282 | AF19: 6387691 | AG19: 2838978 | AH19: 3089256 | AI19: =286031+4103644 -> 4389675 | AJ19: =6214265+4103644 -> 10317909 | AK19: 16995526 | AL19: =23383217 -> 23383217 | AM19: =29597482+4103644 -> 33701126 | AN19: 1283568 | AO19: 1374819 | AP19: 1404605 | AQ19: 4062992 | AR19: 1943674 | AS19: 1819649 | AT19: 6876572 | AU19: 10639895 | AV19: 23001712 | AW19: 1344597 | AX19: 1872372 | AY19: 26218681 | AZ19: 3235759 | BA19: 2913406 | BB19: 5724127 | BC19: 11873292 | BD19: 14702887 | BE19: 40921568 | BF19: 52794860 | BG19: 1364416 | BH19: 1307027 | BI19: 2108408 | BJ19: 4779851 | BK19: 1438051 | BL19: 1376748 | BM19: 1556292 | BN19: 4371091 | BO19: 702717 | BP19: 1445924 | BQ19: 1381829 | BR19: 3530470 | BS19: 1147933 | BT19: 1570325 | BU19: 997814 | BV19: 3716072 | BW19: 9150942 | BX19: 12681412 | BY19: 16397484 | BZ19: 1540319 | CA19: 1086538 | CB19: 1084529 | CC19: 3711386 | CD19: 1289944 | CE19: 1323887 | CF19: 1614484 | CG19: 4228315 | CH19: 1652194 | CI19: 1719947 | CJ19: 1689550 | CK19: 5061691 | CL19: 1712496 | CM19: 1462349 | CN19: 1889648 | CO19: 5064493 | CP19: 7939701 | CQ19: 13001392 | CR19: 18065885 | CS19: 1573425 | CT19: 1984506 | CU19: =[1]TWN_IS!F133 -> 2409569 | CV19: =SUM(CS19:CU19) -> 5967500 | CW19: 1555775 | CX19: 2063374 | CY19: 2768247 | CZ19: =SUM(CW19:CY19) -> 6387396 | DA19: 1779022 | DB19: 1589081 | DC19: 1805551 | DD19: =SUM(DA19:DC19) -> 5173654 | DE19: 2120284 | DF19: 1444010 | DG19: -91619 | DH19: =SUM(DE19:DG19) -> 3472675 | DI19: =CV19+CZ19 -> 12354896 | DJ19: =CV19+CZ19+DD19 -> 17528550 | DK19: =DH19+DJ19 -> 21001225 | DL19: =CR19-DK19 -> -2935340 | DM19: =DL19/DK19 -> -0.13976994 | DN19: =BY19-CR19 -> -1668401 | DO19: =DN19/CR19 -> -0.092350914 | DP19: =BF19-BY19 -> 36397376 | DQ19: =DP19/BY19 -> 2.2196927 | DR19: =AM19-BE19 -> -7220442 | DS19: =DR19/BF19 -> -0.13676411 | DT19: =C19-V19 -> 208366 | DU19: =DT19/BH19 -> 0.15941981
A20: 管理費用 | B20: ='2017 預算'!C19 -> 1755765 | C20: ='2017 預算'!F19 -> 2075875 | D20: ='2017 預算'!I19 -> 1882646 | E20: =SUM(B20:D20) -> 5714286 | F20: ='2017 預算'!O19 -> 1770950 | G20: ='2017 預算'!R19 -> 1871563 | H20: ='2017 預算'!U19 -> 1797661 | I20: =SUM(F20:H20) -> 5440174 | J20: ='2017 預算'!AA19 -> 3498119 | K20: ='2017 預算'!AD19 -> 1755224 | L20: ='2017 預算'!AG19 -> 0 | M20: =SUM(J20:L20) -> 5253343 | N20: ='2017 預算'!AM19 -> 0 | O20: ='2017 預算'!AP19 -> 0 | P20: ='2017 預算'!AS19 -> 0 | Q20: =SUM(N20:P20) -> 0 | R20: =E20+I20 -> 11154460 | S20: =E20+I20+M20 -> 16407803 | T20: =E20+I20+M20+Q20 -> 16407803 | U20: 2234226 | V20: 1643974 | W20: 2044943 | X20: 5923143 | Y20: 1736598 | Z20: 1895472 | AA20: 1827592 | AB20: 5459662 | AC20: 2349662 | AD20: 1786527 | AE20: 1612591 | AF20: 5748780 | AG20: 1658767 | AH20: 1610671 | AI20: =1273127+1575403 -> 2848530 | AJ20: =4542565+1575403 -> 6117968 | AK20: 11382805 | AL20: =17131585 -> 17131585 | AM20: =21674150+1575403 -> 23249553 | AN20: 1762901 | AO20: 2584452 | AP20: 1964971 | AQ20: 6312324 | AR20: 2617103 | AS20: 1871651 | AT20: 2003843 | AU20: 6492597 | AV20: 809714 | AW20: 1836978 | AX20: 1698177 | AY20: 4344869 | AZ20: 1696811 | BA20: 1753506 | BB20: 369588 | BC20: 3819905 | BD20: 12804921 | BE20: 17149790 | BF20: 20969695 | BG20: 1618375 | BH20: 1562878 | BI20: 1627110 | BJ20: 4808363 | BK20: 2791737 | BL20: 1687914 | BM20: 1683059 | BN20: 6162710 | BO20: 1581044 | BP20: 1536597 | BQ20: 1633501 | BR20: 4751142 | BS20: 1955586 | BT20: 1582156 | BU20: 610730 | BV20: 4148472 | BW20: 10971073 | BX20: 15722215 | BY20: 19870687 | BZ20: 1718116 | CA20: 1638839 | CB20: 1784191 | CC20: 5141146 | CD20: 1579660 | CE20: 1838434 | CF20: 2045584 | CG20: 5463678 | CH20: 1809532 | CI20: 1595935 | CJ20: 1776790 | CK20: 5182257 | CL20: 1657010 | CM20: 1711369 | CN20: 1219212 | CO20: 4587591 | CP20: 10604824 | CQ20: 15787081 | CR20: 20374672 | CS20: 1113637 | CT20: 947216 | CU20: =[1]TWN_IS!F171 -> 1006350 | CV20: =SUM(CS20:CU20) -> 3067203 | CW20: 1081393 | CX20: 934670 | CY20: 959121 | CZ20: =SUM(CW20:CY20) -> 2975184 | DA20: 932722 | DB20: 946381 | DC20: 903914 | DD20: =SUM(DA20:DC20) -> 2783017 | DE20: 1213932 | DF20: 1653241 | DG20: 1079582 | DH20: =SUM(DE20:DG20) -> 3946755 | DI20: =CV20+CZ20 -> 6042387 | DJ20: =CV20+CZ20+DD20 -> 8825404 | DK20: =DH20+DJ20 -> 12772159 | DL20: =CR20-DK20 -> 7602513 | DM20: =DL20/DK20 -> 0.59524102 | DN20: =BY20-CR20 -> -503985 | DO20: =DN20/CR20 -> -0.024735858 | DP20: =BF20-BY20 -> 1099008 | DQ20: =DP20/BY20 -> 0.055308002 | DR20: =AM20-BE20 -> 6099763 | DS20: =DR20/BF20 -> 0.29088468 | DT20: =C20-V20 -> 431901 | DU20: =DT20/BH20 -> 0.27634979
A21: 研發費用 | B21: ='2017 預算'!C20 -> 2937856 | C21: ='2017 預算'!F20 -> 2632242 | D21: ='2017 預算'!I20 -> 3208223 | E21: =SUM(B21:D21) -> 8778321 | F21: ='2017 預算'!O20 -> 3367941 | G21: ='2017 預算'!R20 -> 2995265 | H21: ='2017 預算'!U20 -> 3153532 | I21: =SUM(F21:H21) -> 9516738 | J21: ='2017 預算'!AA20 -> 3165352 | K21: ='2017 預算'!AD20 -> 3319491 | L21: ='2017 預算'!AG20 -> 0 | M21: =SUM(J21:L21) -> 6484843 | N21: ='2017 預算'!AM20 -> 0 | O21: ='2017 預算'!AP20 -> 0 | P21: ='2017 預算'!AS20 -> 0 | Q21: =SUM(N21:P21) -> 0 | R21: =E21+I21 -> 18295059 | S21: =E21+I21+M21 -> 24779902 | T21: =E21+I21+M21+Q21 -> 24779902 | U21: 2442035 | V21: 2634465 | W21: 2160422 | X21: 7236922 | Y21: 4308942 | Z21: 3656178 | AA21: 4425308 | AB21: 12390428 | AC21: 3618100 | AD21: 3061104 | AE21: 2873853 | AF21: 9553057 | AG21: 2726807 | AH21: 3337104 | AI21: =31975371-499772 -> 31475599 | AJ21: =8039282-499772 -> 7539510 | AK21: 19627350 | AL21: =29180407 -> 29180407 | AM21: =37219689-499772 -> 36719917 | AN21: 2910670 | AO21: 3444523 | AP21: 3684419 | AQ21: 10039612 | AR21: 3019120 | AS21: 3428280 | AT21: 4776909 | AU21: 11224309 | AV21: 2025847 | AW21: 3242345 | AX21: 3331627 | AY21: 8599819 | AZ21: 3225958 | BA21: 2820055 | BB21: 377947 | BC21: 6423960 | BD21: 21263921 | BE21: 29863740 | BF21: 36287700 | BG21: 1911347 | BH21: 2121988 | BI21: 2913268 | BJ21: 6946603 | BK21: 2225040 | BL21: 2903290 | BM21: 2903012 | BN21: 8031342 | BO21: 2703680 | BP21: 1899527 | BQ21: 2788059 | BR21: 7391266 | BS21: 2546454 | BT21: 2627696 | BU21: 1299213 | BV21: 6473363 | BW21: 14977945 | BX21: 22369211 | BY21: 28842574 | BZ21: 1400314 | CA21: 1421109 | CB21: 1841554 | CC21: 4662977 | CD21: 1749976 | CE21: 2233196 | CF21: 2235893 | CG21: 6219065 | CH21: 1949186 | CI21: 2276031 | CJ21: 2056502 | CK21: 6281719 | CL21: 2285323 | CM21: 2201203 | CN21: 780427 | CO21: 5266953 | CP21: 10882042 | CQ21: 17163761 | CR21: 22430714 | CS21: 2932853 | CT21: 2609909 | CU21: =[1]TWN_IS!F208 -> 2380502 | CV21: =SUM(CS21:CU21) -> 7923264 | CW21: 2754521 | CX21: 2409919 | CY21: 2308627 | CZ21: =SUM(CW21:CY21) -> 7473067 | DA21: 2670939 | DB21: 2454486 | DC21: 3401061 | DD21: =SUM(DA21:DC21) -> 8526486 | DE21: 2570156 | DF21: 1311167 | DG21: -1546310 | DH21: =SUM(DE21:DG21) -> 2335013 | DI21: =CV21+CZ21 -> 15396331 | DJ21: =CV21+CZ21+DD21 -> 23922817 | DK21: =DH21+DJ21 -> 26257830 | DL21: =CR21-DK21 -> -3827116 | DM21: =DL21/DK21 -> -0.14575142 | DN21: =BY21-CR21 -> 6411860 | DO21: =DN21/CR21 -> 0.2858518 | DP21: =BF21-BY21 -> 7445126 | DQ21: =DP21/BY21 -> 0.25812974 | DR21: =AM21-BE21 -> 6856177 | DS21: =DR21/BF21 -> 0.18893942 | DT21: =C21-V21 -> -2223 | DU21: =DT21/BH21 -> -0.0010476025
A22: 營業費用合計 | B22: =SUM(B19:B21) -> 7375802 | C22: =SUM(C19:C21) -> 7742695 | D22: =SUM(D19:D21) -> 7155849 | E22: =SUM(B22:D22) -> 22274346 | F22: =SUM(F19:F21) -> 7967607 | G22: =SUM(G19:G21) -> 7765935 | H22: =SUM(H19:H21) -> 8697754 | I22: =SUM(I19:I21) -> 24431296 | J22: =SUM(J19:J21) -> 10358185 | K22: =SUM(K19:K21) -> 8661532 | L22: =SUM(L19:L21) -> 0 | M22: =SUM(M19:M21) -> 19019717 | ... S22: =SUM(S19:S21) -> 65725359 | T22: =E22+I22+M22+Q22 -> 65725359 | U22: 7135594 | V22: 7104651 | W22: 7170723 | X22: 21410968 | Y22: 9114619 | Z22: 8528304 | AA22: 8951790 | AB22: 26594713 | AC22: 8927608 | AD22: 6986194 | AE22: 5775726 | AF22: 21689528 | AG22: 7224552 | AH22: 8037031 | AI22: =SUM(AI19:AI21) -> 38713804 | AJ22: =SUM(AJ19:AJ21) -> 23975387 | AK22: =SUM(AK19:AK21) -> 48005681 | AL22: =SUM(AL19:AL21) -> 69695209 | AM22: =SUM(AM19:AM21) -> 93670596 | AN22: 5957139 | AO22: 7403794 | AP22: 7053995 | AQ22: 20414928 | AR22: 7579897 | AS22: 7119580 | AT22: 13657324 | AU22: 28356801 | AV22: 25837273 | AW22: 6423920 | AX22: 6902176 | AY22: 39163369 | AZ22: 8158528 | BA22: 7486967 | BB22: 6471662 | BC22: 22117157 | BD22: 48771729 | BE22: 87935098 | BF22: 110052255 | BG22: 4894138 | BH22: 4991893 | BI22: 6648786 | BJ22: 16534817 | BK22: 6454828 | BL22: 5967952 | BM22: 6142363 | BN22: 18565143 | BO22: 4987441 | BP22: 4882048 | BQ22: 5803389 | BR22: 15672878 | BS22: 5649973 | BT22: 5780177 | BU22: 2907757 | BV22: 14337907 | BW22: 35099960 | BX22: 50772838 | BY22: 65110745 | BZ22: 4658749 | CA22: 4146486 | CB22: 4710274 | CC22: 13515509 | CD22: 4619580 | CE22: 5395517 | CF22: 5895961 | CG22: 15911058 | CH22: 5410912 | CI22: 5591913 | CJ22: 5522842 | CK22: 16525667 | CL22: 5654829 | CM22: 5374921 | CN22: 3889287 | CO22: 14919037 | CP22: 29426567 | CQ22: 45952234 | CR22: 60871271 | CS22: 5619915 | CT22: 5541631 | CU22: =CU19+CU20+CU21 -> 5796421 | CV22: =SUM(CS22:CU22) -> 16957967 | CW22: 5391689 | CX22: 5407963 | CY22: =SUM(CY19:CY21) -> 6035995 | CZ22: =SUM(CW22:CY22) -> 16835647 | DA22: =SUM(DA19:DA21) -> 5382683 | DB22: =SUM(DB19:DB21) -> 4989948 | DC22: =SUM(DC19:DC21) -> 6110526 | DD22: =SUM(DA22:DC22) -> 16483157 | DE22: =SUM(DE19:DE21) -> 5904372 | DF22: =SUM(DF19:DF21) -> 4408418 | DG22: =SUM(DG19:DG21) -> -558347 | DH22: =SUM(DE22:DG22) -> 9754443 | DI22: =CV22+CZ22 -> 33793614 | DJ22: =CV22+CZ22+DD22 -> 50276771 | DK22: =DH22+DJ22 -> 60031214 | DL22: =CR22-DK22 -> 840057 | DM22: =DL22/DK22 -> 0.01399367 | DN22: =BY22-CR22 -> 4239474 | DO22: =DN22/CR22 -> 0.06964655 | DP22: =BF22-BY22 -> 44941510 | DQ22: =DP22/BY22 -> 0.69023185 | DR22: =AM22-BE22 -> 5735498 | DS22: =DR22/BF22 -> 0.052116133 | DT22: =C22-V22 -> 638044 | DU22: =DT22/BH22 -> 0.12781604
A23: ▲ 營業淨利： | B23: =B15-B22 -> -2775720 | C23: =C15-C22 -> -6991366 | D23: =D15-D22 -> 3103719 | E23: =SUM(B23:D23) -> -6663367 | F23: =F15-F22 -> -549242 | G23: =G15-G22 -> -1423493.2 | H23: =H15-H22 -> 2233732 | I23: =I15-I22 -> 260996.77 | J23: =J15-J22 -> 691351 | K23: =K15-K22 -> 2522739 | L23: =L15-L22 -> 0 | M23: =M15-M22 -> 3214090 | ... S23: =S15-S22 -> -3188280.2 | T23: =E23+I23+M23+Q23 -> -3188280.2 | U23: -1423925 | V23: -5457767 | W23: 8935438 | X23: 2053746 | Y23: -1247516 | Z23: 6433759 | AA23: 5719568 | AB23: 10905811 | AC23: -363743 | AD23: 5457223 | AE23: 2245724 | AF23: 7339204 | AG23: -1815292 | AH23: 5059382 | AI23: =AI15-AI22 -> -22028645 | AJ23: =AJ15-AJ22 -> 11215445 | AK23: =AK15-AK22 -> 12959557 | AL23: =AL15-AL22 -> 20298761 | AM23: =AM15-AM22 -> 31514206 | AN23: -2528516 | AO23: -6036424 | AP23: 1131978 | AQ23: -7432962 | AR23: 259950 | AS23: -1917606 | AT23: -2577416 | AU23: -4235072 | AV23: -21784226 | AW23: -4561616 | AX23: -2169610 | AY23: -28515452 | AZ23: -5304937 | BA23: -4731023 | BB23: 16574429 | BC23: 6538469 | BD23: -11668034 | BE23: -40183486 | BF23: -33645017 | BG23: -477779 | BH23: -4861017 | BI23: -126693 | BJ23: -5465489 | BK23: -3273659 | BL23: 2057514 | BM23: -830366 | BN23: -2046511 | BO23: 548272 | BP23: -166942 | BQ23: 507205 | BR23: 888535 | BS23: -3936238 | BT23: -4268528 | BU23: 8399082 | BV23: 194316 | BW23: -7512000 | BX23: -6623465 | BY23: -6429149 | BZ23: 4110796 | CA23: -1856866 | CB23: 2399862 | CC23: 4653792 | CD23: 1165094 | CE23: -1844324 | CF23: 2423278 | CG23: 1744048 | CH23: -94107 | CI23: 581173 | CJ23: -4679220 | CK23: -4192154 | CL23: -9312227 | CM23: -1456736 | CN23: 5309987 | CO23: -5458976 | CP23: 6397840 | CQ23: 2205686 | CR23: -3253290 | CS23: -4426153 | CT23: -740005 | CU23: =CU15-CU22 -> -9172930 | CV23: =SUM(CS23:CU23) -> -14339088 | CW23: -1312761 | CX23: -2364596 | CY23: =CY15-CY22 -> -13549516 | CZ23: =SUM(CW23:CY23) -> -17226873 | DA23: =DA15-DA22 -> -3759952 | DB23: =DB15-DB22 -> -12446982 | DC23: =DC15-DC22 -> -16717906 | DD23: =SUM(DA23:DC23) -> -32924840 | DE23: =DE15-DE22 -> -17294645 | DF23: =DF15-DF22 -> -10368404 | DG23: =DG15-DG22 -> -258984 | DH23: =SUM(DE23:DG23) -> -27922033 | DI23: =CV23+CZ23 -> -31565961 | DJ23: =CV23+CZ23+DD23 -> -64490801 | DK23: =DH23+DJ23 -> -92412834 | DL23: =CR23-DK23 -> 89159544 | DM23: =DL23/DK23 -> -0.96479612 | DN23: =BY23-CR23 -> -3175859 | DO23: =DN23/CR23 -> 0.97619917 | DP23: =BF23-BY23 -> -27215868 | DQ23: =DP23/BY23 -> 4.2331991 | DR23: =AM23-BE23 -> 71697692 | DS23: =DR23/BF23 -> -2.1310048 | DT23: =C23-V23 -> -1533599 | DU23: =DT23/BH23 -> 0.31548933
A24: 營業外收入及費用
A25: 營業外收入及利益
A26: 利息收入 | B26: ='2017 預算'!C25 -> 1250 | C26: ='2017 預算'!F25 -> 1250 | D26: ='2017 預算'!I25 -> 1250 | E26: =SUM(B26:D26) -> 3750 | F26: ='2017 預算'!O25 -> 1250 | G26: ='2017 預算'!R25 -> 1250 | H26: ='2017 預算'!U25 -> 61835 | I26: =SUM(F26:H26) -> 64335 | J26: ='2017 預算'!AA25 -> 1250 | K26: ='2017 預算'!AD25 -> 1250 | L26: ='2017 預算'!AG25 -> 0 | M26: =SUM(J26:L26) -> 2500 | N26: ='2017 預算'!AM25 -> 0 | O26: ='2017 預算'!AP25 -> 0 | P26: ='2017 預算'!AS25 -> 0 | Q26: =SUM(N26:P26) -> 0 | R26: =E26+I26 -> 68085 | S26: =E26+I26+M26 -> 70585 | T26: =E26+I26+M26+Q26 -> 70585 | U26: 1598 | V26: 1542 | W26: 1542 | X26: 4682 | Y26: 1466 | Z26: 1396 | AA26: 35801 | AB26: 38663 | AC26: 1352 | AD26: 1250 | AE26: 1250 | AF26: 3852 | AG26: 1250 | AH26: 1250 | AI26: 32926 | AJ26: 35426 | AK26: 43345 | AL26: 47197 | AM26: 82623 | AN26: 71934 | AO26: 71933 | AP26: 71935 | AQ26: 215802 | AR26: 71934 | AS26: 50375 | AT26: 65030 | AU26: 187339 | AV26: 28818 | AW26: 1833 | AX26: 1834 | AY26: 32485 | AZ26: 1790 | BA26: 1811 | BB26: 38407 | BC26: 42008 | BD26: 403141 | BE26: 435626 | BF26: 477634 | BG26: 71933 | BH26: 71934 | BI26: 71935 | BJ26: 215802 | BK26: 71934 | BL26: 71934 | BM26: 89981 | BN26: 233849 | BO26: 71934 | BP26: 71933 | BQ26: 71935 | BR26: 215802 | BS26: 71934 | BT26: 71933 | BU26: 94685 | BV26: 238552 | BW26: 449651 | BX26: 665453 | BY26: 904005 | BZ26: 71933 | CA26: 72181 | CB26: 71933 | CC26: 216047 | CD26: 71933 | CE26: 71933 | CF26: 97149 | CG26: 241015 | CH26: 71935 | CI26: 71934 | CJ26: 71934 | CK26: 215803 | CL26: 71934 | CM26: 71933 | CN26: 94581 | CO26: 238448 | CP26: 457062 | CQ26: 672865 | CR26: 911313 | CS26: 66732 | CT26: 72157 | CU26: 72158 | CV26: =SUM(CS26:CU26) -> 211047 | CW26: 72157 | CX26: 72158 | CY26: 88326 | CZ26: =SUM(CW26:CY26) -> 232641 | DA26: 72158 | DB26: 72157 | DC26: 72157 | DD26: =SUM(DA26:DC26) -> 216472 | DE26: 72158 | DF26: 72157 | DG26: 93631 | DH26: =SUM(DE26:DG26) -> 237946 | DI26: =CV26+CZ26 -> 443688 | DJ26: =CV26+CZ26+DD26 -> 660160 | DK26: =DH26+DJ26 -> 898106 | DL26: =CR26-DK26 -> 13207 | DM26: =DL26/DK26 -> 0.014705391 | DN26: =BY26-CR26 -> -7308 | DO26: =BY26/CR26 -> 0.9919808 | DP26: =BF26-BY26 -> -426371 | DQ26: =DP26/BY26 -> -0.47164673 | DR26: =AM26-BE26 -> -353003 | DS26: =DR26/BF26 -> -0.7390659 | DT26: =C26-V26 -> -292 | DU26: =DT26/BH26 -> -0.0040592766
A27: 投資收益 | B27: ='2017 預算'!C26 -> 0 | C27: ='2017 預算'!F26 -> 0 | D27: ='2017 預算'!I26 -> 0 | E27: =SUM(B27:D27) -> 0 | F27: ='2017 預算'!O26 -> 0 | G27: ='2017 預算'!R26 -> 0 | H27: ='2017 預算'!U26 -> 0 | I27: =SUM(F27:H27) -> 0 | J27: ='2017 預算'!AA26 -> 0 | K27: ='2017 預算'!AD26 -> 0 | L27: ='2017 預算'!AG26 -> 0 | M27: =SUM(J27:L27) -> 0 | N27: ='2017 預算'!AM26 -> 0 | O27: ='2017 預算'!AP26 -> 0 | P27: ='2017 預算'!AS26 -> 0 | Q27: =SUM(N27:P27) -> 0 | R27: =E27+I27 -> 0 | S27: =E27+I27+M27 -> 0 | T27: =E27+I27+M27+Q27 -> 0 | U27: 0 | V27: 0 | W27: 0 | X27: 0 | Y27: 0 | Z27: 0 | AA27: 0 | AB27: 0 | AC27: 0 | AD27: 0 | AE27: 0 | AF27: 0 | AG27: 0 | AH27: 0 | AI27: 0 | AJ27: 0 | AK27: 0 | AL27: 0 | AM27: 0 | AN27: 0 | AO27: 0 | AP27: 0 | AQ27: 0 | AR27: 0 | AS27: 0 | AT27: 0 | AU27: 0 | AV27: 0 | AW27: 0 | AX27: 0 | AY27: 0 | AZ27: 0 | BA27: 0 | BB27: 0 | BC27: 0 | BD27: 0 | BE27: 0 | BF27: 0 | BI27: 0 | BJ27: 0 | BK27: 0 | BN27: 0 | BR27: 0 | BV27: 0 | BW27: 0 | BX27: 0 | BY27: 0 | BZ27: 0 | CA27: 0 | CB27: 0 | CC27: 0 | CD27: 0 | CE27: 0 | CF27: 0 | CG27: 0 | CH27: 0 | CI27: 0 | CJ27: 0 | CK27: 0 | CO27: 0 | CP27: 0 | CQ27: 0 | CR27: 0 | CS27: 0 | CT27: 0 | CU27: 0 | CV27: =SUM(CS27:CU27) -> 0 | CW27: 0 | CX27: 0 | CY27: 0 | CZ27: =SUM(CW27:CY27) -> 0 | DA27: 0 | DB27: 0 | DC27: 0 | DD27: =SUM(DA27:DC27) -> 0 | DH27: =SUM(DE27:DG27) -> 0 | DI27: =CV27+CZ27 -> 0 | DJ27: =CV27+CZ27+DD27 -> 0 | DK27: =DH27+DJ27 -> 0 | DL27: =CR27-DK27 -> 0 | DN27: =BY27-CR27 -> 0 | DP27: =BF27-BY27 -> 0 | DR27: =AM27-BE27 -> 0 | DT27: =C27-V27 -> 0
A28: 處分固定資產利益 | B28: ='2017 預算'!C27 -> 0 | C28: ='2017 預算'!F27 -> 0 | D28: ='2017 預算'!I27 -> 0 | E28: =SUM(B28:D28) -> 0 | F28: ='2017 預算'!O27 -> 0 | G28: ='2017 預算'!R27 -> 0 | H28: ='2017 預算'!U27 -> 0 | I28: =SUM(F28:H28) -> 0 | J28: ='2017 預算'!AA27 -> 0 | K28: ='2017 預算'!AD27 -> 0 | L28: ='2017 預算'!AG27 -> 0 | M28: =SUM(J28:L28) -> 0 | N28: ='2017 預算'!AM27 -> 0 | O28: ='2017 預算'!AP27 -> 0 | P28: ='2017 預算'!AS27 -> 0 | Q28: =SUM(N28:P28) -> 0 | R28: =E28+I28 -> 0 | S28: =E28+I28+M28 -> 0 | T28: =E28+I28+M28+Q28 -> 0 | U28: 0 | V28: 0 | W28: 6480 | X28: 6480 | Y28: 0 | Z28: 0 | AA28: 0 | AB28: 0 | AC28: 0 | AD28: 0 | AE28: 0 | AF28: 0 | AG28: 0 | AH28: 0 | AI28: 0 | AJ28: 0 | AK28: 6480 | AL28: 6480 | AM28: 6480 | AN28: 0 | AO28: 0 | AP28: 30762 | AQ28: 30762 | AR28: 0 | AS28: 20766 | AT28: 0 | AU28: 20766 | AV28: 0 | AW28: 0 | AX28: 0 | AY28: 0 | AZ28: 0 | BA28: 5909 | BB28: 0 | BC28: 5909 | BD28: 51528 | BE28: 51528 | BF28: 57437 | BG28: 4190 | BI28: 4857 | BJ28: 9047 | BK28: 0 | BN28: 0 | BR28: 0 | BV28: 0 | BW28: 9047 | BX28: 9047 | BY28: 9047 | BZ28: 0 | CA28: 0 | CB28: 0 | CC28: 0 | CD28: 0 | CE28: 0 | CF28: 0 | CG28: 0 | CH28: 0 | CI28: 0 | CJ28: 0 | CK28: 0 | CN28: 914 | CO28: 914 | CP28: 0 | CQ28: 0 | CR28: 914 | CS28: 0 | CT28: 0 | CU28: 0 | CV28: =SUM(CS28:CU28) -> 0 | CW28: 0 | CX28: 0 | CY28: 0 | CZ28: =SUM(CW28:CY28) -> 0 | DA28: 0 | DB28: 0 | DC28: 0 | DD28: =SUM(DA28:DC28) -> 0 | DH28: =SUM(DE28:DG28) -> 0 | DI28: =CV28+CZ28 -> 0 | DJ28: =CV28+CZ28+DD28 -> 0 | DK28: =DH28+DJ28 -> 0 | DL28: =CR28-DK28 -> 914 | DN28: =BY28-CR28 -> 8133 | DO28: =BY28/CR28-1 -> 8.8982495 | DP28: =BF28-BY28 -> 48390 | DQ28: =DP28/BY28 -> 5.3487344 | DR28: =AM28-BE28 -> -45048 | DS28: =DR28/BF28 -> -0.7843028 | DT28: =C28-V28 -> 0 | DU28: =DT28/BH28 -> #DIV/0!
A29: 處分投資利益 | B29: ='2017 預算'!C28 -> 0 | C29: ='2017 預算'!F28 -> 0 | D29: ='2017 預算'!I28 -> 0 | E29: =SUM(B29:D29) -> 0 | F29: ='2017 預算'!O28 -> 0 | G29: ='2017 預算'!R28 -> 0 | H29: ='2017 預算'!U28 -> 0 | I29: =SUM(F29:H29) -> 0 | J29: ='2017 預算'!AA28 -> 0 | K29: ='2017 預算'!AD28 -> 0 | L29: ='2017 預算'!AG28 -> 0 | M29: =SUM(J29:L29) -> 0 | N29: ='2017 預算'!AM28 -> 0 | O29: ='2017 預算'!AP28 -> 0 | P29: ='2017 預算'!AS28 -> 0 | Q29: =SUM(N29:P29) -> 0 | R29: =E29+I29 -> 0 | S29: =E29+I29+M29 -> 0 | T29: =E29+I29+M29+Q29 -> 0 | U29: 0 | V29: 0 | W29: 0 | X29: 0 | Y29: 0 | Z29: 0 | AA29: 0 | AB29: 0 | AC29: 0 | AD29: 0 | AE29: 0 | AF29: 0 | AG29: 0 | AH29: 0 | AI29: 0 | AJ29: 0 | AK29: 0 | AL29: 0 | AM29: 0 | AN29: 0 | AO29: 0 | AP29: 0 | AQ29: 0 | AR29: 0 | AS29: 0 | AT29: 0 | AU29: 0 | AV29: 0 | AW29: 0 | AX29: 0 | AY29: 0 | AZ29: 0 | BA29: 0 | BB29: 0 | BC29: 0 | BD29: 0 | BE29: 0 | BF29: 0 | BI29: 0 | BJ29: 0 | BK29: 0 | BN29: 0 | BR29: 0 | BV29: 0 | BW29: 0 | BX29: 0 | BY29: 0 | BZ29: 0 | CA29: 0 | CB29: 0 | CC29: 0 | CD29: 0 | CE29: 0 | CF29: 0 | CG29: 0 | CH29: 0 | CI29: 0 | CJ29: 0 | CK29: 0 | CO29: 0 | CP29: 0 | CQ29: 0 | CR29: 0 | CS29: 0 | CT29: 0 | CU29: 0 | CV29: =SUM(CS29:CU29) -> 0 | CW29: 0 | CX29: 0 | CY29: 0 | CZ29: =SUM(CW29:CY29) -> 0 | DA29: 0 | DB29: 0 | DC29: 0 | DD29: =SUM(DA29:DC29) -> 0 | DH29: =SUM(DE29:DG29) -> 0 | DI29: =CV29+CZ29 -> 0 | DJ29: =CV29+CZ29+DD29 -> 0 | DK29: =DH29+DJ29 -> 0 | DL29: =CR29-DK29 -> 0 | DN29: =BY29-CR29 -> 0 | DP29: =BF29-BY29 -> 0 | DR29: =AM29-BE29 -> 0 | DT29: =C29-V29 -> 0
A30: 存貨盤盈 | B30: ='2017 預算'!C29 -> 0 | C30: ='2017 預算'!F29 -> 0 | D30: ='2017 預算'!I29 -> 0 | E30: =SUM(B30:D30) -> 0 | F30: ='2017 預算'!O29 -> 0 | G30: ='2017 預算'!R29 -> 0 | H30: ='2017 預算'!U29 -> 0 | I30: =SUM(F30:H30) -> 0 | J30: ='2017 預算'!AA29 -> 0 | K30: ='2017 預算'!AD29 -> 0 | L30: ='2017 預算'!AG29 -> 0 | M30: =SUM(J30:L30) -> 0 | N30: ='2017 預算'!AM29 -> 0 | O30: ='2017 預算'!AP29 -> 0 | P30: ='2017 預算'!AS29 -> 0 | Q30: =SUM(N30:P30) -> 0 | R30: =E30+I30 -> 0 | S30: =E30+I30+M30 -> 0 | T30: =E30+I30+M30+Q30 -> 0 | U30: 0 | V30: 0 | W30: 0 | X30: 0 | Y30: 0 | Z30: 0 | AA30: 0 | AB30: 0 | AC30: 0 | AD30: 0 | AE30: 0 | AF30: 0 | AG30: 0 | AH30: 0 | AI30: 0 | AJ30: 0 | AK30: 0 | AL30: 0 | AM30: 0 | AN30: 0 | AO30: 0 | AP30: 0 | AQ30: 0 | AR30: 0 | AS30: 0 | AT30: 0 | AU30: 0 | AV30: 0 | AW30: 0 | AX30: 0 | AY30: 0 | AZ30: 0 | BA30: 0 | BB30: 0 | BC30: 0 | BD30: 0 | BE30: 0 | BF30: 0 | BI30: 0 | BJ30: 0 | BK30: 0 | BN30: 0 | BR30: 0 | BV30: 0 | BW30: 0 | BX30: 0 | BY30: 0 | BZ30: 0 | CA30: 0 | CB30: 0 | CC30: 0 | CD30: 0 | CE30: 0 | CF30: 0 | CG30: 0 | CH30: 0 | CI30: 0 | CJ30: 0 | CK30: 0 | CO30: 0 | CP30: 0 | CQ30: 0 | CR30: 0 | CS30: 0 | CT30: 0 | CU30: 0 | CV30: =SUM(CS30:CU30) -> 0 | CW30: 0 | CX30: 0 | CY30: 0 | CZ30: =SUM(CW30:CY30) -> 0 | DA30: 0 | DB30: 0 | DC30: 0 | DD30: =SUM(DA30:DC30) -> 0 | DH30: =SUM(DE30:DG30) -> 0 | DI30: =CV30+CZ30 -> 0 | DJ30: =CV30+CZ30+DD30 -> 0 | DK30: =DH30+DJ30 -> 0 | DL30: =CR30-DK30 -> 0 | DN30: =BY30-CR30 -> 0 | DP30: =BF30-BY30 -> 0 | DR30: =AM30-BE30 -> 0 | DT30: =C30-V30 -> 0
A31: 兌換利益 | B31: ='2017 預算'!C30 -> 860624 | C31: ='2017 預算'!F30 -> 930103 | D31: ='2017 預算'!I30 -> 2946964 | E31: =SUM(B31:D31) -> 4737691 | F31: ='2017 預算'!O30 -> 3612795 | G31: ='2017 預算'!R30 -> 1971131 | H31: ='2017 預算'!U30 -> 3773237 | I31: =SUM(F31:H31) -> 9357163 | J31: ='2017 預算'!AA30 -> 1126662 | K31: ='2017 預算'!AD30 -> 739833 | L31: ='2017 預算'!AG30 -> 0 | M31: =SUM(J31:L31) -> 1866495 | N31: ='2017 預算'!AM30 -> 0 | O31: ='2017 預算'!AP30 -> 0 | P31: ='2017 預算'!AS30 -> 0 | Q31: =SUM(N31:P31) -> 0 | R31: =E31+I31 -> 14094854 | S31: =E31+I31+M31 -> 15961349 | T31: =E31+I31+M31+Q31 -> 15961349 | U31: 2693672 | V31: 2124541 | W31: 914162 | X31: 5732375 | Y31: 2826308 | Z31: 2021649 | AA31: 594478 | AB31: 5442435 | AC31: 36207 | AD31: 1578743 | AE31: 1322573 | AF31: 2937523 | AG31: 1590892 | AH31: 1952388 | AI31: 2621871 | AJ31: 6165151 | AK31: 11174810 | AL31: 14112333 | AM31: 20277484 | AN31: 2016454 | AO31: 971858 | AP31: 389450 | AQ31: 3377762 | AR31: 1156880 | AS31: 2189799 | AT31: 1616760 | AU31: 4963439 | AV31: 2656680 | AW31: 5099592 | AX31: 4000727 | AY31: 11756999 | AZ31: 1820220 | BA31: 1588224 | BB31: 1090974 | BC31: 4499418 | BD31: 8341201 | BE31: 20098200 | BF31: 24597618 | BG31: 1244092 | BH31: 1274263 | BI31: 890875 | BJ31: 3409230 | BK31: 454351 | BL31: 33842 | BM31: 437724 | BN31: 925917 | BO31: 705066 | BP31: 239930 | BQ31: 1819616 | BR31: 2764612 | BS31: 1310425 | BT31: 1331589 | BU31: 2367453 | BV31: 5009467 | BW31: 4335147 | BX31: 7099759 | BY31: 12109226 | BZ31: 1559367 | CA31: 1742044 | CB31: 663010 | CC31: 3964421 | CD31: 1003807 | CE31: 2173671 | CF31: 1077115 | CG31: 4254593 | CH31: 318652 | CI31: 158556 | CJ31: 231081 | CK31: 708289 | CL31: 800699 | CM31: 1010043 | CN31: 865399 | CO31: 2676141 | CP31: 8219014 | CQ31: 8927303 | CR31: 11603444 | CS31: 886004 | CT31: 1360909 | CU31: 851406 | CV31: =SUM(CS31:CU31) -> 3098319 | CW31: 834778 | CX31: 1934883 | CY31: 1181696 | CZ31: =SUM(CW31:CY31) -> 3951357 | DA31: 678875 | DB31: 301077 | DC31: 34353 | DD31: =SUM(DA31:DC31) -> 1014305 | DE31: 1206134 | DF31: 87171 | DG31: 286929 | DH31: =SUM(DE31:DG31) -> 1580234 | DI31: =CV31+CZ31 -> 7049676 | DJ31: =CV31+CZ31+DD31 -> 8063981 | DK31: =DH31+DJ31 -> 9644215 | DL31: =CR31-DK31 -> 1959229 | DM31: =DL31/DK31 -> 0.2031507 | DN31: =BY31-CR31 -> 505782 | DO31: =BY31/CR31-1 -> 0.043588955 | DP31: =BF31-BY31 -> 12488392 | DQ31: =DP31/BY31 -> 1.0313122 | DR31: =AM31-BE31 -> 179284 | DS31: =DR31/BF31 -> 0.0072886732 | DT31: =C31-V31 -> -1194438 | DU31: =DT31/BH31 -> -0.93735595
A32: 租金收入 | B32: ='2017 預算'!C31 -> 0 | C32: ='2017 預算'!F31 -> 0 | D32: ='2017 預算'!I31 -> 0 | E32: =SUM(B32:D32) -> 0 | F32: ='2017 預算'!O31 -> 0 | G32: ='2017 預算'!R31 -> 0 | H32: ='2017 預算'!U31 -> 0 | I32: =SUM(F32:H32) -> 0 | J32: ='2017 預算'!AA31 -> 0 | K32: ='2017 預算'!AD31 -> 0 | L32: ='2017 預算'!AG31 -> 0 | M32: =SUM(J32:L32) -> 0 | N32: ='2017 預算'!AM31 -> 0 | O32: ='2017 預算'!AP31 -> 0 | P32: ='2017 預算'!AS31 -> 0 | Q32: =SUM(N32:P32) -> 0 | R32: =E32+I32 -> 0 | S32: =E32+I32+M32 -> 0 | T32: =E32+I32+M32+Q32 -> 0 | U32: 0 | V32: 0 | W32: 0 | X32: 0 | Y32: 0 | Z32: 0 | AA32: 0 | AB32: 0 | AC32: 0 | AD32: 0 | AE32: 0 | AF32: 0 | AG32: 0 | AH32: 0 | AI32: 0 | AJ32: 0 | AK32: 0 | AL32: 0 | AM32: 0 | AN32: 0 | AO32: 0 | AP32: 0 | AQ32: 0 | AR32: 0 | AS32: 0 | AT32: 0 | AU32: 0 | AV32: 0 | AW32: 0 | AX32: 0 | AY32: 0 | AZ32: 0 | BA32: 0 | BB32: 0 | BC32: 0 | BD32: 0 | BE32: 0 | BF32: 0 | BI32: 0 | BJ32: 0 | BK32: 0 | BN32: 0 | BR32: 0 | BV32: 0 | BW32: 0 | BX32: 0 | BY32: 0 | BZ32: 0 | CA32: 0 | CB32: 0 | CC32: 0 | CD32: 0 | CE32: 0 | CF32: 0 | CG32: 0 | CH32: 0 | CI32: 0 | CJ32: 0 | CK32: 0 | CO32: 0 | CP32: 0 | CQ32: 0 | CR32: 0 | CS32: 0 | CT32: 0 | CU32: 0 | CV32: =SUM(CS32:CU32) -> 0 | CW32: 0 | CX32: 0 | CY32: 0 | CZ32: =SUM(CW32:CY32) -> 0 | DA32: 0 | DB32: 0 | DC32: 0 | DD32: =SUM(DA32:DC32) -> 0 | DH32: =SUM(DE32:DG32) -> 0 | DI32: =CV32+CZ32 -> 0 | DJ32: =CV32+CZ32+DD32 -> 0 | DK32: =DH32+DJ32 -> 0 | DL32: =CR32-DK32 -> 0 | DN32: =BY32-CR32 -> 0 | DP32: =BF32-BY32 -> 0 | DR32: =AM32-BE32 -> 0 | DT32: =C32-V32 -> 0
A33: 金融資產評價利益 | B33: ='2017 預算'!C32 -> 0 | C33: ='2017 預算'!F32 -> 0 | D33: ='2017 預算'!I32 -> 0 | E33: =SUM(B33:D33) -> 0 | F33: ='2017 預算'!O32 -> 0 | G33: ='2017 預算'!R32 -> 0 | H33: ='2017 預算'!U32 -> 0 | I33: =SUM(F33:H33) -> 0 | J33: ='2017 預算'!AA32 -> 0 | K33: ='2017 預算'!AD32 -> 0 | L33: ='2017 預算'!AG32 -> 0 | M33: =SUM(J33:L33) -> 0 | N33: ='2017 預算'!AM32 -> 0 | O33: ='2017 預算'!AP32 -> 0 | P33: ='2017 預算'!AS32 -> 0 | Q33: =SUM(N33:P33) -> 0 | R33: =E33+I33 -> 0 | S33: =E33+I33+M33 -> 0 | T33: =E33+I33+M33+Q33 -> 0 | U33: 0 | V33: 0 | W33: 0 | X33: 0 | Y33: 0 | Z33: 0 | AA33: 0 | AB33: 0 | AC33: 0 | AD33: 0 | AE33: 0 | AF33: 0 | AG33: 0 | AH33: 0 | AI33: 0 | AJ33: 0 | AK33: 0 | AL33: 0 | AM33: 0 | AN33: 0 | AO33: 0 | AP33: 0 | AQ33: 0 | AR33: 0 | AS33: 0 | AT33: 0 | AU33: 0 | AV33: 0 | AW33: 0 | AX33: 0 | AY33: 0 | AZ33: 0 | BA33: 0 | BB33: 0 | BC33: 0 | BD33: 0 | BE33: 0 | BF33: 0 | BI33: 0 | BJ33: 0 | BK33: 0 | BN33: 0 | BR33: 0 | BV33: 0 | BW33: 0 | BX33: 0 | BY33: 0 | BZ33: 0 | CA33: 0 | CB33: 0 | CC33: 0 | CD33: 0 | CE33: 0 | CF33: 0 | CG33: 0 | CH33: 0 | CI33: 0 | CJ33: 0 | CK33: 0 | CO33: 0 | CP33: 0 | CQ33: 0 | CR33: 0 | CS33: 0 | CT33: 0 | CU33: 0 | CV33: =SUM(CS33:CU33) -> 0 | CW33: 0 | CX33: 0 | CY33: 0 | CZ33: =SUM(CW33:CY33) -> 0 | DA33: 0 | DB33: 0 | DC33: 0 | DD33: =SUM(DA33:DC33) -> 0 | DH33: =SUM(DE33:DG33) -> 0 | DI33: =CV33+CZ33 -> 0 | DJ33: =CV33+CZ33+DD33 -> 0 | DK33: =DH33+DJ33 -> 0 | DL33: =CR33-DK33 -> 0 | DN33: =BY33-CR33 -> 0 | DP33: =BF33-BY33 -> 0 | DR33: =AM33-BE33 -> 0 | DT33: =C33-V33 -> 0
A34: 信用卡手續費收入 | B34: ='2017 預算'!C33 -> 0 | C34: ='2017 預算'!F33 -> 0 | D34: ='2017 預算'!I33 -> 0 | E34: =SUM(B34:D34) -> 0 | F34: ='2017 預算'!O33 -> 0 | G34: ='2017 預算'!R33 -> 0 | H34: ='2017 預算'!U33 -> 0 | I34: =SUM(F34:H34) -> 0 | J34: ='2017 預算'!AA33 -> 0 | K34: ='2017 預算'!AD33 -> 0 | L34: ='2017 預算'!AG33 -> 0 | M34: =SUM(J34:L34) -> 0 | N34: ='2017 預算'!AM33 -> 0 | O34: ='2017 預算'!AP33 -> 0 | P34: ='2017 預算'!AS33 -> 0 | Q34: =SUM(N34:P34) -> 0 | R34: =E34+I34 -> 0 | S34: =E34+I34+M34 -> 0 | T34: =E34+I34+M34+Q34 -> 0 | U34: 0 | V34: 0 | W34: 0 | X34: 0 | Y34: 0 | Z34: 0 | AA34: 0 | AB34: 0 | AC34: 0 | AD34: 0 | AE34: 0 | AF34: 0 | AG34: 0 | AH34: 0 | AI34: 0 | AJ34: 0 | AK34: 0 | AL34: 0 | AM34: 0 | AN34: 0 | AO34: 0 | AP34: 0 | AQ34: 0 | AR34: 0 | AS34: 0 | AT34: 0 | AU34: 0 | AV34: 0 | AW34: 0 | AX34: 0 | AY34: 0 | AZ34: 0 | BA34: 0 | BB34: 0 | BC34: 0 | BD34: 0 | BE34: 0 | BF34: 0 | BI34: 0 | BJ34: 0 | BK34: 0 | BN34: 0 | BR34: 0 | BV34: 0 | BW34: 0 | BX34: 0 | BY34: 0 | BZ34: 0 | CA34: 0 | CB34: 0 | CC34: 0 | CD34: 0 | CE34: 0 | CF34: 0 | CG34: 0 | CH34: 0 | CI34: 0 | CJ34: 0 | CK34: 0 | CO34: 0 | CP34: 0 | CQ34: 0 | CR34: 0 | CS34: 0 | CT34: 0 | CU34: 0 | CV34: =SUM(CS34:CU34) -> 0 | CW34: 0 | CX34: 0 | CY34: 0 | CZ34: =SUM(CW34:CY34) -> 0 | DA34: 0 | DB34: 0 | DC34: 0 | DD34: =SUM(DA34:DC34) -> 0 | DH34: =SUM(DE34:DG34) -> 0 | DI34: =CV34+CZ34 -> 0 | DJ34: =CV34+CZ34+DD34 -> 0 | DK34: =DH34+DJ34 -> 0 | DL34: =CR34-DK34 -> 0 | DN34: =BY34-CR34 -> 0 | DP34: =BF34-BY34 -> 0 | DR34: =AM34-BE34 -> 0 | DT34: =C34-V34 -> 0
A35: 什項收入 | B35: ='2017 預算'!C34 -> 151618 | C35: ='2017 預算'!F34 -> 59477 | D35: ='2017 預算'!I34 -> 53695 | E35: =SUM(B35:D35) -> 264790 | F35: ='2017 預算'!O34 -> 277576 | G35: ='2017 預算'!R34 -> 239006 | H35: ='2017 預算'!U34 -> 88951 | I35: =SUM(F35:H35) -> 605533 | J35: ='2017 預算'!AA34 -> 70176 | K35: ='2017 預算'!AD34 -> 264338 | L35: ='2017 預算'!AG34 -> 0 | M35: =SUM(J35:L35) -> 334514 | N35: ='2017 預算'!AM34 -> 0 | O35: ='2017 預算'!AP34 -> 0 | P35: ='2017 預算'!AS34 -> 0 | Q35: =SUM(N35:P35) -> 0 | R35: =E35+I35 -> 870323 | S35: =E35+I35+M35 -> 1204837 | T35: =E35+I35+M35+Q35 -> 1204837 | U35: 316554 | V35: 17278 | W35: 59891 | X35: 393723 | Y35: 26161 | Z35: 30609 | AA35: 363717 | AB35: 420487 | AC35: 52290 | AD35: 254108 | AE35: 86845 | AF35: 393243 | AG35: 200602 | AH35: 136446 | AI35: =192813+4506014 -> 4698827 | AJ35: =529861+4506014 -> 5035875 | AK35: 814210 | AL35: =1207453 -> 1207453 | AM35: =1737314+4506014 -> 6243328 | AN35: 15073 | AO35: 316952 | AP35: 169202 | AQ35: 501227 | AR35: 16367 | AS35: 9525 | AT35: 11230 | AU35: 37122 | AV35: 25340 | AW35: 273025 | AX35: 9216 | AY35: 307581 | AZ35: 7620 | BA35: 19106 | BB35: 26458 | BC35: 53184 | BD35: 538349 | BE35: 845930 | BF35: 899114 | BG35: 29130 | BH35: 93336 | BI35: 27340 | BJ35: 149806 | BK35: 53409 | BL35: 173225 | BM35: 608202 | BN35: 834836 | BO35: 65715 | BP35: 541206 | BQ35: 10315 | BR35: 617236 | BS35: 109511 | BT35: 14275 | BU35: 21505 | BV35: 145291 | BW35: 984642 | BX35: 1601878 | BY35: 1747169 | BZ35: 34721 | CA35: 6283 | CB35: 78067 | CC35: 119071 | CD35: 369105 | CE35: 160457 | CF35: 116734 | CG35: 646296 | CH35: 38077 | CI35: 147416 | CJ35: 22196 | CK35: 207689 | CL35: 129784 | CM35: 257694 | CN35: 149822 | CO35: 537300 | CP35: 765367 | CQ35: 973056 | CR35: 1510356 | CS35: 134662 | CT35: 55454 | CU35: 228604 | CV35: =SUM(CS35:CU35) -> 418720 | CW35: 310500 | CX35: 36511 | CY35: 155005 | CZ35: =SUM(CW35:CY35) -> 502016 | DA35: 15926 | DB35: 205279 | DC35: 153300 | DD35: =SUM(DA35:DC35) -> 374505 | DE35: 67513 | DF35: 40935 | DG35: 188307 | DH35: =SUM(DE35:DG35) -> 296755 | DI35: =CV35+CZ35 -> 920736 | DJ35: =CV35+CZ35+DD35 -> 1295241 | DK35: =DH35+DJ35 -> 1591996 | DL35: =CR35-DK35 -> -81640 | DM35: =DL35/DK35 -> -0.051281536 | DN35: =BY35-CR35 -> 236813 | DO35: =BY35/CR35-1 -> 0.15679284 | DP35: =BF35-BY35 -> -848055 | DQ35: =DP35/BY35 -> -0.48538808 | DR35: =AM35-BE35 -> 5397398 | DS35: =DR35/BF35 -> 6.0030185 | DT35: =C35-V35 -> 42199 | DU35: =DT35/BH35 -> 0.45211923
A36: 小計 | B36: =SUM(B26:B35) -> 1013492 | C36: =SUM(C26:C35) -> 990830 | D36: =SUM(D26:D35) -> 3001909 | E36: =SUM(B36:D36) -> 5006231 | F36: =SUM(F26:F35) -> 3891621 | G36: =SUM(G26:G35) -> 2211387 | H36: =SUM(H26:H35) -> 3924023 | I36: =SUM(I26:I35) -> 10027031 | J36: =SUM(J26:J35) -> 1198088 | K36: =SUM(K26:K35) -> 1005421 | L36: =SUM(L26:L35) -> 0 | M36: =SUM(M26:M35) -> 2203509 | ... S36: =SUM(S26:S35) -> 17236771 | T36: =E36+I36+M36+Q36 -> 17236771 | U36: 3011824 | V36: 2143361 | W36: 982075 | X36: 6137260 | Y36: 2853935 | Z36: 2053654 | AA36: 993996 | AB36: 5901585 | AC36: 89849 | AD36: 1834101 | AE36: 1410668 | AF36: 3334618 | AG36: 1792744 | AH36: 2090084 | AI36: =SUM(AI26:AI35) -> 7353624 | AJ36: =SUM(AJ26:AJ35) -> 11236452 | AK36: =SUM(AK26:AK35) -> 12038845 | AL36: =SUM(AL26:AL35) -> 15373463 | AM36: =SUM(AM26:AM35) -> 26609915 | AN36: 2103461 | AO36: 1360743 | AP36: 661349 | AQ36: 4125553 | AR36: 1245181 | AS36: 2270465 | AT36: 1693020 | AU36: 5208666 | AV36: 2710838 | AW36: 5374450 | AX36: 4011777 | AY36: 12097065 | AZ36: 1829630 | BA36: 1615050 | BB36: 1155839 | BC36: 4600519 | BD36: 9334219 | BE36: 21431284 | BF36: 26031803 | BG36: 1349345 | BH36: 1439533 | BI36: 995007 | BJ36: 3783885 | BK36: 579694 | BL36: 279001 | BM36: 1135907 | BN36: 1994602 | BO36: 842715 | BP36: 853069 | BQ36: 1901866 | BR36: 3597650 | BS36: 1491870 | BT36: 1417797 | BU36: 2483643 | BV36: 5393310 | BW36: 5778487 | BX36: 9376137 | BY36: 14769447 | BZ36: 1666021 | CA36: 1820508 | CB36: 813010 | CC36: 4299539 | CD36: 1444845 | CE36: 2406061 | CF36: 1290998 | CG36: 5141904 | CH36: 428664 | CI36: 377906 | CJ36: 325211 | CK36: 1131781 | CL36: 1002417 | CM36: 1339670 | CN36: 1110716 | CO36: 3452803 | CP36: 9441443 | CQ36: 10573224 | CR36: 14026027 | CS36: 1087398 | CT36: 1488520 | CU36: =SUM(CU26:CU35) -> 1152168 | CV36: =SUM(CS36:CU36) -> 3728086 | CW36: 1217435 | CX36: 2043552 | CY36: =SUM(CY26:CY35) -> 1425027 | CZ36: =SUM(CW36:CY36) -> 4686014 | DA36: =SUM(DA26:DA35) -> 766959 | DB36: =SUM(DB26:DB35) -> 578513 | DC36: =SUM(DC26:DC35) -> 259810 | DD36: =SUM(DA36:DC36) -> 1605282 | DE36: =SUM(DE26:DE35) -> 1345805 | DF36: =SUM(DF26:DF35) -> 200263 | DG36: =SUM(DG26:DG35) -> 568867 | DH36: =SUM(DE36:DG36) -> 2114935 | DI36: =CV36+CZ36 -> 8414100 | DJ36: =CV36+CZ36+DD36 -> 10019382 | DK36: =DH36+DJ36 -> 12134317 | DL36: =CR36-DK36 -> 1891710 | DM36: =DL36/DK36 -> 0.15589753 | DN36: =BY36-CR36 -> 743420 | DO36: =BY36/CR36-1 -> 0.053002892 | DP36: =BF36-BY36 -> 11262356 | DQ36: =DP36/BY36 -> 0.76254419 | DR36: =AM36-BE36 -> 5178631 | DS36: =DR36/BF36 -> 0.19893478 | DT36: =C36-V36 -> -1152531 | DU36: =DT36/BH36 -> -0.8006284
A37: 營業外費用及損失 | BX37: 0 | CO37: 0
A38: 利息費用 | B38: ='2017 預算'!C37 -> 26301 | C38: ='2017 預算'!F37 -> 74827 | D38: ='2017 預算'!I37 -> 69962 | E38: =SUM(B38:D38) -> 171090 | F38: ='2017 預算'!O37 -> 93988 | G38: ='2017 預算'!R37 -> 91944 | H38: ='2017 預算'!U37 -> 112861 | I38: =SUM(F38:H38) -> 298793 | J38: ='2017 預算'!AA37 -> 96752 | K38: ='2017 預算'!AD37 -> 117626 | L38: ='2017 預算'!AG37 -> 0 | M38: =SUM(J38:L38) -> 214378 | N38: ='2017 預算'!AM37 -> 0 | O38: ='2017 預算'!AP37 -> 0 | P38: ='2017 預算'!AS37 -> 0 | Q38: =SUM(N38:P38) -> 0 | R38: =E38+I38 -> 469883 | S38: =E38+I38+M38 -> 684261 | T38: =E38+I38+M38+Q38 -> 684261 | U38: 25944 | V38: 0 | W38: 0 | X38: 25944 | Y38: 0 | Z38: 23548 | AA38: 63676 | AB38: 87224 | AC38: 88995 | AD38: 62155 | AE38: 30610 | AF38: 181760 | AG38: 24394 | AH38: 1563 | AI38: 89640 | AJ38: 115597 | AK38: 113168 | AL38: 294928 | AM38: 410525 | AN38: 0 | AO38: 0 | AP38: 14575 | AQ38: 14575 | AR38: 0 | AS38: 0 | AT38: 0 | AU38: 0 | AV38: 15616 | AW38: 0 | AX38: 14575 | AY38: 30191 | AZ38: 90575 | BA38: 51326 | BB38: 37167 | BC38: 179068 | BD38: 14575 | BE38: 44766 | BF38: 223834 | BI38: 0 | BJ38: 0 | BK38: 0 | BN38: 0 | BR38: 0 | BV38: 0 | BW38: 0 | BX38: 0 | BY38: 0 | BZ38: 0 | CA38: 0 | CB38: 0 | CC38: 0 | CD38: 0 | CE38: 0 | CF38: 0 | CG38: 0 | CH38: 0 | CI38: 0 | CJ38: 0 | CK38: 0 | CO38: 0 | CP38: 0 | CQ38: 0 | CR38: 0 | CS38: 0 | CT38: 1712 | CU38: 0 | CV38: =SUM(CS38:CU38) -> 1712 | CW38: 0 | CX38: 0 | CY38: 0 | CZ38: =SUM(CW38:CY38) -> 0 | DA38: 0 | DB38: 0 | DC38: 0 | DD38: =SUM(DA38:DC38) -> 0 | DH38: =SUM(DE38:DG38) -> 0 | DI38: =CV38+CZ38 -> 1712 | DJ38: =CV38+CZ38+DD38 -> 1712 | DK38: =DH38+DJ38 -> 1712 | DL38: =CR38-DK38 -> -1712 | DM38: =DL38/DK38 -> -1 | DN38: =BY38-CR38 -> 0 | DP38: =BF38-BY38 -> 223834 | DR38: =AM38-BE38 -> 365759 | DS38: =DR38/BF38 -> 1.6340636 | DT38: =C38-V38 -> 74827 | DU38: =DT38/BH38 -> #DIV/0!
A39: 投資損失 | B39: ='2017 預算'!C38 -> 0 | C39: ='2017 預算'!F38 -> 0 | D39: ='2017 預算'!I38 -> 0 | E39: =SUM(B39:D39) -> 0 | F39: ='2017 預算'!O38 -> 0 | G39: ='2017 預算'!R38 -> 0 | H39: ='2017 預算'!U38 -> 0 | I39: =SUM(F39:H39) -> 0 | J39: ='2017 預算'!AA38 -> 0 | K39: ='2017 預算'!AD38 -> 0 | L39: ='2017 預算'!AG38 -> 0 | M39: =SUM(J39:L39) -> 0 | N39: ='2017 預算'!AM38 -> 0 | O39: ='2017 預算'!AP38 -> 0 | P39: ='2017 預算'!AS38 -> 0 | Q39: =SUM(N39:P39) -> 0 | R39: =E39+I39 -> 0 | S39: =E39+I39+M39 -> 0 | T39: =E39+I39+M39+Q39 -> 0 | U39: 0 | V39: 0 | W39: 0 | X39: 0 | Y39: 0 | Z39: 0 | AA39: 0 | AB39: 0 | AC39: 0 | AD39: 0 | AE39: 0 | AF39: 0 | AG39: 0 | AH39: 0 | AI39: 0 | AJ39: 0 | AK39: 0 | AL39: 0 | AM39: 0 | AN39: 0 | AO39: 0 | AP39: 0 | AQ39: 0 | AR39: 0 | AS39: 0 | AT39: 0 | AU39: 0 | AV39: 0 | AW39: 0 | AX39: 0 | AY39: 0 | AZ39: 0 | BA39: 0 | BB39: 0 | BC39: 0 | BD39: 0 | BE39: 0 | BF39: 0 | BI39: 0 | BJ39: 0 | BK39: 0 | BN39: 0 | BR39: 0 | BV39: 0 | BW39: 0 | BX39: 0 | BY39: 0 | BZ39: 0 | CA39: 0 | CB39: 0 | CC39: 0 | CD39: 0 | CE39: 0 | CF39: 0 | CG39: 0 | CH39: 0 | CI39: 0 | CJ39: 0 | CK39: 0 | CO39: 0 | CP39: 0 | CQ39: 0 | CR39: 0 | CS39: 0 | CT39: 0 | CU39: 0 | CV39: =SUM(CS39:CU39) -> 0 | CW39: 0 | CX39: 0 | CY39: 0 | CZ39: =SUM(CW39:CY39) -> 0 | DA39: 0 | DB39: 0 | DC39: 0 | DD39: =SUM(DA39:DC39) -> 0 | DH39: =SUM(DE39:DG39) -> 0 | DI39: =CV39+CZ39 -> 0 | DJ39: =CV39+CZ39+DD39 -> 0 | DK39: =DH39+DJ39 -> 0 | DL39: =CR39-DK39 -> 0 | DN39: =BY39-CR39 -> 0 | DP39: =BF39-BY39 -> 0 | DR39: =AM39-BE39 -> 0 | DT39: =C39-V39 -> 0
A40: 處分固定資產損失 | B40: ='2017 預算'!C39 -> 0 | C40: ='2017 預算'!F39 -> 0 | D40: ='2017 預算'!I39 -> 0 | E40: =SUM(B40:D40) -> 0 | F40: ='2017 預算'!O39 -> 0 | G40: ='2017 預算'!R39 -> 0 | H40: ='2017 預算'!U39 -> 0 | I40: =SUM(F40:H40) -> 0 | J40: ='2017 預算'!AA39 -> 0 | K40: ='2017 預算'!AD39 -> 0 | L40: ='2017 預算'!AG39 -> 0 | M40: =SUM(J40:L40) -> 0 | N40: ='2017 預算'!AM39 -> 0 | O40: ='2017 預算'!AP39 -> 0 | P40: ='2017 預算'!AS39 -> 0 | Q40: =SUM(N40:P40) -> 0 | R40: =E40+I40 -> 0 | S40: =E40+I40+M40 -> 0 | T40: =E40+I40+M40+Q40 -> 0 | U40: 0 | V40: 0 | W40: 0 | X40: 0 | Y40: 0 | Z40: 0 | AA40: 0 | AB40: 0 | AC40: 0 | AD40: 0 | AE40: 0 | AF40: 0 | AG40: 0 | AH40: 0 | AI40: 0 | AJ40: 0 | AK40: 0 | AL40: 0 | AM40: 0 | AN40: 0 | AO40: 0 | AP40: 0 | AQ40: 0 | AR40: 0 | AS40: 0 | AT40: 0 | AU40: 0 | AV40: 0 | AW40: 0 | AX40: 0 | AY40: 0 | AZ40: 0 | BA40: 0 | BB40: 0 | BC40: 0 | BD40: 0 | BE40: 0 | BF40: 0 | BI40: 0 | BJ40: 0 | BK40: 0 | BN40: 0 | BR40: 0 | BV40: 0 | BW40: 0 | BX40: 0 | BY40: 0 | BZ40: 540000 | CA40: 0 | CB40: 0 | CC40: 540000 | CD40: 0 | CE40: 0 | CF40: 0 | CG40: 0 | CH40: 0 | CI40: 0 | CJ40: 0 | CK40: 0 | CO40: 0 | CP40: 540000 | CQ40: 540000 | CR40: 540000 | CS40: 0 | CT40: 0 | CU40: 0 | CV40: =SUM(CS40:CU40) -> 0 | CW40: 0 | CX40: 0 | CY40: 0 | CZ40: =SUM(CW40:CY40) -> 0 | DA40: 0 | DB40: 0 | DC40: 0 | DD40: =SUM(DA40:DC40) -> 0 | DH40: =SUM(DE40:DG40) -> 0 | DI40: =CV40+CZ40 -> 0 | DJ40: =CV40+CZ40+DD40 -> 0 | DK40: =DH40+DJ40 -> 0 | DL40: =CR40-DK40 -> 540000 | DN40: =BY40-CR40 -> -540000 | DO40: =BY40/CR40-1 -> -1 | DP40: =BF40-BY40 -> 0 | DR40: =AM40-BE40 -> 0 | DT40: =C40-V40 -> 0
A41: 處分投資損失 | B41: ='2017 預算'!C40 -> 0 | C41: ='2017 預算'!F40 -> 0 | D41: ='2017 預算'!I40 -> 0 | E41: =SUM(B41:D41) -> 0 | F41: ='2017 預算'!O40 -> 0 | G41: ='2017 預算'!R40 -> 0 | H41: ='2017 預算'!U40 -> 0 | I41: =SUM(F41:H41) -> 0 | J41: ='2017 預算'!AA40 -> 0 | K41: ='2017 預算'!AD40 -> 0 | L41: ='2017 預算'!AG40 -> 0 | M41: =SUM(J41:L41) -> 0 | N41: ='2017 預算'!AM40 -> 0 | O41: ='2017 預算'!AP40 -> 0 | P41: ='2017 預算'!AS40 -> 0 | Q41: =SUM(N41:P41) -> 0 | R41: =E41+I41 -> 0 | S41: =E41+I41+M41 -> 0 | T41: =E41+I41+M41+Q41 -> 0 | U41: 0 | V41: 0 | W41: 0 | X41: 0 | Y41: 0 | Z41: 0 | AA41: 0 | AB41: 0 | AC41: 0 | AD41: 0 | AE41: 0 | AF41: 0 | AG41: 0 | AH41: 0 | AI41: 0 | AJ41: 0 | AK41: 0 | AL41: 0 | AM41: 0 | AN41: 0 | AO41: 0 | AP41: 0 | AQ41: 0 | AR41: 0 | AS41: 0 | AT41: 0 | AU41: 0 | AV41: 0 | AW41: 0 | AX41: 0 | AY41: 0 | AZ41: 0 | BA41: 0 | BB41: 0 | BC41: 0 | BD41: 0 | BE41: 0 | BF41: 0 | BI41: 0 | BJ41: 0 | BK41: 0 | BN41: 0 | BR41: 0 | BV41: 0 | BW41: 0 | BX41: 0 | BY41: 0 | BZ41: 0 | CA41: 0 | CB41: 0 | CC41: 0 | CD41: 0 | CE41: 0 | CF41: 0 | CG41: 0 | CH41: 0 | CI41: 0 | CJ41: 0 | CK41: 0 | CO41: 0 | CP41: 0 | CQ41: 0 | CR41: 0 | CS41: 0 | CT41: 0 | CU41: 0 | CV41: =SUM(CS41:CU41) -> 0 | CW41: 0 | CX41: 0 | CY41: 0 | CZ41: =SUM(CW41:CY41) -> 0 | DA41: 0 | DB41: 0 | DC41: 0 | DD41: =SUM(DA41:DC41) -> 0 | DH41: =SUM(DE41:DG41) -> 0 | DI41: =CV41+CZ41 -> 0 | DJ41: =CV41+CZ41+DD41 -> 0 | DK41: =DH41+DJ41 -> 0 | DL41: =CR41-DK41 -> 0 | DN41: =BY41-CR41 -> 0 | DP41: =BF41-BY41 -> 0 | DR41: =AM41-BE41 -> 0 | DT41: =C41-V41 -> 0
A42: 存貨盤損 | B42: ='2017 預算'!C41 -> 0 | C42: ='2017 預算'!F41 -> 0 | D42: ='2017 預算'!I41 -> 0 | E42: =SUM(B42:D42) -> 0 | F42: ='2017 預算'!O41 -> 0 | G42: ='2017 預算'!R41 -> 0 | H42: ='2017 預算'!U41 -> 0 | I42: =SUM(F42:H42) -> 0 | J42: ='2017 預算'!AA41 -> 0 | K42: ='2017 預算'!AD41 -> 0 | L42: ='2017 預算'!AG41 -> 0 | M42: =SUM(J42:L42) -> 0 | N42: ='2017 預算'!AM41 -> 0 | O42: ='2017 預算'!AP41 -> 0 | P42: ='2017 預算'!AS41 -> 0 | Q42: =SUM(N42:P42) -> 0 | R42: =E42+I42 -> 0 | S42: =E42+I42+M42 -> 0 | T42: =E42+I42+M42+Q42 -> 0 | U42: 0 | V42: 0 | W42: 0 | X42: 0 | Y42: 0 | Z42: 0 | AA42: 0 | AB42: 0 | AC42: 0 | AD42: 0 | AE42: 0 | AF42: 0 | AG42: 0 | AH42: 0 | AI42: 0 | AJ42: 0 | AK42: 0 | AL42: 0 | AM42: 0 | AN42: 0 | AO42: 0 | AP42: 0 | AQ42: 0 | AR42: 0 | AS42: 0 | AT42: 0 | AU42: 0 | AV42: 0 | AW42: 0 | AX42: 0 | AY42: 0 | AZ42: 0 | BA42: 0 | BB42: 0 | BC42: 0 | BD42: 0 | BE42: 0 | BF42: 0 | BI42: 0 | BJ42: 0 | BK42: 0 | BN42: 0 | BR42: 0 | BV42: 0 | BW42: 0 | BX42: 0 | BY42: 0 | BZ42: 0 | CA42: 0 | CB42: 0 | CC42: 0 | CD42: 0 | CE42: 0 | CF42: 0 | CG42: 0 | CH42: 0 | CI42: 0 | CJ42: 0 | CK42: 0 | CO42: 0 | CP42: 0 | CQ42: 0 | CR42: 0 | CS42: 0 | CT42: 0 | CU42: 0 | CV42: =SUM(CS42:CU42) -> 0 | CW42: 0 | CX42: 0 | CY42: 0 | CZ42: =SUM(CW42:CY42) -> 0 | DA42: 0 | DB42: 0 | DC42: 0 | DD42: =SUM(DA42:DC42) -> 0 | DH42: =SUM(DE42:DG42) -> 0 | DI42: =CV42+CZ42 -> 0 | DJ42: =CV42+CZ42+DD42 -> 0 | DK42: =DH42+DJ42 -> 0 | DL42: =CR42-DK42 -> 0 | DN42: =BY42-CR42 -> 0 | DP42: =BF42-BY42 -> 0 | DR42: =AM42-BE42 -> 0 | DT42: =C42-V42 -> 0
A43: 兌換損失 | B43: ='2017 預算'!C42 -> 5599361 | C43: ='2017 預算'!F42 -> 4644987 | D43: ='2017 預算'!I42 -> 3836889 | E43: =SUM(B43:D43) -> 14081237 | F43: ='2017 預算'!O42 -> 3895955 | G43: ='2017 預算'!R42 -> 2165183 | H43: ='2017 預算'!U42 -> 1755192 | I43: =SUM(F43:H43) -> 7816330 | J43: ='2017 預算'!AA42 -> 2260251 | K43: ='2017 預算'!AD42 -> 704027 | L43: ='2017 預算'!AG42 -> 0 | M43: =SUM(J43:L43) -> 2964278 | N43: ='2017 預算'!AM42 -> 0 | O43: ='2017 預算'!AP42 -> 0 | P43: ='2017 預算'!AS42 -> 0 | Q43: =SUM(N43:P43) -> 0 | R43: =E43+I43 -> 21897567 | S43: =E43+I43+M43 -> 24861845 | T43: =E43+I43+M43+Q43 -> 24861845 | U43: 19615 | V43: 2502663 | W43: 4209814 | X43: 6732092 | Y43: 2443825 | Z43: 608760 | AA43: 2095018 | AB43: 5147603 | AC43: 1708754 | AD43: 2330212 | AE43: 2630390 | AF43: 6669356 | AG43: 666357 | AH43: 592629 | AI43: 807763 | AJ43: 2066749 | AK43: 11879695 | AL43: 18549051 | AM43: 20615800 | AN43: 2780615 | AO43: 1118466 | AP43: 997749 | AQ43: 4896830 | AR43: 2473689 | AS43: 1892170 | AT43: 1041341 | AU43: 5407200 | AV43: 649885 | AW43: 2326972 | AX43: 2698283 | AY43: 5675140 | AZ43: 3439049 | BA43: 987461 | BB43: 98328 | BC43: 4524838 | BD43: 10304030 | BE43: 15979170 | BF43: 20504008 | BG43: 17319 | BH43: 1221200 | BI43: 373865 | BJ43: 1612384 | BK43: 1029079 | BL43: 532553 | BM43: 791422 | BN43: 2353054 | BO43: 317277 | BP43: 479471 | BQ43: 325014 | BR43: 1121762 | BS43: 1275906 | BT43: 37088 | BU43: 682840 | BV43: 1995834 | BW43: 3965438 | BX43: 5087200 | BY43: 7083034 | BZ43: 189678 | CA43: 1531918 | CB43: 219132 | CC43: 1940728 | CD43: 1677255 | CE43: 957140 | CF43: 777360 | CG43: 3411755 | CH43: 259142 | CI43: 284834 | CJ43: 1076333 | CK43: 1620309 | CL43: 1146111 | CM43: 480583 | CN43: 74132 | CO43: 1700826 | CP43: 5352483 | CQ43: 6972792 | CR43: 8673618 | CS43: 2007504 | CT43: 1520436 | CU43: 612724 | CV43: =SUM(CS43:CU43) -> 4140664 | CW43: 1406207 | CX43: 769310 | CY43: 1105201 | CZ43: =SUM(CW43:CY43) -> 3280718 | DA43: 302045 | DB43: 368375 | DC43: 1121176 | DD43: =SUM(DA43:DC43) -> 1791596 | DE43: 1223402 | DF43: 320402 | DG43: 250230 | DH43: =SUM(DE43:DG43) -> 1794034 | DI43: =CV43+CZ43 -> 7421382 | DJ43: =CV43+CZ43+DD43 -> 9212978 | DK43: =DH43+DJ43 -> 11007012 | DL43: =CR43-DK43 -> -2333394 | DM43: =DL43/DK43 -> -0.21199159 | DN43: =BY43-CR43 -> -1590584 | DO43: =BY43/CR43-1 -> -0.18338184 | DP43: =BF43-BY43 -> 13420974 | DQ43: =DP43/BY43 -> 1.8948058 | DR43: =AM43-BE43 -> 4636630 | DS43: =DR43/BF43 -> 0.22613286 | DT43: =C43-V43 -> 2142324 | DU43: =DT43/BH43 -> 1.7542778
A44: 財務費用 | B44: ='2017 預算'!C43 -> 368283 | C44: ='2017 預算'!F43 -> 252106 | D44: ='2017 預算'!I43 -> 140305 | E44: =SUM(B44:D44) -> 760694 | F44: ='2017 預算'!O43 -> 118770 | G44: ='2017 預算'!R43 -> 230411 | H44: ='2017 預算'!U43 -> 277435 | I44: =SUM(F44:H44) -> 626616 | J44: ='2017 預算'!AA43 -> 178264 | K44: ='2017 預算'!AD43 -> 416667 | L44: ='2017 預算'!AG43 -> 0 | M44: =SUM(J44:L44) -> 594931 | N44: ='2017 預算'!AM43 -> 0 | O44: ='2017 預算'!AP43 -> 0 | P44: ='2017 預算'!AS43 -> 0 | Q44: =SUM(N44:P44) -> 0 | R44: =E44+I44 -> 1387310 | S44: =E44+I44+M44 -> 1982241 | T44: =E44+I44+M44+Q44 -> 1982241 | U44: 202020 | V44: 134886 | W44: 236582 | X44: 573488 | Y44: 144646 | Z44: 172593 | AA44: 272892 | AB44: 590131 | AC44: 234369 | AD44: 147568 | AE44: 145610 | AF44: 527547 | AG44: 223107 | AH44: 293346 | AI44: 198750 | AJ44: 715203 | AK44: 1163619 | AL44: 1691166 | AM44: 2406369 | AN44: 53875 | AO44: 41285 | AP44: 266839 | AQ44: 361999 | AR44: 247053 | AS44: 164704 | AT44: 189360 | AU44: 601117 | AV44: 162011 | AW44: 86240 | AX44: 80408 | AY44: 328659 | AZ44: 133374 | BA44: 66607 | BB44: 200401 | BC44: 400382 | BD44: 963116 | BE44: 1291775 | BF44: 1692157 | BG44: 54579 | BH44: 80479 | BI44: 77281 | BJ44: 212339 | BK44: 61598 | BL44: 114405 | BM44: 143187 | BN44: 319190 | BO44: 221396 | BP44: 58806 | BQ44: 101358 | BR44: 381560 | BS44: 72996 | BT44: 57135 | BU44: 29357 | BV44: 159488 | BW44: 531529 | BX44: 913089 | BY44: 1072577 | BZ44: 130059 | CA44: 169680 | CB44: 97150 | CC44: 396889 | CD44: 99482 | CE44: 168683 | CF44: 120618 | CG44: 388783 | CH44: 115196 | CI44: 162767 | CJ44: 83171 | CK44: 361134 | CL44: 70915 | CM44: 47457 | CN44: 97345 | CO44: 215717 | CP44: 785672 | CQ44: 1146806 | CR44: 1362523 | CS44: 123728 | CT44: 78057 | CU44: 133736 | CV44: =SUM(CS44:CU44) -> 335521 | CW44: 126471 | CX44: 114013 | CY44: 59428 | CZ44: =SUM(CW44:CY44) -> 299912 | DA44: 137538 | DB44: 66884 | DC44: 73526 | DD44: =SUM(DA44:DC44) -> 277948 | DE44: 141683 | DF44: 107034 | DG44: 81456 | DH44: =SUM(DE44:DG44) -> 330173 | DI44: =CV44+CZ44 -> 635433 | DJ44: =CV44+CZ44+DD44 -> 913381 | DK44: =DH44+DJ44 -> 1243554 | DL44: =CR44-DK44 -> 118969 | DM44: =DL44/DK44 -> 0.095668544 | DN44: =BY44-CR44 -> -289946 | DO44: =BY44/CR44-1 -> -0.21280081 | DP44: =BF44-BY44 -> 619580 | DQ44: =DP44/BY44 -> 0.5776555 | DR44: =AM44-BE44 -> 1114594 | DS44: =DR44/BF44 -> 0.65868238 | DT44: =C44-V44 -> 117220 | DU44: =DT44/BH44 -> 1.456529
A45: 金融資產評價損失 | B45: ='2017 預算'!C44 -> 0 | C45: ='2017 預算'!F44 -> 0 | D45: ='2017 預算'!I44 -> 0 | E45: =SUM(B45:D45) -> 0 | F45: ='2017 預算'!O44 -> 0 | G45: ='2017 預算'!R44 -> 0 | H45: ='2017 預算'!U44 -> 0 | I45: =SUM(F45:H45) -> 0 | J45: ='2017 預算'!AA44 -> 0 | K45: ='2017 預算'!AD44 -> 0 | L45: ='2017 預算'!AG44 -> 0 | M45: =SUM(J45:L45) -> 0 | N45: ='2017 預算'!AM44 -> 0 | O45: ='2017 預算'!AP44 -> 0 | P45: ='2017 預算'!AS44 -> 0 | Q45: =SUM(N45:P45) -> 0 | R45: =E45+I45 -> 0 | S45: =E45+I45+M45 -> 0 | T45: =E45+I45+M45+Q45 -> 0 | U45: 0 | V45: 0 | W45: 0 | X45: 0 | Y45: 0 | Z45: 0 | AA45: 0 | AB45: 0 | AC45: 0 | AD45: 0 | AE45: 0 | AF45: 0 | AG45: 0 | AH45: 0 | AI45: 0 | AJ45: 0 | AK45: 0 | AL45: 0 | AM45: 0 | AN45: 0 | AO45: 0 | AP45: 0 | AQ45: 0 | AR45: 0 | AS45: 0 | AT45: 0 | AU45: 0 | AV45: 0 | AW45: 0 | AX45: 0 | AY45: 0 | AZ45: 0 | BA45: 0 | BB45: 0 | BC45: 0 | BD45: 0 | BE45: 0 | BF45: 0 | BI45: 0 | BJ45: 0 | BK45: 0 | BN45: 0 | BR45: 0 | BV45: 0 | BW45: 0 | BX45: 0 | BY45: 0 | BZ45: 0 | CA45: 0 | CB45: 0 | CC45: 0 | CD45: 0 | CE45: 0 | CF45: 0 | CG45: 0 | CH45: 0 | CI45: 0 | CJ45: 0 | CK45: 0 | CO45: 0 | CP45: 0 | CQ45: 0 | CR45: 0 | CS45: 0 | CT45: 0 | CU45: 0 | CV45: =SUM(CS45:CU45) -> 0 | CW45: 0 | CX45: 0 | CY45: 0 | CZ45: =SUM(CW45:CY45) -> 0 | DA45: 0 | DB45: 0 | DC45: 0 | DD45: =SUM(DA45:DC45) -> 0 | DH45: =SUM(DE45:DG45) -> 0 | DI45: =CV45+CZ45 -> 0 | DJ45: =CV45+CZ45+DD45 -> 0 | DK45: =DH45+DJ45 -> 0 | DL45: =CR45-DK45 -> 0 | DN45: =BY45-CR45 -> 0 | DP45: =BF45-BY45 -> 0 | DR45: =AM45-BE45 -> 0 | DT45: =C45-V45 -> 0
A46: 什項支出 | B46: ='2017 預算'!C45 -> 0 | C46: ='2017 預算'!F45 -> 0 | D46: ='2017 預算'!I45 -> 0 | E46: =SUM(B46:D46) -> 0 | F46: ='2017 預算'!O45 -> 133996 | G46: ='2017 預算'!R45 -> 0 | H46: ='2017 預算'!U45 -> 0 | I46: =SUM(F46:H46) -> 133996 | J46: ='2017 預算'!AA45 -> 0 | K46: ='2017 預算'!AD45 -> 0 | L46: ='2017 預算'!AG45 -> 0 | M46: =SUM(J46:L46) -> 0 | N46: ='2017 預算'!AM45 -> 0 | O46: ='2017 預算'!AP45 -> 0 | P46: ='2017 預算'!AS45 -> 0 | Q46: =SUM(N46:P46) -> 0 | R46: =E46+I46 -> 133996 | S46: =E46+I46+M46 -> 133996 | T46: =E46+I46+M46+Q46 -> 133996 | U46: 0 | V46: 0 | W46: 0 | X46: 0 | Y46: 0 | Z46: 0 | AA46: 0 | AB46: 0 | AC46: 0 | AD46: 0 | AE46: 0 | AF46: 0 | AG46: 0 | AH46: 0 | AI46: =19969-19969 -> 0 | AJ46: =19969-19969 -> 0 | AK46: 0 | AL46: 0 | AM46: =19969-19969 -> 0 | AN46: 0 | AO46: 0 | AP46: 0 | AQ46: 0 | AR46: 0 | AS46: 0 | AT46: 0 | AU46: 0 | AV46: 0 | AW46: 0 | AX46: 0 | AY46: 0 | AZ46: 0 | BA46: 0 | BB46: 0 | BC46: 0 | BD46: 0 | BE46: 0 | BF46: 0 | BI46: 0 | BJ46: 0 | BK46: 0 | BN46: 0 | BR46: 0 | BU46: 0 | BV46: 0 | BW46: 0 | BX46: 0 | BY46: 0 | BZ46: 0 | CA46: 0 | CB46: 3540 | CC46: 3540 | CD46: 280 | CE46: 0 | CF46: 0 | CG46: 280 | CH46: 0 | CI46: 0 | CJ46: 0 | CK46: 0 | CO46: 0 | CP46: 3820 | CQ46: 3820 | CR46: 3820 | CS46: 0 | CT46: 0 | CU46: 0 | CV46: =SUM(CS46:CU46) -> 0 | CW46: 0 | CX46: 0 | CY46: 0 | CZ46: =SUM(CW46:CY46) -> 0 | DA46: 0 | DB46: 0 | DC46: 0 | DD46: =SUM(DA46:DC46) -> 0 | DH46: =SUM(DE46:DG46) -> 0 | DI46: =CV46+CZ46 -> 0 | DJ46: =CV46+CZ46+DD46 -> 0 | DK46: =DH46+DJ46 -> 0 | DL46: =CR46-DK46 -> 3820 | DN46: =BY46-CR46 -> -3820 | DO46: =BY46/CR46-1 -> -1 | DP46: =BF46-BY46 -> 0 | DR46: =AM46-BE46 -> 0 | DT46: =C46-V46 -> 0
A47: 小計 | B47: =SUM(B38:B46) -> 5993945 | C47: =SUM(C38:C46) -> 4971920 | D47: =SUM(D38:D46) -> 4047156 | E47: =SUM(B47:D47) -> 15013021 | F47: =SUM(F38:F46) -> 4242709 | G47: =SUM(G38:G46) -> 2487538 | H47: =SUM(H38:H46) -> 2145488 | I47: =SUM(I38:I46) -> 8875735 | J47: =SUM(J38:J46) -> 2535267 | K47: =SUM(K38:K46) -> 1238320 | L47: =SUM(L38:L46) -> 0 | M47: =SUM(M38:M46) -> 3773587 | ... S47: =SUM(S38:S46) -> 27662343 | T47: =E47+I47+M47+Q47 -> 27662343 | U47: 247579 | V47: 2637549 | W47: 4446396 | X47: 7331524 | Y47: 2588471 | Z47: 804901 | AA47: 2431586 | AB47: 5824958 | AC47: 2032118 | AD47: 2539935 | AE47: 2806610 | AF47: 7378663 | AG47: 913858 | AH47: 887538 | AI47: =SUM(AI38:AI46) -> 1096153 | AJ47: =SUM(AJ38:AJ46) -> 2897549 | AK47: =SUM(AK38:AK46) -> 13156482 | AL47: =SUM(AL38:AL46) -> 20535145 | AM47: =SUM(AM38:AM46) -> 23432694 | AN47: 2834490 | AO47: 1159751 | AP47: 1279163 | AQ47: 5273404 | AR47: 2720742 | AS47: 2056874 | AT47: 1230701 | AU47: 6008317 | AV47: 827512 | AW47: 2413212 | AX47: 2793266 | AY47: 6033990 | AZ47: 3662998 | BA47: 1105394 | BB47: 335896 | BC47: 5104288 | BD47: 11281721 | BE47: 17315711 | BF47: 22419999 | BG47: 71898 | BH47: 1301679 | BI47: 451146 | BJ47: 1824723 | BK47: 1090677 | BL47: 646958 | BM47: 934609 | BN47: 2672244 | BO47: 538673 | BP47: 538277 | BQ47: 426372 | BR47: 1503322 | BS47: 1348902 | BT47: 94223 | BU47: 712197 | BV47: 2155322 | BW47: 4496967 | BX47: 6000289 | BY47: 8155611 | BZ47: 859737 | CA47: 1701598 | CB47: 319822 | CC47: 2881157 | CD47: 1777017 | CE47: 1125823 | CF47: 897978 | CG47: 3800818 | CH47: 374338 | CI47: 447601 | CJ47: 1159504 | CK47: 1981443 | CL47: 1217026 | CM47: 528040 | CN47: 171477 | CO47: 1916543 | CP47: 6681975 | CQ47: 8663418 | CR47: 10579961 | CS47: 2131232 | CT47: 1600205 | CU47: =SUM(CU38:CU46) -> 746460 | CV47: =SUM(CS47:CU47) -> 4477897 | CW47: 1532678 | CX47: 883323 | CY47: =SUM(CY38:CY46) -> 1164629 | CZ47: =SUM(CW47:CY47) -> 3580630 | DA47: =SUM(DA38:DA46) -> 439583 | DB47: =SUM(DB38:DB46) -> 435259 | DC47: =SUM(DC38:DC46) -> 1194702 | DD47: =SUM(DA47:DC47) -> 2069544 | DE47: =SUM(DE38:DE46) -> 1365085 | DF47: =SUM(DF38:DF46) -> 427436 | DG47: =SUM(DG38:DG46) -> 331686 | DH47: =SUM(DE47:DG47) -> 2124207 | DI47: =CV47+CZ47 -> 8058527 | DJ47: =CV47+CZ47+DD47 -> 10128071 | DK47: =DH47+DJ47 -> 12252278 | DL47: =CR47-DK47 -> -1672317 | DM47: =DL47/DK47 -> -0.13649029 | DN47: =BY47-CR47 -> -2424350 | DO47: =BY47/CR47-1 -> -0.22914546 | DP47: =BF47-BY47 -> 14264388 | DQ47: =DP47/BY47 -> 1.7490275 | DR47: =AM47-BE47 -> 6116983 | DS47: =DR47/BF47 -> 0.27283601 | DT47: =C47-V47 -> 2334371 | DU47: =DT47/BH47 -> 1.7933538
A48: 營業外收入及費用合計 | B48: =B36-B47 -> -4980453 | C48: =C36-C47 -> -3981090 | D48: =D36-D47 -> -1045247 | E48: =SUM(B48:D48) -> -10006790 | F48: =F36-F47 -> -351088 | G48: =G36-G47 -> -276151 | H48: =H36-H47 -> 1778535 | I48: =I36-I47 -> 1151296 | J48: =J36-J47 -> -1337179 | K48: =K36-K47 -> -232899 | L48: =L36-L47 -> 0 | M48: =M36-M47 -> -1570078 | ... S48: =S36-S47 -> -10425572 | T48: =E48+I48+M48+Q48 -> -10425572 | U48: 2764245 | V48: -494188 | W48: -3464321 | X48: -1194264 | Y48: 265464 | Z48: 1248753 | AA48: -1437590 | AB48: 76627 | AC48: -1942269 | AD48: -705834 | AE48: -1395942 | AF48: -4044045 | AG48: 878886 | AH48: 1202546 | AI48: =AI36-AI47 -> 6257471 | AJ48: =AJ36-AJ47 -> 8338903 | AK48: =AK36-AK47 -> -1117637 | AL48: =AL36-AL47 -> -5161682 | AM48: =AM36-AM47 -> 3177221 | AN48: -731029 | AO48: 200992 | AP48: -617814 | AQ48: -1147851 | AR48: -1475561 | AS48: 213591 | AT48: 462319 | AU48: -799651 | AV48: 1883326 | AW48: 2961238 | AX48: 1218511 | AY48: 6063075 | AZ48: -1833368 | BA48: 509656 | BB48: 819943 | BC48: -503769 | BD48: -1947502 | BE48: 4115573 | BF48: 3611804 | BG48: 1277447 | BH48: 137854 | BI48: 543861 | BJ48: 1959162 | BK48: -510983 | BL48: -367957 | BM48: 201298 | BN48: -677642 | BO48: 304042 | BP48: 314792 | BQ48: 1475494 | BR48: 2094328 | BS48: 142968 | BT48: 1323574 | BU48: 1771446 | BV48: 3237988 | BW48: 1281520 | BX48: 3375848 | BY48: 6613836 | BZ48: 806284 | CA48: 118910 | CB48: 493188 | CC48: 1418382 | CD48: -332172 | CE48: 1280238 | CF48: 393020 | CG48: 1341086 | CH48: 54326 | CI48: -69695 | CJ48: -834293 | CK48: -849662 | CL48: -214609 | CM48: 811630 | CN48: 939239 | CO48: 1536260 | CP48: 2759468 | CQ48: 1909806 | CR48: 3446066 | CS48: =CS36-CS47 -> -1043834 | CT48: =CT36-CT47 -> -111685 | CU48: =CU36-CU47 -> 405708 | CV48: =CV36-CV47 -> -749811 | CW48: =CW36-CW47 -> -315243 | CX48: =CX36-CX47 -> 1160229 | CY48: =CY36-CY47 -> 260398 | CZ48: =CZ36-CZ47 -> 1105384 | ... DL48: =DL36-DL47 -> 3564027 | DM48: =DL48/DK48 -> -30.213604 | DN48: =BY48-CR48 -> 3167770 | DO48: =DN48/CR48 -> 0.91924241 | DP48: =BF48-BY48 -> -3002032 | DQ48: =DP48/BY48 -> -0.45390179 | DR48: =AM48-BE48 -> -938352 | DS48: =DR48/BF48 -> -0.25980147 | DT48: =C48-V48 -> -3486902 | DU48: =DT48/BH48 -> -25.294166
A49: ▲ 稅前損益： | B49: =B23+B48 -> -7756173 | C49: =C23+C48 -> -10972456 | D49: =D23+D48 -> 2058472 | E49: =SUM(B49:D49) -> -16670157 | F49: =F23+F48 -> -900330 | G49: =G23+G48 -> -1699644.2 | H49: =H23+H48 -> 4012267 | I49: =I23+I48 -> 1412292.8 | J49: =J23+J48 -> -645828 | K49: =K23+K48 -> 2289840 | L49: =L23+L48 -> 0 | M49: =M23+M48 -> 1644012 | ... S49: =S23+S48 -> -13613852 | T49: =E49+I49+M49+Q49 -> -13613852 | U49: 1340320 | V49: -5951955 | W49: 5471117 | X49: 859482 | Y49: -982052 | Z49: 7682512 | AA49: 4281978 | AB49: 10982438 | AC49: -2306012 | AD49: 4751389 | AE49: 849782 | AF49: 3295159 | AG49: -936406 | AH49: 6261928 | AI49: =AI23+AI48 -> -15771174 | AJ49: =AJ23+AJ48 -> 19554348 | AK49: =AK23+AK48 -> 11841920 | AL49: =AL23+AL48 -> 15137079 | AM49: =AM23+AM48 -> 34691427 | AN49: -3259545 | AO49: -5835432 | AP49: 514164 | AQ49: -8580813 | AR49: -1215611 | AS49: -1704015 | AT49: -2115097 | AU49: -5034723 | AV49: -19900900 | AW49: -1600378 | AX49: -951099 | AY49: -22452377 | AZ49: -7138305 | BA49: -4221367 | BB49: 17394372 | BC49: 6034700 | BD49: -13615536 | BE49: -36067913 | BF49: -30033213 | BG49: 799668 | BH49: -4723163 | BI49: 417168 | BJ49: -3506327 | BK49: -3784642 | BL49: 1689557 | BM49: -629068 | BN49: -2724153 | BO49: 852314 | BP49: 147850 | BQ49: 1982699 | BR49: 2982863 | BS49: -3793270 | BT49: -2944954 | BU49: 10170528 | BV49: 3432304 | BW49: -6230480 | BX49: -3247617 | BY49: 184687 | BZ49: 4917080 | CA49: -1737956 | CB49: 2893050 | CC49: 6072174 | CD49: 832922 | CE49: -564086 | CF49: 2816298 | CG49: 3085134 | CH49: -39781 | CI49: 511478 | CJ49: -5513513 | CK49: -5041816 | CL49: -9526836 | CM49: -645106 | CN49: 6249226 | CO49: -3922716 | CP49: 9157308 | CQ49: 4115492 | CR49: 192776 | CS49: -5469987 | CT49: -851690 | CU49: =CU23+CU36-CU47 -> -8767222 | CV49: =SUM(CS49:CU49) -> -15088899 | CW49: -1628004 | CX49: -1204367 | CY49: =CY23+CY36-CY47 -> -13289118 | CZ49: =SUM(CW49:CY49) -> -16121489 | DA49: =DA23+DA36-DA47 -> -3432576 | DB49: =DB23+DB36-DB47 -> -12303728 | DC49: =DC23+DC36-DC47 -> -17652798 | DD49: =SUM(DA49:DC49) -> -33389102 | DE49: =DE23+DE36-DE47 -> -17313925 | DF49: =DF23+DF36-DF47 -> -10595577 | DG49: =DG23+DG36-DG47 -> -21803 | DH49: =SUM(DE49:DG49) -> -27931305 | DI49: =CV49+CZ49 -> -31210388 | DJ49: =CV49+CZ49+DD49 -> -64599490 | DK49: =DH49+DJ49 -> -92530795 | DL49: =CR49-DK49 -> 92723571 | DM49: =DL49/DK49 -> -1.0020834 | DN49: =BY49-CR49 -> -8089 | DO49: =DN49/CR49 -> -0.041960618 | DP49: =BF49-BY49 -> -30217900 | DQ49: =DP49/BY49 -> -163.61682 | DR49: =AM49-BE49 -> 70759340 | DS49: =DR49/BF49 -> -2.3560363 | DT49: =C49-V49 -> -5020501 | DU49: =DT49/BH49 -> 1.0629532
A50: 存貨跌價損失成本 | B50: =IS明細!D77 -> 2874749 | C50: =IS明細!F77 -> 2763471 | D50: =IS明細!H77 -> -7456555 | E50: =SUM(B50:D50) -> -1818335 | F50: =IS明細!J77 -> -591918 | G50: =IS明細!L77 -> 1054460 | H50: =IS明細!N77 -> -1470722 | I50: =SUM(F50:H50) -> -1008180 | J50: =IS明細!P77 -> -2031582 | K50: =IS明細!R77 -> 23984 | L50: =IS明細!T77 -> 0 | M50: =SUM(J50,K50,L50) -> -2007598 | N50: =IS明細!V77 -> 0 | O50: =IS明細!X77 -> 0 | P50: =IS明細!Z77 -> 0 | Q50: =SUM(N50,O50,P50) -> 0 | R50: =E50+I50 -> -2826515 | S50: =E50+I50+M50 -> -4834113 | T50: =E50+I50+M50+Q50 -> -4834113 | U50: 18009 | V50: 3394765 | W50: -247668 | X50: 3165106 | Y50: -550181 | Z50: -3751573 | AA50: -1121731 | AB50: -5423485 | AC50: 1930469 | AD50: -3321881 | AE50: -248102 | AF50: -1639514 | AG50: 1489805 | AH50: -4152418 | AI50: -1597662 | AJ50: -4260275 | AK50: -2258379 | AL50: -3897893 | AM50: -8158168 | AN50: 679485 | AO50: 1557982 | AP50: 1944212 | AQ50: 4181679 | AR50: -1335008 | AS50: -1358656 | AT50: 545425 | AU50: -2148239 | AV50: 889114 | AW50: 2202228 | AX50: 1496218 | AY50: 4587560 | AZ50: 3145858 | BA50: 996953 | BB50: -7750654 | BC50: -3607843 | BD50: 2033440 | BE50: 6621000 | BF50: 3013157 | BG50: -368213 | BH50: 2682174 | BI50: 554797 | BJ50: 2868758 | BK50: 185823 | BL50: -370904 | BM50: 2984510 | BN50: 2799429 | BO50: -487879 | BP50: 622107 | BQ50: -791857 | BR50: -657629 | BS50: 619227 | BT50: 2238761 | BU50: -4631568 | BV50: -1773580 | BW50: 5668187 | BX50: 5010558 | BY50: 3236978 | BZ50: 249599 | CA50: 449900 | CB50: -1549228 | CC50: -849729 | CD50: 908426 | CE50: 2313514 | CF50: 70744 | CG50: 3292684 | CH50: 538753 | CI50: -855830 | CJ50: 3645917 | CK50: 3328840 | CL50: 5848692 | CM50: 1133280 | CN50: -2730923 | CO50: 4251049 | CP50: 2442955 | CQ50: 5771795 | CR50: 10022844 | DK50: -1970062 | DL50: =CR50-DK50 -> 11992906 | DM50: =DL50/DK50 -> -6.087578 | DN50: =BY50-CR50 -> -6785866 | DO50: =DN50/CR50 -> -0.67703997 | DP50: =BF50-BY50 -> -223821 | DQ50: =DP50/BY50 -> -0.069145048 | DR50: =AM50-BE50 -> -14779168 | DS50: =DR50/BF50 -> -4.9048782 | DT50: =C50-V50 -> -631294 | DU50: =DT50/BH50 -> -0.23536653

Sheet 2017 預算
A1: 賀毅科技股份有限公司
A2: 預計損益表
A3: 期間：2017
B5: Jan | E5: Feb | H5: Mar | K5: Q1 | N5: Apr | Q5: May | T5: Jun | W5: Q2 | Z5: Jul | AC5: Aug | AF5: Sep | AI5: Q3 | AL5: Oct | AO5: Nov | AR5: Dec | AU5: Q4 | AX5: 1~12
B6: Forecast | C6: Actual | D6: 月逹成率 | E6: Forecast | F6: Actual | G6: 月逹成率 | H6: Forecast | I6: Actual | J6: 月逹成率 | K6: Forecast | L6: Actual | M6: 季逹成率 | N6: Forecast | O6: Actual | P6: 月逹成率 | Q6: Forecast | R6: Actual | S6: 月逹成率 | T6: Forecast | U6: Actual | V6: 月逹成率 | W6: Forecast | X6: Actual | Y6: 季逹成率 | Z6: Forecast | AA6: Actual | AB6: 月逹成率 | AC6: Forecast | AD6: Actual | AE6: 月逹成率 | AF6: Forecast | AG6: Actual | AH6: 月逹成率 | AI6: Forecast | AJ6: Actual | AK6: 季逹成率 | AL6: Forecast | AM6: Actual | AN6: 月逹成率 | AO6: Forecast | AP6: Actual | AQ6: 月逹成率 | AR6: Forecast | AS6: Actual | AT6: 月逹成率 | AU6: Forecast | AV6: Actual | AW6: 季逹成率 | AX6: Forecast | AY6: Actual | AZ6: 年度逹成率
A7: 營業收入
A8: POS BU1 | B8: 16500000 | C8: 4501975 | D8: =C8/B8 -> 0.27284697 | E8: 16500000 | F8: 4505830 | G8: =F8/E8 -> 0.27308061 | H8: 16500000 | I8: 28499391 | J8: =I8/H8 -> 1.7272358 | K8: =B8+E8+H8 -> 49500000 | L8: =C8+F8+I8 -> 37507196 | M8: =L8/K8 -> 0.75772113 | N8: 16500000 | O8: 4764667 | P8: =O8/N8 -> 0.2887677 | Q8: 16500000 | R8: 12977409 | S8: =R8/Q8 -> 0.78650962 | T8: 16500000 | U8: 14460790 | V8: =U8/T8 -> 0.87641152 | W8: =N8+Q8+T8 -> 49500000 | X8: =O8+R8+U8 -> 32202866 | Y8: =X8/W8 -> 0.65056294 | Z8: 20166667 | AA8: 5214450 | AB8: =AA8/Z8 -> 0.25856776 | AC8: 20166667 | AD8: 9660426 | AE8: =AD8/AC8 -> 0.47902938 | AF8: 20166666 | AG8: 0 | AH8: =AG8/AF8 -> 0 | AI8: =Z8+AC8+AF8 -> 60500000 | AJ8: =AA8+AD8+AG8 -> 14874876 | AK8: =AJ8/AI8 -> 0.24586572 | AL8: 20166666 | AM8: 0 | AN8: =AM8/AL8 -> 0 | AO8: 20166667 | AP8: 0 | AQ8: =AP8/AO8 -> 0 | AR8: 20166667 | AS8: 0 | AT8: =AS8/AR8 -> 0 | AU8: =AL8+AO8+AR8 -> 60500000 | AV8: =AM8+AP8+AS8 -> 0 | AW8: =AV8/AU8 -> 0 | AX8: =K8+W8+AI8+AU8 -> 220000000 | AY8: =L8+X8+AJ8+AV8 -> 84584938 | AZ8: =AY8/AX8 -> 0.38447699
A9: POS BU2 | B9: 0 | C9: 0 | D9: =C9/B9 -> #DIV/0! | E9: 0 | F9: 0 | G9: =F9/E9 -> #DIV/0! | H9: 0 | I9: 0 | J9: =I9/H9 -> #DIV/0! | K9: =B9+E9+H9 -> 0 | L9: =C9+F9+I9 -> 0 | M9: =L9/K9 -> #DIV/0! | N9: 0 | O9: 0 | P9: =O9/N9 -> #DIV/0! | Q9: 0 | R9: 0 | S9: =R9/Q9 -> #DIV/0! | T9: 0 | U9: 0 | V9: =U9/T9 -> #DIV/0! | W9: =N9+Q9+T9 -> 0 | X9: =O9+R9+U9 -> 0 | Y9: =X9/W9 -> #DIV/0! | Z9: 0 | AA9: 0 | AB9: =AA9/Z9 -> #DIV/0! | AC9: 0 | AD9: 0 | AE9: 0 | AF9: 0 | AG9: 0 | AH9: 0 | AI9: =Z9+AC9+AF9 -> 0 | AJ9: =AA9+AD9+AG9 -> 0 | AK9: =AJ9/AI9 -> #DIV/0! | AL9: 0 | AM9: 0 | AN9: =AM9/AL9 -> #DIV/0! | AO9: 0 | AP9: 0 | AQ9: =AP9/AO9 -> #DIV/0! | AR9: 0 | AS9: 0 | AT9: =AS9/AR9 -> #DIV/0! | AU9: =AL9+AO9+AR9 -> 0 | AV9: =AM9+AP9+AS9 -> 0 | AW9: =AV9/AU9 -> #DIV/0! | AX9: =K9+W9+AI9+AU9 -> 0 | AY9: =L9+X9+AJ9+AV9 -> 0 | AZ9: =AY9/AX9 -> #DIV/0!
A10: POS BU3-SE | B10: 55200000 | C10: 51078473 | D10: =C10/B10 -> 0.92533466 | E10: 55200000 | F10: 42980961 | G10: =F10/E10 -> 0.7786406 | H10: 55200000 | I10: 30561593 | J10: =I10/H10 -> 0.55365205 | K10: =B10+E10+H10 -> 165600000 | L10: =C10+F10+I10 -> 124621027 | M10: =L10/K10 -> 0.75254243 | N10: 55200000 | O10: 59543429 | P10: =O10/N10 -> 1.0786853 | Q10: 55200000 | R10: 37166163 | S10: =R10/Q10 -> 0.67330005 | T10: 55200000 | U10: 69467942 | V10: =U10/T10 -> 1.2584772 | W10: =N10+Q10+T10 -> 165600000 | X10: =O10+R10+U10 -> 166177534 | Y10: =X10/W10 -> 1.0034875 | Z10: 59800000 | AA10: 85004893 | AB10: =AA10/Z10 -> 1.4214865 | AC10: 59800000 | AD10: 65629388 | AE10: =AD10/AC10 -> 1.0974814 | AF10: 59800000 | AG10: 0 | AH10: =AG10/AF10 -> 0 | AI10: =Z10+AC10+AF10 -> 179400000 | AJ10: =AA10+AD10+AG10 -> 150634281 | AK10: =AJ10/AI10 -> 0.83965597 | AL10: 59800000 | AM10: 0 | AN10: =AM10/AL10 -> 0 | AO10: 59800000 | AP10: 0 | AQ10: =AP10/AO10 -> 0 | AR10: 59800000 | AS10: 0 | AT10: =AS10/AR10 -> 0 | AU10: =AL10+AO10+AR10 -> 179400000 | AV10: =AM10+AP10+AS10 -> 0 | AW10: =AV10/AU10 -> 0 | AX10: =K10+W10+AI10+AU10 -> 690000000 | AY10: =L10+X10+AJ10+AV10 -> 441432842 | AZ10: =AY10/AX10 -> 0.63975774
A11: POS BU4-AB | B11: 5250000 | C11: 4662544 | D11: =C11/B11 -> 0.88810362 | E11: 5250000 | F11: 5540923 | G11: =F11/E11 -> 1.0554139 | H11: 5250000 | I11: 4643464 | J11: =I11/H11 -> 0.88446933 | K11: =B11+E11+H11 -> 15750000 | L11: =C11+F11+I11 -> 14846931 | M11: =L11/K11 -> 0.94266229 | N11: 5250000 | O11: 3036598 | P11: =O11/N11 -> 0.57839962 | Q11: 5250000 | R11: 3094664 | S11: =R11/Q11 -> 0.58945981 | T11: 5250000 | U11: 3477355 | V11: =U11/T11 -> 0.66235333 | W11: =N11+Q11+T11 -> 15750000 | X11: =O11+R11+U11 -> 9608617 | Y11: =X11/W11 -> 0.61007092 | Z11: 9750000 | AA11: 8018284 | AB11: =AA11/Z11 -> 0.8223881 | AC11: 9750000 | AD11: 6841562 | AE11: =AD11/AC11 -> 0.70169867 | AF11: 9750000 | AG11: 0 | AH11: =AG11/AF11 -> 0 | AI11: =Z11+AC11+AF11 -> 29250000 | AJ11: =AA11+AD11+AG11 -> 14859846 | AK11: =AJ11/AI11 -> 0.50802892 | AL11: 9750000 | AM11: 0 | AN11: =AM11/AL11 -> 0 | AO11: 9750000 | AP11: 0 | AQ11: =AP11/AO11 -> 0 | AR11: 9750000 | AS11: 0 | AT11: =AS11/AR11 -> 0 | AU11: =AL11+AO11+AR11 -> 29250000 | AV11: =AM11+AP11+AS11 -> 0 | AW11: =AV11/AU11 -> 0 | AX11: =K11+W11+AI11+AU11 -> 90000000 | AY11: =L11+X11+AJ11+AV11 -> 39315394 | AZ11: =AY11/AX11 -> 0.43683771
A12: 維修收入 | B12: 0 | C12: =IS明細!D20 -> 3959 | E12: 0 | F12: =IS明細!F20 -> 43786 | H12: 0 | I12: =IS明細!H20 -> 27522 | K12: =B12+E12+H12 -> 0 | L12: =C12+F12+I12 -> 75267 | N12: 0 | O12: =IS明細!J20 -> 20986 | Q12: 0 | R12: =IS明細!L20 -> 43107 | T12: 0 | U12: =IS明細!N20 -> 81879 | W12: =N12+Q12+T12 -> 0 | X12: =O12+R12+U12 -> 145972 | Z12: 0 | AA12: =IS明細!P20 -> 3539 | AC12: 0 | AD12: =IS明細!R20 -> 3539 | AF12: 0 | AG12: =IS明細!T20 -> 0 | AI12: =Z12+AC12+AF12 -> 0 | AJ12: =AA12+AD12+AG12 -> 7078 | AL12: 0 | AM12: =IS明細!V20 -> 0 | AO12: 0 | AP12: =IS明細!X20 -> 0 | AR12: 0 | AS12: =IS明細!Z20 -> 0 | AU12: =AL12+AO12+AR12 -> 0 | AV12: =AM12+AP12+AS12 -> 0 | AX12: =K12+W12+AI12+AU12 -> 0 | AY12: =L12+X12+AJ12+AV12 -> 228317
A13: 營業收入合計 | B13: =SUM(B8:B12) -> 76950000 | C13: =SUM(C8:C12) -> 60246951 | D13: =C13/B13 -> 0.78293634 | E13: =SUM(E8:E12) -> 76950000 | F13: =SUM(F8:F12) -> 53071500 | G13: =F13/E13 -> 0.68968811 | H13: =SUM(H8:H12) -> 76950000 | I13: =SUM(I8:I12) -> 63731970 | J13: =I13/H13 -> 0.82822573 | K13: =SUM(K8:K12) -> 230850000 | L13: =SUM(L8:L12) -> 177050421 | M13: =L13/K13 -> 0.76695006 | N13: =SUM(N8:N12) -> 76950000 | O13: =SUM(O8:O12) -> 67365680 | P13: =O13/N13 -> 0.87544743 | Q13: =SUM(Q8:Q12) -> 76950000 | R13: =SUM(R8:R12) -> 53281343 | S13: =R13/Q13 -> 0.69241511 | T13: =SUM(T8:T12) -> 76950000 | U13: =SUM(U8:U12) -> 87487966 | V13: =U13/T13 -> 1.1369456 | W13: =SUM(W8:W12) -> 230850000 | X13: =SUM(X8:X12) -> 2.0813499e+08 | Y13: =X13/W13 -> 0.90160272 | Z13: =SUM(Z8:Z12) -> 89716667 | AA13: =SUM(AA8:AA12) -> 98241166 | AB13: =AA13/Z13 -> 1.0950158 | AC13: =SUM(AC8:AC12) -> 89716667 | AD13: =SUM(AD8:AD12) -> 82134915 | AE13: =AD13/AC13 -> 0.91549227 | AF13: =SUM(AF8:AF12) -> 89716666 | AG13: =SUM(AG8:AG12) -> 0 | AH13: =AG13/AF13 -> 0 | AI13: =SUM(AI8:AI12) -> 269150000 | AJ13: =SUM(AJ8:AJ12) -> 180376081 | AK13: =AJ13/AI13 -> 0.67016935 | AL13: =SUM(AL8:AL12) -> 89716666 | AM13: =SUM(AM8:AM12) -> 0 | AN13: =AM13/AL13 -> 0 | AO13: =SUM(AO8:AO12) -> 89716667 | AP13: =SUM(AP8:AP12) -> 0 | AQ13: =AP13/AO13 -> 0 | AR13: =SUM(AR8:AR12) -> 89716667 | AS13: =SUM(AS8:AS12) -> 0 | AT13: =AS13/AR13 -> 0 | AU13: =SUM(AU8:AU12) -> 269150000 | AV13: =SUM(AV8:AV12) -> 0 | AW13: =AV13/AU13 -> 0 | AX13: =SUM(AX8:AX12) -> 1000000000 | AY13: =SUM(AY8:AY12) -> 5.6556149e+08 | AZ13: =AY13/AX13 -> 0.56556149
A14: 營業成本 | B14: 63669000 | C14: =IS明細!D89 -> 55646869 | E14: 63669000 | F14: =IS明細!F89 -> 52320171 | H14: 63669000 | I14: =IS明細!H89 -> 53472402 | K14: =B14+E14+H14 -> 191007000 | L14: =C14+F14+I14 -> 161439442 | N14: 63669000 | O14: =IS明細!J89 -> 59947315 | Q14: 63669000 | R14: =IS明細!L89 -> 46938901 | T14: 63669000 | U14: =IS明細!N89 -> 76556480 | W14: =N14+Q14+T14 -> 191007000 | X14: =O14+R14+U14 -> 183442696 | Z14: 73390917 | AA14: =IS明細!P89 -> 87191630 | AC14: 73390917 | AD14: =IS明細!R89 -> 70950644 | AF14: 73390916 | AG14: =IS明細!T89 -> 0 | AI14: =Z14+AC14+AF14 -> 220172750 | AJ14: =AA14+AD14+AG14 -> 158142274 | AL14: 73390916 | AM14: =IS明細!V89 -> 0 | AO14: 73390917 | AP14: =IS明細!X89 -> 0 | AR14: 73390917 | AS14: =IS明細!Z89 -> 0 | AU14: =AL14+AO14+AR14 -> 220172750 | AV14: =AM14+AP14+AS14 -> 0 | AX14: =K14+W14+AI14+AU14 -> 822359500 | AY14: =L14+X14+AJ14+AV14 -> 503024412
A15: ▲ 營業毛利： | B15: =B13-B14 -> 13281000 | C15: =C13-C14 -> 4600082 | E15: =E13-E14 -> 13281000 | F15: =F13-F14 -> 751329 | H15: =H13-H14 -> 13281000 | I15: =I13-I14 -> 10259568 | K15: =K13-K14 -> 39843000 | L15: =L13-L14 -> 15610979 | N15: =N13-N14 -> 13281000 | O15: =O13-O14 -> 7418365 | Q15: =Q13-Q14 -> 13281000 | R15: =R13-R14 -> 6342441.8 | T15: =T13-T14 -> 13281000 | U15: =U13-U14 -> 10931486 | W15: =W13-W14 -> 39843000 | X15: =X13-X14 -> 24692293 | Z15: =Z13-Z14 -> 16325750 | AA15: =AA13-AA14 -> 11049536 | AC15: =AC13-AC14 -> 16325750 | AD15: =AD13-AD14 -> 11184271 | AF15: =AF13-AF14 -> 16325750 | AG15: =AG13-AG14 -> 0 | AI15: =AI13-AI14 -> 48977250 | AJ15: =AJ13-AJ14 -> 22233807 | AL15: =AL13-AL14 -> 16325750 | AM15: =AM13-AM14 -> 0 | AO15: =AO13-AO14 -> 16325750 | AP15: =AP13-AP14 -> 0 | AR15: =AR13-AR14 -> 16325750 | AS15: =AS13-AS14 -> 0 | AU15: =AU13-AU14 -> 48977250 | AV15: =AV13-AV14 -> 0 | AX15: =AX13-AX14 -> 177640500 | AY15: =AY13-AY14 -> 62537079
A16: 毛利率 | B16: =B15/B13 -> 0.17259259 | C16: =C15/C13 -> 0.076353773 | E16: =E15/E13 -> 0.17259259 | F16: =F15/F13 -> 0.01415692 | H16: =H15/H13 -> 0.17259259 | I16: =I15/I13 -> 0.16097993 | K16: =K15/K13 -> 0.17259259 | L16: =L15/L13 -> 0.088172504 | N16: =N15/N13 -> 0.17259259 | O16: =O15/O13 -> 0.11012084 | Q16: =Q15/Q13 -> 0.17259259 | R16: =R15/R13 -> 0.11903682 | T16: =T15/T13 -> 0.17259259 | U16: =U15/U13 -> 0.12494845 | W16: =W15/W13 -> 0.17259259 | X16: =X15/X13 -> 0.11863595 | Z16: =Z15/Z13 -> 0.18197009 | AA16: =AA15/AA13 -> 0.11247358 | AC16: =AC15/AC13 -> 0.18197009 | AD16: =AD15/AD13 -> 0.13616951 | AF16: =AF15/AF13 -> 0.18197009 | AG16: =AG15/AG13 -> #DIV/0! | AI16: =AI15/AI13 -> 0.18197009 | AJ16: =AJ15/AJ13 -> 0.12326361 | AL16: =AL15/AL13 -> 0.18197009 | AM16: =AM15/AM13 -> #DIV/0! | AO16: =AO15/AO13 -> 0.18197009 | AP16: =AP15/AP13 -> #DIV/0! | AR16: =AR15/AR13 -> 0.18197009 | AS16: =AS15/AS13 -> #DIV/0! | AU16: =AU15/AU13 -> 0.18197009 | AV16: =AV15/AV13 -> #DIV/0! | AX16: =AX15/AX13 -> 0.1776405 | AY16: =AY15/AY13 -> 0.11057521
A17: 營業費用
A18: 銷售費用 | B18: 2549980 | C18: =IS明細!D134 -> 2682181 | E18: 2549048 | F18: =IS明細!F134 -> 3034578 | H18: 2521014 | I18: =IS明細!H134 -> 2064980 | K18: =B18+E18+H18 -> 7620042 | L18: =C18+F18+I18 -> 7781739 | N18: 2549323 | O18: =IS明細!J134 -> 2828716 | Q18: 2340258 | R18: =IS明細!L134 -> 2899107 | T18: 2486213 | U18: =IS明細!N134 -> 3746561 | W18: =N18+Q18+T18 -> 7375794 | X18: =O18+R18+U18 -> 9474384 | Z18: 3998136 | AA18: =IS明細!P134 -> 3694714 | AC18: 4015058 | AD18: =IS明細!R134 -> 3586817 | AF18: 3978371 | AG18: =IS明細!T134 -> 0 | AI18: =Z18+AC18+AF18 -> 11991565 | AJ18: =AA18+AD18+AG18 -> 7281531 | AL18: 4015613 | AM18: =IS明細!V134 -> 0 | AO18: 4010829 | AP18: =IS明細!X134 -> 0 | AR18: 3983074 | AS18: =IS明細!Z134 -> 0 | AU18: =AL18+AO18+AR18 -> 12009516 | AV18: =AM18+AP18+AS18 -> 0 | AX18: =K18+W18+AI18+AU18 -> 38996917 | AY18: =L18+X18+AJ18+AV18 -> 24537654
A19: 管理費用 | B19: 1802773 | C19: =IS明細!D172 -> 1755765 | E19: 1803705 | F19: =IS明細!F172 -> 2075875 | H19: 1831739 | I19: =IS明細!H172 -> 1882646 | K19: =B19+E19+H19 -> 5438217 | L19: =C19+F19+I19 -> 5714286 | N19: 1803430 | O19: =IS明細!J172 -> 1770950 | Q19: 2012495 | R19: =IS明細!L172 -> 1871563 | T19: 1866540 | U19: =IS明細!N172 -> 1797661 | W19: =N19+Q19+T19 -> 5682465 | X19: =O19+R19+U19 -> 5440174 | Z19: 1821867 | AA19: =IS明細!P172 -> 3498119 | AC19: 1804945 | AD19: =IS明細!R172 -> 1755224 | AF19: 1841632 | AG19: =IS明細!T172 -> 0 | AI19: =Z19+AC19+AF19 -> 5468444 | AJ19: =AA19+AD19+AG19 -> 5253343 | AL19: 1804390 | AM19: =IS明細!V172 -> 0 | AO19: 1809174 | AP19: =IS明細!X172 -> 0 | AR19: 1836929 | AS19: =IS明細!Z172 -> 0 | AU19: =AL19+AO19+AR19 -> 5450493 | AV19: =AM19+AP19+AS19 -> 0 | AX19: =K19+W19+AI19+AU19 -> 22039619 | AY19: =L19+X19+AJ19+AV19 -> 16407803
A20: 研發費用 | B20: 3426247 | C20: =IS明細!D209 -> 2937856 | E20: 3426247 | F20: =IS明細!F209 -> 2632242 | H20: 3426247 | I20: =IS明細!H209 -> 3208223 | K20: =B20+E20+H20 -> 10278741 | L20: =C20+F20+I20 -> 8778321 | N20: 3426247 | O20: =IS明細!J209 -> 3367941 | Q20: 3426247 | R20: =IS明細!L209 -> 2995265 | T20: 3426247 | U20: =IS明細!N209 -> 3153532 | W20: =N20+Q20+T20 -> 10278741 | X20: =O20+R20+U20 -> 9516738 | Z20: 3408747 | AA20: =IS明細!P209 -> 3165352 | AC20: 3408747 | AD20: =IS明細!R209 -> 3319491 | AF20: 3408747 | AG20: =IS明細!T209 -> 0 | AI20: =Z20+AC20+AF20 -> 10226241 | AJ20: =AA20+AD20+AG20 -> 6484843 | AL20: 3408747 | AM20: =IS明細!V209 -> 0 | AO20: 3408747 | AP20: =IS明細!X209 -> 0 | AR20: 3408747 | AS20: =IS明細!Z209 -> 0 | AU20: =AL20+AO20+AR20 -> 10226241 | AV20: =AM20+AP20+AS20 -> 0 | AX20: =K20+W20+AI20+AU20 -> 41009964 | AY20: =L20+X20+AJ20+AV20 -> 24779902
A21: 營業費用合計 | B21: =B18+B19+B20 -> 7779000 | C21: =C18+C19+C20 -> 7375802 | E21: =E18+E19+E20 -> 7779000 | F21: =F18+F19+F20 -> 7742695 | H21: =H18+H19+H20 -> 7779000 | I21: =I18+I19+I20 -> 7155849 | K21: =SUM(K18:K20) -> 23337000 | L21: =SUM(L18:L20) -> 22274346 | N21: =SUM(N18:N20) -> 7779000 | O21: =SUM(O18:O20) -> 7967607 | Q21: =SUM(Q18:Q20) -> 7779000 | R21: =SUM(R18:R20) -> 7765935 | T21: =SUM(T18:T20) -> 7779000 | U21: =SUM(U18:U20) -> 8697754 | W21: =SUM(W18:W20) -> 23337000 | X21: =SUM(X18:X20) -> 24431296 | Z21: =SUM(Z18:Z20) -> 9228750 | AA21: =SUM(AA18:AA20) -> 10358185 | AC21: =SUM(AC18:AC20) -> 9228750 | AD21: =SUM(AD18:AD20) -> 8661532 | AF21: =SUM(AF18:AF20) -> 9228750 | AG21: =SUM(AG18:AG20) -> 0 | AI21: =SUM(AI18:AI20) -> 27686250 | AJ21: =SUM(AJ18:AJ20) -> 19019717 | AL21: =SUM(AL18:AL20) -> 9228750 | AM21: =SUM(AM18:AM20) -> 0 | AO21: =SUM(AO18:AO20) -> 9228750 | AP21: =SUM(AP18:AP20) -> 0 | AR21: =SUM(AR18:AR20) -> 9228750 | AS21: =SUM(AS18:AS20) -> 0 | AU21: =SUM(AU18:AU20) -> 27686250 | AV21: =SUM(AV18:AV20) -> 0 | AX21: =SUM(AX18:AX20) -> 102046500 | AY21: =SUM(AY18:AY20) -> 65725359
A22: ▲ 營業淨利： | B22: =B15-B21 -> 5502000 | C22: =C15-C21 -> -2775720 | E22: =E15-E21 -> 5502000 | F22: =F15-F21 -> -6991366 | H22: =H15-H21 -> 5502000 | I22: =I15-I21 -> 3103719 | K22: =K15-K21 -> 16506000 | L22: =L15-L21 -> -6663367 | N22: =N15-N21 -> 5502000 | O22: =O15-O21 -> -549242 | Q22: =Q15-Q21 -> 5502000 | R22: =R15-R21 -> -1423493.2 | T22: =T15-T21 -> 5502000 | U22: =U15-U21 -> 2233732 | W22: =W15-W21 -> 16506000 | X22: =X15-X21 -> 260996.77 | Z22: =Z15-Z21 -> 7097000 | AA22: =AA15-AA21 -> 691351 | AC22: =AC15-AC21 -> 7097000 | AD22: =AD15-AD21 -> 2522739 | AF22: =AF15-AF21 -> 7097000 | AG22: =AG15-AG21 -> 0 | AI22: =AI15-AI21 -> 21291000 | AJ22: =AJ15-AJ21 -> 3214090 | AL22: =AL15-AL21 -> 7097000 | AM22: =AM15-AM21 -> 0 | AO22: =AO15-AO21 -> 7097000 | AP22: =AP15-AP21 -> 0 | AR22: =AR15-AR21 -> 7097000 | AS22: =AS15-AS21 -> 0 | AU22: =AU15-AU21 -> 21291000 | AV22: =AV15-AV21 -> 0 | AX22: =AX15-AX21 -> 75594000 | AY22: =AY15-AY21 -> -3188280.2
A24: 營業外收入及利益
A25: 利息收入 | B25: 0 | C25: =IS明細!D214 -> 1250 | E25: 0 | F25: =IS明細!F214 -> 1250 | H25: 0 | I25: =IS明細!H214 -> 1250 | K25: =B25+E25+H25 -> 0 | L25: =C25+F25+I25 -> 3750 | N25: 0 | O25: =IS明細!J214 -> 1250 | Q25: 0 | R25: =IS明細!L214 -> 1250 | T25: 0 | U25: =IS明細!N214 -> 61835 | W25: =N25+Q25+T25 -> 0 | X25: =O25+R25+U25 -> 64335 | Z25: 0 | AA25: =IS明細!P214 -> 1250 | AC25: 0 | AD25: =IS明細!R214 -> 1250 | AF25: 0 | AG25: =IS明細!T214 -> 0 | AI25: =Z25+AC25+AF25 -> 0 | AJ25: =AA25+AD25+AG25 -> 2500 | AL25: 0 | AM25: =IS明細!V214 -> 0 | AO25: 0 | AP25: =IS明細!X214 -> 0 | AR25: 0 | AS25: =IS明細!Z214 -> 0 | AU25: =AL25+AO25+AR25 -> 0 | AV25: =AM25+AP25+AS25 -> 0 | AX25: =K25+W25+AI25+AU25 -> 0 | AY25: =L25+X25+AJ25+AV25 -> 70585
A26: 投資收益 | B26: 0 | C26: =IS明細!D218 -> 0 | E26: 0 | F26: =IS明細!F218 -> 0 | H26: 0 | I26: =IS明細!H218 -> 0 | K26: =B26+E26+H26 -> 0 | L26: =C26+F26+I26 -> 0 | N26: 0 | O26: =IS明細!J218 -> 0 | Q26: 0 | R26: =IS明細!L218 -> 0 | T26: 0 | U26: =IS明細!N218 -> 0 | W26: =N26+Q26+T26 -> 0 | X26: =O26+R26+U26 -> 0 | Z26: 0 | AA26: =IS明細!P218 -> 0 | AC26: 0 | AD26: =IS明細!R218 -> 0 | AF26: 0 | AG26: =IS明細!T218 -> 0 | AI26: =Z26+AC26+AF26 -> 0 | AJ26: =AA26+AD26+AG26 -> 0 | AL26: 0 | AM26: =IS明細!V218 -> 0 | AO26: 0 | AP26: =IS明細!X218 -> 0 | AR26: 0 | AS26: =IS明細!Z218 -> 0 | AU26: =AL26+AO26+AR26 -> 0 | AV26: =AM26+AP26+AS26 -> 0 | AX26: =K26+W26+AI26+AU26 -> 0 | AY26: =L26+X26+AJ26+AV26 -> 0
A27: 處分固定資產利益 | B27: 0 | C27: =IS明細!D221 -> 0 | E27: 0 | F27: =IS明細!F221 -> 0 | H27: 0 | I27: =IS明細!H221 -> 0 | K27: =B27+E27+H27 -> 0 | L27: =C27+F27+I27 -> 0 | N27: 0 | O27: =IS明細!J221 -> 0 | Q27: 0 | R27: =IS明細!L221 -> 0 | T27: 0 | U27: =IS明細!N221 -> 0 | W27: =N27+Q27+T27 -> 0 | X27: =O27+R27+U27 -> 0 | Z27: 0 | AA27: =IS明細!P221 -> 0 | AC27: 0 | AD27: =IS明細!R221 -> 0 | AF27: 0 | AG27: =IS明細!T221 -> 0 | AI27: =Z27+AC27+AF27 -> 0 | AJ27: =AA27+AD27+AG27 -> 0 | AL27: 0 | AM27: =IS明細!V221 -> 0 | AO27: 0 | AP27: =IS明細!X221 -> 0 | AR27: 0 | AS27: =IS明細!Z221 -> 0 | AU27: =AL27+AO27+AR27 -> 0 | AV27: =AM27+AP27+AS27 -> 0 | AX27: =K27+W27+AI27+AU27 -> 0 | AY27: =L27+X27+AJ27+AV27 -> 0
A28: 處分投資利益 | B28: 0 | C28: =IS明細!D222 -> 0 | E28: 0 | F28: =IS明細!F222 -> 0 | H28: 0 | I28: =IS明細!H222 -> 0 | K28: =B28+E28+H28 -> 0 | L28: =C28+F28+I28 -> 0 | N28: 0 | O28: =IS明細!J222 -> 0 | Q28: 0 | R28: =IS明細!L222 -> 0 | T28: 0 | U28: =IS明細!N222 -> 0 | W28: =N28+Q28+T28 -> 0 | X28: =O28+R28+U28 -> 0 | Z28: 0 | AA28: =IS明細!P222 -> 0 | AC28: 0 | AD28: =IS明細!R222 -> 0 | AF28: 0 | AG28: =IS明細!T222 -> 0 | AI28: =Z28+AC28+AF28 -> 0 | AJ28: =AA28+AD28+AG28 -> 0 | AL28: 0 | AM28: =IS明細!V222 -> 0 | AO28: 0 | AP28: =IS明細!X222 -> 0 | AR28: 0 | AS28: =IS明細!Z222 -> 0 | AU28: =AL28+AO28+AR28 -> 0 | AV28: =AM28+AP28+AS28 -> 0 | AX28: =K28+W28+AI28+AU28 -> 0 | AY28: =L28+X28+AJ28+AV28 -> 0
A29: 存貨盤盈 | B29: 0 | C29: =IS明細!D223 -> 0 | E29: 0 | F29: =IS明細!F223 -> 0 | H29: 0 | I29: =IS明細!H223 -> 0 | K29: =B29+E29+H29 -> 0 | L29: =C29+F29+I29 -> 0 | N29: 0 | O29: =IS明細!J223 -> 0 | Q29: 0 | R29: =IS明細!L223 -> 0 | T29: 0 | U29: =IS明細!N223 -> 0 | W29: =N29+Q29+T29 -> 0 | X29: =O29+R29+U29 -> 0 | Z29: 0 | AA29: =IS明細!P223 -> 0 | AC29: 0 | AD29: =IS明細!R223 -> 0 | AF29: 0 | AG29: =IS明細!T223 -> 0 | AI29: =Z29+AC29+AF29 -> 0 | AJ29: =AA29+AD29+AG29 -> 0 | AL29: 0 | AM29: =IS明細!V223 -> 0 | AO29: 0 | AP29: =IS明細!X223 -> 0 | AR29: 0 | AS29: =IS明細!Z223 -> 0 | AU29: =AL29+AO29+AR29 -> 0 | AV29: =AM29+AP29+AS29 -> 0 | AX29: =K29+W29+AI29+AU29 -> 0 | AY29: =L29+X29+AJ29+AV29 -> 0
A30: 兌換利益 | B30: 0 | C30: =IS明細!D229 -> 860624 | E30: 0 | F30: =IS明細!F229 -> 930103 | H30: 0 | I30: =IS明細!H229 -> 2946964 | K30: =B30+E30+H30 -> 0 | L30: =C30+F30+I30 -> 4737691 | N30: 0 | O30: =IS明細!J229 -> 3612795 | Q30: 0 | R30: =IS明細!L229 -> 1971131 | T30: 0 | U30: =IS明細!N229 -> 3773237 | W30: =N30+Q30+T30 -> 0 | X30: =O30+R30+U30 -> 9357163 | Z30: 0 | AA30: =IS明細!P229 -> 1126662 | AC30: 0 | AD30: =IS明細!R229 -> 739833 | AF30: 0 | AG30: =IS明細!T229 -> 0 | AI30: =Z30+AC30+AF30 -> 0 | AJ30: =AA30+AD30+AG30 -> 1866495 | AL30: 0 | AM30: =IS明細!V229 -> 0 | AO30: 0 | AP30: =IS明細!X229 -> 0 | AR30: 0 | AS30: =IS明細!Z229 -> 0 | AU30: =AL30+AO30+AR30 -> 0 | AV30: =AM30+AP30+AS30 -> 0 | AX30: =K30+W30+AI30+AU30 -> 0 | AY30: =L30+X30+AJ30+AV30 -> 15961349
A31: 租金收入 | B31: 0 | C31: =IS明細!D233 -> 0 | E31: 0 | F31: =IS明細!F233 -> 0 | H31: 0 | I31: =IS明細!H233 -> 0 | K31: =B31+E31+H31 -> 0 | L31: =C31+F31+I31 -> 0 | N31: 0 | O31: =IS明細!J233 -> 0 | Q31: 0 | R31: =IS明細!L233 -> 0 | T31: 0 | U31: =IS明細!N233 -> 0 | W31: =N31+Q31+T31 -> 0 | X31: =O31+R31+U31 -> 0 | Z31: 0 | AA31: =IS明細!P233 -> 0 | AC31: 0 | AD31: =IS明細!R233 -> 0 | AF31: 0 | AG31: =IS明細!T233 -> 0 | AI31: =Z31+AC31+AF31 -> 0 | AJ31: =AA31+AD31+AG31 -> 0 | AL31: 0 | AM31: =IS明細!V233 -> 0 | AO31: 0 | AP31: =IS明細!X233 -> 0 | AR31: 0 | AS31: =IS明細!Z233 -> 0 | AU31: =AL31+AO31+AR31 -> 0 | AV31: =AM31+AP31+AS31 -> 0 | AX31: =K31+W31+AI31+AU31 -> 0 | AY31: =L31+X31+AJ31+AV31 -> 0
A32: 金融資產評價利益 | B32: 0 | C32: =IS明細!D236 -> 0 | E32: 0 | F32: =IS明細!F236 -> 0 | H32: 0 | I32: =IS明細!H236 -> 0 | K32: =B32+E32+H32 -> 0 | L32: =C32+F32+I32 -> 0 | N32: 0 | O32: =IS明細!J236 -> 0 | Q32: 0 | R32: =IS明細!L236 -> 0 | T32: 0 | U32: =IS明細!N236 -> 0 | W32: =N32+Q32+T32 -> 0 | X32: =O32+R32+U32 -> 0 | Z32: 0 | AA32: =IS明細!P236 -> 0 | AC32: 0 | AD32: =IS明細!R236 -> 0 | AF32: 0 | AG32: =IS明細!T236 -> 0 | AI32: =Z32+AC32+AF32 -> 0 | AJ32: =AA32+AD32+AG32 -> 0 | AL32: 0 | AM32: =IS明細!V236 -> 0 | AO32: 0 | AP32: =IS明細!X236 -> 0 | AR32: 0 | AS32: =IS明細!Z236 -> 0 | AU32: =AL32+AO32+AR32 -> 0 | AV32: =AM32+AP32+AS32 -> 0 | AX32: =K32+W32+AI32+AU32 -> 0 | AY32: =L32+X32+AJ32+AV32 -> 0
A33: 信用卡手續費收入 | B33: 0 | C33: =IS明細!D237 -> 0 | E33: 0 | F33: =IS明細!F237 -> 0 | H33: 0 | I33: =IS明細!H237 -> 0 | K33: =B33+E33+H33 -> 0 | L33: =C33+F33+I33 -> 0 | N33: 0 | O33: =IS明細!J237 -> 0 | Q33: 0 | R33: =IS明細!L237 -> 0 | T33: 0 | U33: =IS明細!N237 -> 0 | W33: =N33+Q33+T33 -> 0 | X33: =O33+R33+U33 -> 0 | Z33: 0 | AA33: =IS明細!P237 -> 0 | AC33: 0 | AD33: =IS明細!R237 -> 0 | AF33: 0 | AG33: =IS明細!T237 -> 0 | AI33: =Z33+AC33+AF33 -> 0 | AJ33: =AA33+AD33+AG33 -> 0 | AL33: 0 | AM33: =IS明細!V237 -> 0 | AO33: 0 | AP33: =IS明細!X237 -> 0 | AR33: 0 | AS33: =IS明細!Z237 -> 0 | AU33: =AL33+AO33+AR33 -> 0 | AV33: =AM33+AP33+AS33 -> 0 | AX33: =K33+W33+AI33+AU33 -> 0 | AY33: =L33+X33+AJ33+AV33 -> 0
A34: 什項收入 | B34: 0 | C34: =IS明細!D238 -> 151618 | E34: 0 | F34: =IS明細!F238 -> 59477 | H34: 0 | I34: =IS明細!H238 -> 53695 | K34: =B34+E34+H34 -> 0 | L34: =C34+F34+I34 -> 264790 | N34: 0 | O34: =IS明細!J238 -> 277576 | Q34: 0 | R34: =IS明細!L238 -> 239006 | T34: 0 | U34: =IS明細!N238 -> 88951 | W34: =N34+Q34+T34 -> 0 | X34: =O34+R34+U34 -> 605533 | Z34: 0 | AA34: =IS明細!P238 -> 70176 | AC34: 0 | AD34: =IS明細!R238 -> 264338 | AF34: 0 | AG34: =IS明細!T238 -> 0 | AI34: =Z34+AC34+AF34 -> 0 | AJ34: =AA34+AD34+AG34 -> 334514 | AL34: 0 | AM34: =IS明細!V238 -> 0 | AO34: 0 | AP34: =IS明細!X238 -> 0 | AR34: 0 | AS34: =IS明細!Z238 -> 0 | AU34: =AL34+AO34+AR34 -> 0 | AV34: =AM34+AP34+AS34 -> 0 | AX34: =K34+W34+AI34+AU34 -> 0 | AY34: =L34+X34+AJ34+AV34 -> 1204837
A35: 小計 | B35: =SUM(B25:B34) -> 0 | C35: =SUM(C25:C34) -> 1013492 | E35: =SUM(E25:E34) -> 0 | F35: =SUM(F25:F34) -> 990830 | H35: =SUM(H25:H34) -> 0 | I35: =SUM(I25:I34) -> 3001909 | K35: =B35+E35+H35 -> 0 | L35: =C35+F35+I35 -> 5006231 | N35: =SUM(N25:N34) -> 0 | O35: =SUM(O25:O34) -> 3891621 | Q35: =SUM(Q25:Q34) -> 0 | R35: =SUM(R25:R34) -> 2211387 | T35: =SUM(T25:T34) -> 0 | U35: =SUM(U25:U34) -> 3924023 | W35: =SUM(W25:W34) -> 0 | X35: =SUM(X25:X34) -> 10027031 | Z35: =SUM(Z25:Z34) -> 0 | AA35: =SUM(AA25:AA34) -> 1198088 | AC35: =SUM(AC25:AC34) -> 0 | AD35: =SUM(AD25:AD34) -> 1005421 | AF35: =SUM(AF25:AF34) -> 0 | AG35: =SUM(AG25:AG34) -> 0 | AI35: =SUM(AI25:AI34) -> 0 | AJ35: =SUM(AJ25:AJ34) -> 2203509 | AL35: =SUM(AL25:AL34) -> 0 | AM35: =SUM(AM25:AM34) -> 0 | AO35: =SUM(AO25:AO34) -> 0 | AP35: =SUM(AP25:AP34) -> 0 | AR35: =SUM(AR25:AR34) -> 0 | AS35: =SUM(AS25:AS34) -> 0 | AU35: =SUM(AU25:AU34) -> 0 | AV35: =SUM(AV25:AV34) -> 0 | AX35: =K35+W35+AI35+AU35 -> 0 | AY35: =L35+X35+AJ35+AV35 -> 17236771
A36: 營業外費用及損失
A37: 利息費用 | B37: 0 | C37: =IS明細!D241 -> 26301 | E37: 0 | F37: =IS明細!F241 -> 74827 | H37: 0 | I37: =IS明細!H241 -> 69962 | K37: =B37+E37+H37 -> 0 | L37: =C37+F37+I37 -> 171090 | N37: 0 | O37: =IS明細!J241 -> 93988 | Q37: 0 | R37: =IS明細!L241 -> 91944 | T37: 0 | U37: =IS明細!N241 -> 112861 | W37: =N37+Q37+T37 -> 0 | X37: =O37+R37+U37 -> 298793 | Z37: 0 | AA37: =IS明細!P241 -> 96752 | AC37: 0 | AD37: =IS明細!R241 -> 117626 | AF37: 0 | AG37: =IS明細!T241 -> 0 | AI37: =Z37+AC37+AF37 -> 0 | AJ37: =AA37+AD37+AG37 -> 214378 | AL37: 0 | AM37: =IS明細!V241 -> 0 | AO37: 0 | AP37: =IS明細!X241 -> 0 | AR37: 0 | AS37: =IS明細!Z241 -> 0 | AU37: =AL37+AO37+AR37 -> 0 | AV37: =AM37+AP37+AS37 -> 0 | AX37: =K37+W37+AI37+AU37 -> 0 | AY37: =L37+X37+AJ37+AV37 -> 684261
A38: 投資損失 | B38: 0 | C38: =IS明細!D245 -> 0 | E38: 0 | F38: =IS明細!F245 -> 0 | H38: 0 | I38: =IS明細!H245 -> 0 | K38: =B38+E38+H38 -> 0 | L38: =C38+F38+I38 -> 0 | N38: 0 | O38: =IS明細!J245 -> 0 | Q38: 0 | R38: =IS明細!L245 -> 0 | T38: 0 | U38: =IS明細!N245 -> 0 | W38: =N38+Q38+T38 -> 0 | X38: =O38+R38+U38 -> 0 | Z38: 0 | AA38: =IS明細!P245 -> 0 | AC38: 0 | AD38: =IS明細!R245 -> 0 | AF38: 0 | AG38: =IS明細!T245 -> 0 | AI38: =Z38+AC38+AF38 -> 0 | AJ38: =AA38+AD38+AG38 -> 0 | AL38: 0 | AM38: =IS明細!V245 -> 0 | AO38: 0 | AP38: =IS明細!X245 -> 0 | AR38: 0 | AS38: =IS明細!Z245 -> 0 | AU38: =AL38+AO38+AR38 -> 0 | AV38: =AM38+AP38+AS38 -> 0 | AX38: =K38+W38+AI38+AU38 -> 0 | AY38: =L38+X38+AJ38+AV38 -> 0
A39: 處分固定資產損失 | B39: 0 | C39: =IS明細!D248 -> 0 | E39: 0 | F39: =IS明細!F248 -> 0 | H39: 0 | I39: =IS明細!H248 -> 0 | K39: =B39+E39+H39 -> 0 | L39: =C39+F39+I39 -> 0 | N39: 0 | O39: =IS明細!J248 -> 0 | Q39: 0 | R39: =IS明細!L248 -> 0 | T39: 0 | U39: =IS明細!N248 -> 0 | W39: =N39+Q39+T39 -> 0 | X39: =O39+R39+U39 -> 0 | Z39: 0 | AA39: =IS明細!P248 -> 0 | AC39: 0 | AD39: =IS明細!R248 -> 0 | AF39: 0 | AG39: =IS明細!T248 -> 0 | AI39: =Z39+AC39+AF39 -> 0 | AJ39: =AA39+AD39+AG39 -> 0 | AL39: 0 | AM39: =IS明細!V248 -> 0 | AO39: 0 | AP39: =IS明細!X248 -> 0 | AR39: 0 | AS39: =IS明細!Z248 -> 0 | AU39: =AL39+AO39+AR39 -> 0 | AV39: =AM39+AP39+AS39 -> 0 | AX39: =K39+W39+AI39+AU39 -> 0 | AY39: =L39+X39+AJ39+AV39 -> 0
A40: 處分投資損失 | B40: 0 | C40: =IS明細!D249 -> 0 | E40: 0 | F40: =IS明細!F249 -> 0 | H40: 0 | I40: =IS明細!H249 -> 0 | K40: =B40+E40+H40 -> 0 | L40: =C40+F40+I40 -> 0 | N40: 0 | O40: =IS明細!J249 -> 0 | Q40: 0 | R40: =IS明細!L249 -> 0 | T40: 0 | U40: =IS明細!N249 -> 0 | W40: =N40+Q40+T40 -> 0 | X40: =O40+R40+U40 -> 0 | Z40: 0 | AA40: =IS明細!P249 -> 0 | AC40: 0 | AD40: =IS明細!R249 -> 0 | AF40: 0 | AG40: =IS明細!T249 -> 0 | AI40: =Z40+AC40+AF40 -> 0 | AJ40: =AA40+AD40+AG40 -> 0 | AL40: 0 | AM40: =IS明細!V249 -> 0 | AO40: 0 | AP40: =IS明細!X249 -> 0 | AR40: 0 | AS40: =IS明細!Z249 -> 0 | AU40: =AL40+AO40+AR40 -> 0 | AV40: =AM40+AP40+AS40 -> 0 | AX40: =K40+W40+AI40+AU40 -> 0 | AY40: =L40+X40+AJ40+AV40 -> 0
A41: 存貨盤損 | B41: 0 | C41: =IS明細!D250 -> 0 | E41: 0 | F41: =IS明細!F250 -> 0 | H41: 0 | I41: =IS明細!H250 -> 0 | K41: =B41+E41+H41 -> 0 | L41: =C41+F41+I41 -> 0 | N41: 0 | O41: =IS明細!J250 -> 0 | Q41: 0 | R41: =IS明細!L250 -> 0 | T41: 0 | U41: =IS明細!N250 -> 0 | W41: =N41+Q41+T41 -> 0 | X41: =O41+R41+U41 -> 0 | Z41: 0 | AA41: =IS明細!P250 -> 0 | AC41: 0 | AD41: =IS明細!R250 -> 0 | AF41: 0 | AG41: =IS明細!T250 -> 0 | AI41: =Z41+AC41+AF41 -> 0 | AJ41: =AA41+AD41+AG41 -> 0 | AL41: 0 | AM41: =IS明細!V250 -> 0 | AO41: 0 | AP41: =IS明細!X250 -> 0 | AR41: 0 | AS41: =IS明細!Z250 -> 0 | AU41: =AL41+AO41+AR41 -> 0 | AV41: =AM41+AP41+AS41 -> 0 | AX41: =K41+W41+AI41+AU41 -> 0 | AY41: =L41+X41+AJ41+AV41 -> 0
A42: 兌換損失 | B42: 0 | C42: =IS明細!D256 -> 5599361 | E42: 0 | F42: =IS明細!F256 -> 4644987 | H42: 0 | I42: =IS明細!H256 -> 3836889 | K42: =B42+E42+H42 -> 0 | L42: =C42+F42+I42 -> 14081237 | N42: 0 | O42: =IS明細!J256 -> 3895955 | Q42: 0 | R42: =IS明細!L256 -> 2165183 | T42: 0 | U42: =IS明細!N256 -> 1755192 | W42: =N42+Q42+T42 -> 0 | X42: =O42+R42+U42 -> 7816330 | Z42: 0 | AA42: =IS明細!P256 -> 2260251 | AC42: 0 | AD42: =IS明細!R256 -> 704027 | AF42: 0 | AG42: =IS明細!T256 -> 0 | AI42: =Z42+AC42+AF42 -> 0 | AJ42: =AA42+AD42+AG42 -> 2964278 | AL42: 0 | AM42: =IS明細!V256 -> 0 | AO42: 0 | AP42: =IS明細!X256 -> 0 | AR42: 0 | AS42: =IS明細!Z256 -> 0 | AU42: =AL42+AO42+AR42 -> 0 | AV42: =AM42+AP42+AS42 -> 0 | AX42: =K42+W42+AI42+AU42 -> 0 | AY42: =L42+X42+AJ42+AV42 -> 24861845
A43: 財務費用 | B43: 892725 | C43: =IS明細!D260 -> 368283 | E43: 892725 | F43: =IS明細!F260 -> 252106 | H43: 892725 | I43: =IS明細!H260 -> 140305 | K43: =B43+E43+H43 -> 2678175 | L43: =C43+F43+I43 -> 760694 | N43: 892724 | O43: =IS明細!J260 -> 118770 | Q43: 892724 | R43: =IS明細!L260 -> 230411 | T43: 892725 | U43: =IS明細!N260 -> 277435 | W43: =N43+Q43+T43 -> 2678173 | X43: =O43+R43+U43 -> 626616 | Z43: 1040836 | AA43: =IS明細!P260 -> 178264 | AC43: 1040837 | AD43: =IS明細!R260 -> 416667 | AF43: 1040835 | AG43: =IS明細!T260 -> 0 | AI43: =Z43+AC43+AF43 -> 3122508 | AJ43: =AA43+AD43+AG43 -> 594931 | AL43: 1040835 | AM43: =IS明細!V260 -> 0 | AO43: 1040835 | AP43: =IS明細!X260 -> 0 | AR43: 1040835 | AS43: =IS明細!Z260 -> 0 | AU43: =AL43+AO43+AR43 -> 3122505 | AV43: =AM43+AP43+AS43 -> 0 | AX43: =K43+W43+AI43+AU43 -> 11601361 | AY43: =L43+X43+AJ43+AV43 -> 1982241
A44: 金融資產評價損失 | B44: 0 | C44: =IS明細!D262 -> 0 | E44: 0 | F44: =IS明細!F262 -> 0 | H44: 0 | I44: =IS明細!H262 -> 0 | K44: =B44+E44+H44 -> 0 | L44: =C44+F44+I44 -> 0 | N44: 0 | O44: =IS明細!J262 -> 0 | Q44: 0 | R44: =IS明細!L262 -> 0 | T44: 0 | U44: =IS明細!N262 -> 0 | W44: =N44+Q44+T44 -> 0 | X44: =O44+R44+U44 -> 0 | Z44: 0 | AA44: =IS明細!P262 -> 0 | AC44: 0 | AD44: =IS明細!R262 -> 0 | AF44: 0 | AG44: =IS明細!T262 -> 0 | AI44: =Z44+AC44+AF44 -> 0 | AJ44: =AA44+AD44+AG44 -> 0 | AL44: 0 | AM44: =IS明細!V262 -> 0 | AO44: 0 | AP44: =IS明細!X262 -> 0 | AR44: 0 | AS44: =IS明細!Z262 -> 0 | AU44: =AL44+AO44+AR44 -> 0 | AV44: =AM44+AP44+AS44 -> 0 | AX44: =K44+W44+AI44+AU44 -> 0 | AY44: =L44+X44+AJ44+AV44 -> 0
A45: 什項支出 | B45: 0 | C45: =IS明細!D263 -> 0 | E45: 0 | F45: =IS明細!F263 -> 0 | H45: 0 | I45: =IS明細!H263 -> 0 | K45: =B45+E45+H45 -> 0 | L45: =C45+F45+I45 -> 0 | N45: 0 | O45: =IS明細!J263 -> 133996 | Q45: 0 | R45: =IS明細!L263 -> 0 | T45: 0 | U45: =IS明細!N263+IS明細!N261 -> 0 | W45: =N45+Q45+T45 -> 0 | X45: =O45+R45+U45 -> 133996 | Z45: 0 | AA45: =IS明細!P263+IS明細!P261 -> 0 | AC45: 0 | AD45: =IS明細!R263+IS明細!R261 -> 0 | AF45: 0 | AG45: =IS明細!T263+IS明細!T261 -> 0 | AI45: =Z45+AC45+AF45 -> 0 | AJ45: =AA45+AD45+AG45 -> 0 | AL45: 0 | AM45: =IS明細!V263+IS明細!V261 -> 0 | AO45: 0 | AP45: =IS明細!X263+IS明細!X261 -> 0 | AR45: 0 | AS45: =IS明細!Z263+IS明細!Z261 -> 0 | AU45: =AL45+AO45+AR45 -> 0 | AV45: =AM45+AP45+AS45 -> 0 | AX45: =K45+W45+AI45+AU45 -> 0 | AY45: =L45+X45+AJ45+AV45 -> 133996
A46: 小計 | B46: =SUM(B37:B45) -> 892725 | C46: =SUM(C37:C45) -> 5993945 | E46: =SUM(E37:E45) -> 892725 | F46: =SUM(F37:F45) -> 4971920 | H46: =SUM(H37:H45) -> 892725 | I46: =SUM(I37:I45) -> 4047156 | K46: =B46+E46+H46 -> 2678175 | L46: =C46+F46+I46 -> 15013021 | N46: =SUM(N37:N45) -> 892724 | O46: =SUM(O37:O45) -> 4242709 | Q46: =SUM(Q37:Q45) -> 892724 | R46: =SUM(R37:R45) -> 2487538 | T46: =SUM(T37:T45) -> 892725 | U46: =SUM(U37:U45) -> 2145488 | W46: =SUM(W37:W45) -> 2678173 | X46: =SUM(X37:X45) -> 8875735 | Z46: =SUM(Z37:Z45) -> 1040836 | AA46: =SUM(AA37:AA45) -> 2535267 | AC46: =SUM(AC37:AC45) -> 1040837 | AD46: =SUM(AD37:AD45) -> 1238320 | AF46: =SUM(AF37:AF45) -> 1040835 | AG46: =SUM(AG37:AG45) -> 0 | AI46: =SUM(AI37:AI45) -> 3122508 | AJ46: =SUM(AJ37:AJ45) -> 3773587 | AL46: =SUM(AL37:AL45) -> 1040835 | AM46: =SUM(AM37:AM45) -> 0 | AO46: =SUM(AO37:AO45) -> 1040835 | AP46: =SUM(AP37:AP45) -> 0 | AR46: =SUM(AR37:AR45) -> 1040835 | AS46: =SUM(AS37:AS45) -> 0 | AU46: =SUM(AU37:AU45) -> 3122505 | AV46: =SUM(AV37:AV45) -> 0 | AX46: =K46+W46+AI46+AU46 -> 11601361 | AY46: =L46+X46+AJ46+AV46 -> 27662343
A47: ▲ 營業外收入(費用) | B47: =B35-B46 -> -892725 | C47: =C35-C46 -> -4980453 | E47: =E35-E46 -> -892725 | F47: =F35-F46 -> -3981090 | H47: =H35-H46 -> -892725 | I47: =I35-I46 -> -1045247 | K47: =K35-K46 -> -2678175 | L47: =L35-L46 -> -10006790 | N47: =N35-N46 -> -892724 | O47: =O35-O46 -> -351088 | P47: =P35-P46 -> 0 | Q47: =Q35-Q46 -> -892724 | R47: =R35-R46 -> -276151 | T47: =T35-T46 -> -892725 | U47: =U35-U46 -> 1778535 | W47: =W35-W46 -> -2678173 | X47: =X35-X46 -> 1151296 | Z47: =Z35-Z46 -> -1040836 | AA47: =AA35-AA46 -> -1337179 | AC47: =AC35-AC46 -> -1040837 | AD47: =AD35-AD46 -> -232899 | AF47: =AF35-AF46 -> -1040835 | AG47: =AG35-AG46 -> 0 | AI47: =AI35-AI46 -> -3122508 | AJ47: =AJ35-AJ46 -> -1570078 | AL47: =AL35-AL46 -> -1040835 | AM47: =AM35-AM46 -> 0 | AO47: =AO35-AO46 -> -1040835 | AP47: =AP35-AP46 -> 0 | AR47: =AR35-AR46 -> -1040835 | AS47: =AS35-AS46 -> 0 | AU47: =AU35-AU46 -> -3122505 | AV47: =AV35-AV46 -> 0 | AX47: =AX35-AX46 -> -11601361 | AY47: =AY35-AY46 -> -10425572
A48: ▲ 稅前損益： | B48: =B22+B47 -> 4609275 | C48: =C22+C47 -> -7756173 | E48: =E22+E47 -> 4609275 | F48: =F22+F47 -> -10972456 | H48: =H22+H47 -> 4609275 | I48: =I22+I47 -> 2058472 | K48: =K22+K47 -> 13827825 | L48: =L22+L47 -> -16670157 | N48: =N22+N47 -> 4609276 | O48: =O22+O47 -> -900330 | P48: =P22+P47 -> 0 | Q48: =Q22+Q47 -> 4609276 | R48: =R22+R47 -> -1699644.2 | T48: =T22+T47 -> 4609275 | U48: =U22+U47 -> 4012267 | W48: =W22+W47 -> 13827827 | X48: =X22+X47 -> 1412292.8 | Z48: =Z22+Z47 -> 6056164 | AA48: =AA22+AA47 -> -645828 | AC48: =AC22+AC47 -> 6056163 | AD48: =AD22+AD47 -> 2289840 | AF48: =AF22+AF47 -> 6056165 | AG48: =AG22+AG47 -> 0 | AI48: =AI22+AI47 -> 18168492 | AJ48: =AJ22+AJ47 -> 1644012 | AL48: =AL22+AL47 -> 6056165 | AM48: =AM22+AM47 -> 0 | AO48: =AO22+AO47 -> 6056165 | AP48: =AP22+AP47 -> 0 | AR48: =AR22+AR47 -> 6056165 | AS48: =AS22+AS47 -> 0 | AU48: =AU22+AU47 -> 18168495 | AV48: =AV22+AV47 -> 0 | AX48: =AX22+AX47 -> 63992639 | AY48: =AY22+AY47 -> -13613852
A50: 實際數
B51: 數量 | C51: 銷貨淨額 | E51: 數量 | F51: 銷貨淨額 | H51: 數量 | I51: 銷貨淨額 | K51: 數量 | L51: 銷貨淨額 | N51: 數量 | O51: 銷貨淨額 | Q51: 數量 | R51: 銷貨淨額 | T51: 數量 | U51: 銷貨淨額 | W51: 數量 | X51: 銷貨淨額 | Z51: 數量 | AA51: 銷貨淨額 | AC51: 數量 | AD51: 銷貨淨額 | AF51: 數量 | AG51: 銷貨淨額 | AI51: 數量 | AJ51: 銷貨淨額 | AL51: 數量 | AM51: 銷貨淨額 | AO51: 數量 | AP51: 銷貨淨額 | AR51: 數量 | AS51: 銷貨淨額 | AU51: 數量 | AV51: 銷貨淨額 | AX51: 數量 | AY51: 銷貨淨額
A52: 主機(不包含Aures) | B52: 514 | C52: 7988506 | D52: =IF(B52=0,0,C52/B52) -> 15541.84 | E52: 543 | F52: 8311342 | G52: =IF(E52=0,0,F52/E52) -> 15306.339 | H52: 1874 | I52: 31039124 | J52: =IF(H52=0,0,I52/H52) -> 16563.033 | K52: =B52+E52+H52 -> 2931 | L52: =C52+F52+I52 -> 47338972 | M52: =IF(K52=0,0,L52/K52) -> 16151.133 | N52: 378 | O52: 6293287 | P52: =IF(N52=0,0,O52/N52) -> 16648.907 | Q52: 876 | R52: 14950751 | S52: =IF(Q52=0,0,R52/Q52) -> 17067.067 | T52: 1087 | U52: 16143932 | V52: =IF(T52=0,0,U52/T52) -> 14851.823 | W52: =N52+Q52+T52 -> 2341 | X52: =O52+R52+U52 -> 37387970 | Y52: =IF(W52=0,0,X52/W52) -> 15970.94 | Z52: 2474 | AA52: 19017365 | AB52: =IF(Z52=0,0,AA52/Z52) -> 7686.8897 | AC52: 1064 | AD52: 15730491 | AE52: =IF(AC52=0,0,AD52/AC52) -> 14784.296 | AH52: =IF(AF52=0,0,AG52/AF52) -> 0 | AI52: =Z52+AC52+AF52 -> 3538 | AJ52: =AA52+AD52+AG52 -> 34747856 | AK52: =IF(AI52=0,0,AJ52/AI52) -> 9821.3273 | AN52: =IF(AL52=0,0,AM52/AL52) -> 0 | AQ52: =IF(AO52=0,0,AP52/AO52) -> 0 | AT52: =IF(AR52=0,0,AS52/AR52) -> 0 | AU52: =AL52+AO52+AR52 -> 0 | AV52: =AM52+AP52+AS52 -> 0 | AW52: =IF(AU52=0,0,AV52/AU52) -> 0 | AX52: =K52+W52+AI52+AU52 -> 8810 | AY52: =L52+X52+AJ52+AV52 -> 119474798 | AZ52: =IF(AX52=0,0,AY52/AX52) -> 13561.271
A53: Aures(不含週邊商品等)
A54: YUNO-BASE151 | B54: 2740 | C54: 19071564 | D54: =IF(B54=0,0,C54/B54) -> 6960.4248 | E54: 2380 | F54: 16031611 | G54: =IF(E54=0,0,F54/E54) -> 6735.971 | H54: 1616 | I54: 10171332 | J54: =IF(H54=0,0,I54/H54) -> 6294.1411 | K54: =B54+E54+H54 -> 6736 | L54: =C54+F54+I54 -> 45274507 | M54: =IF(K54=0,0,L54/K54) -> 6721.2748 | N54: 3290 | O54: 22010639 | P54: =IF(N54=0,0,O54/N54) -> 6690.1638 | Q54: 1850 | R54: 12671223 | S54: =IF(Q54=0,0,R54/Q54) -> 6849.3097 | T54: 3620 | U54: 24071934 | V54: =IF(T54=0,0,U54/T54) -> 6649.7055 | W54: =N54+Q54+T54 -> 8760 | X54: =O54+R54+U54 -> 58753796 | Y54: =IF(W54=0,0,X54/W54) -> 6707.0543 | Z54: 4430 | AA54: 30248189 | AB54: =IF(Z54=0,0,AA54/Z54) -> 6828.0336 | AC54: 3267 | AD54: 21761496 | AE54: =IF(AC54=0,0,AD54/AC54) -> 6661.0028 | AH54: =IF(AF54=0,0,AG54/AF54) -> 0 | AI54: =Z54+AC54+AF54 -> 7697 | AJ54: =AA54+AD54+AG54 -> 52009685 | AK54: =IF(AI54=0,0,AJ54/AI54) -> 6757.1372 | AN54: =IF(AL54=0,0,AM54/AL54) -> 0 | AQ54: =IF(AO54=0,0,AP54/AO54) -> 0 | AT54: =IF(AR54=0,0,AS54/AR54) -> 0 | AU54: =AL54+AO54+AR54 -> 0 | AV54: =AM54+AP54+AS54 -> 0 | AW54: =IF(AU54=0,0,AV54/AU54) -> 0 | AX54: =K54+W54+AI54+AU54 -> 23193 | AY54: =L54+X54+AJ54+AV54 -> 156037988 | AZ54: =IF(AX54=0,0,AY54/AX54) -> 6727.8053
A55: YUNO-BASE156 | B55: 330 | C55: 2486273 | D55: =IF(B55=0,0,C55/B55) -> 7534.1606 | E55: 275 | F55: 2067483 | G55: =IF(E55=0,0,F55/E55) -> 7518.12 | H55: 115 | I55: 832053 | J55: =IF(H55=0,0,I55/H55) -> 7235.2435 | K55: =B55+E55+H55 -> 720 | L55: =C55+F55+I55 -> 5385809 | M55: =IF(K55=0,0,L55/K55) -> 7480.2903 | N55: 320 | O55: 2341273 | P55: =IF(N55=0,0,O55/N55) -> 7316.4781 | Q55: 75 | R55: 503622 | S55: =IF(Q55=0,0,R55/Q55) -> 6714.96 | T55: 440 | U55: 3062979 | V55: =IF(T55=0,0,U55/T55) -> 6961.3159 | W55: =N55+Q55+T55 -> 835 | X55: =O55+R55+U55 -> 5907874 | Y55: =IF(W55=0,0,X55/W55) -> 7075.2982 | Z55: 180 | AA55: 1230231 | AB55: =IF(Z55=0,0,AA55/Z55) -> 6834.6167 | AC55: 380 | AD55: 2713650 | AE55: =IF(AC55=0,0,AD55/AC55) -> 7141.1842 | AH55: =IF(AF55=0,0,AG55/AF55) -> 0 | AI55: =Z55+AC55+AF55 -> 560 | AJ55: =AA55+AD55+AG55 -> 3943881 | AK55: =IF(AI55=0,0,AJ55/AI55) -> 7042.6446 | AN55: =IF(AL55=0,0,AM55/AL55) -> 0 | AQ55: =IF(AO55=0,0,AP55/AO55) -> 0 | AT55: =IF(AR55=0,0,AS55/AR55) -> 0 | AU55: =AL55+AO55+AR55 -> 0 | AV55: =AM55+AP55+AS55 -> 0 | AW55: =IF(AU55=0,0,AV55/AU55) -> 0 | AX55: =K55+W55+AI55+AU55 -> 2115 | AY55: =L55+X55+AJ55+AV55 -> 15237564 | AZ55: =IF(AX55=0,0,AY55/AX55) -> 7204.522
A56: YUNO151-TOUCHSCREEN | B56: 80 | C56: 719040 | D56: =IF(B56=0,0,C56/B56) -> 8988 | E56: 80 | F56: 700336 | G56: =IF(E56=0,0,F56/E56) -> 8754.2 | H56: 70 | I56: 599760 | J56: =IF(H56=0,0,I56/H56) -> 8568 | K56: =B56+E56+H56 -> 230 | L56: =C56+F56+I56 -> 2019136 | M56: =IF(K56=0,0,L56/K56) -> 8778.8522 | N56: 130 | O56: 1104110 | P56: =IF(N56=0,0,O56/N56) -> 8493.1538 | Q56: 110 | R56: 927276 | S56: =IF(Q56=0,0,R56/Q56) -> 8429.7818 | T56: 105 | U56: 883428 | V56: =IF(T56=0,0,U56/T56) -> 8413.6 | W56: =N56+Q56+T56 -> 345 | X56: =O56+R56+U56 -> 2914814 | Y56: =IF(W56=0,0,X56/W56) -> 8448.7362 | Z56: 95 | AA56: 809165 | AB56: =IF(Z56=0,0,AA56/Z56) -> 8517.5263 | AE56: =IF(AC56=0,0,AD56/AC56) -> 0 | AH56: =IF(AF56=0,0,AG56/AF56) -> 0 | AI56: =Z56+AC56+AF56 -> 95 | AJ56: =AA56+AD56+AG56 -> 809165 | AK56: =IF(AI56=0,0,AJ56/AI56) -> 8517.5263 | AN56: =IF(AL56=0,0,AM56/AL56) -> 0 | AQ56: =IF(AO56=0,0,AP56/AO56) -> 0 | AT56: =IF(AR56=0,0,AS56/AR56) -> 0 | AU56: =AL56+AO56+AR56 -> 0 | AV56: =AM56+AP56+AS56 -> 0 | AW56: =IF(AU56=0,0,AV56/AU56) -> 0 | AX56: =K56+W56+AI56+AU56 -> 670 | AY56: =L56+X56+AJ56+AV56 -> 5743115 | AZ56: =IF(AX56=0,0,AY56/AX56) -> 8571.8134
A57: YUNO156-TOUCHSCREEN | D57: =IF(B57=0,0,C57/B57) -> 0 | E57: 0 | F57: 0 | G57: =IF(E57=0,0,F57/E57) -> 0 | J57: =IF(H57=0,0,I57/H57) -> 0 | K57: =B57+E57+H57 -> 0 | L57: =C57+F57+I57 -> 0 | M57: =IF(K57=0,0,L57/K57) -> 0 | P57: =IF(N57=0,0,O57/N57) -> 0 | Q57: 10 | R57: 90390 | S57: =IF(Q57=0,0,R57/Q57) -> 9039 | V57: =IF(T57=0,0,U57/T57) -> 0 | W57: =N57+Q57+T57 -> 10 | X57: =O57+R57+U57 -> 90390 | Y57: =IF(W57=0,0,X57/W57) -> 9039 | AB57: =IF(Z57=0,0,AA57/Z57) -> 0 | AE57: =IF(AC57=0,0,AD57/AC57) -> 0 | AH57: =IF(AF57=0,0,AG57/AF57) -> 0 | AI57: =Z57+AC57+AF57 -> 0 | AJ57: =AA57+AD57+AG57 -> 0 | AK57: =IF(AI57=0,0,AJ57/AI57) -> 0 | AN57: =IF(AL57=0,0,AM57/AL57) -> 0 | AQ57: =IF(AO57=0,0,AP57/AO57) -> 0 | AT57: =IF(AR57=0,0,AS57/AR57) -> 0 | AU57: =AL57+AO57+AR57 -> 0 | AV57: =AM57+AP57+AS57 -> 0 | AW57: =IF(AU57=0,0,AV57/AU57) -> 0 | AX57: =K57+W57+AI57+AU57 -> 10 | AY57: =L57+X57+AJ57+AV57 -> 90390 | AZ57: =IF(AX57=0,0,AY57/AX57) -> 9039
A58: YUNO-KIOSK | D58: =IF(B58=0,0,C58/B58) -> 0 | E58: 100 | F58: 642760 | G58: =IF(E58=0,0,F58/E58) -> 6427.6 | J58: =IF(H58=0,0,I58/H58) -> 0 | K58: =B58+E58+H58 -> 100 | L58: =C58+F58+I58 -> 642760 | M58: =IF(K58=0,0,L58/K58) -> 6427.6 | N58: 100 | O58: 637005 | P58: =IF(N58=0,0,O58/N58) -> 6370.05 | Q58: 50 | R58: 330375 | S58: =IF(Q58=0,0,R58/Q58) -> 6607.5 | V58: =IF(T58=0,0,U58/T58) -> 0 | W58: =N58+Q58+T58 -> 150 | X58: =O58+R58+U58 -> 967380 | Y58: =IF(W58=0,0,X58/W58) -> 6449.2 | AB58: =IF(Z58=0,0,AA58/Z58) -> 0 | AE58: =IF(AC58=0,0,AD58/AC58) -> 0 | AH58: =IF(AF58=0,0,AG58/AF58) -> 0 | AI58: =Z58+AC58+AF58 -> 0 | AJ58: =AA58+AD58+AG58 -> 0 | AK58: =IF(AI58=0,0,AJ58/AI58) -> 0 | AN58: =IF(AL58=0,0,AM58/AL58) -> 0 | AQ58: =IF(AO58=0,0,AP58/AO58) -> 0 | AT58: =IF(AR58=0,0,AS58/AR58) -> 0 | AU58: =AL58+AO58+AR58 -> 0 | AV58: =AM58+AP58+AS58 -> 0 | AW58: =IF(AU58=0,0,AV58/AU58) -> 0 | AX58: =K58+W58+AI58+AU58 -> 250 | AY58: =L58+X58+AJ58+AV58 -> 1610140 | AZ58: =IF(AX58=0,0,AY58/AX58) -> 6440.56
A59: YUNO-MB | B59: 2610 | C59: 17328369 | D59: =IF(B59=0,0,C59/B59) -> 6639.2218 | E59: 2215 | F59: 14473450 | G59: =IF(E59=0,0,F59/E59) -> 6534.2889 | H59: 1326 | I59: 8498578 | J59: =IF(H59=0,0,I59/H59) -> 6409.184 | K59: =B59+E59+H59 -> 6151 | L59: =C59+F59+I59 -> 40300397 | M59: =IF(K59=0,0,L59/K59) -> 6551.8447 | N59: 3065 | O59: 19682762 | P59: =IF(N59=0,0,O59/N59) -> 6421.7821 | Q59: 1545 | R59: 9084188 | S59: =IF(Q59=0,0,R59/Q59) -> 5879.7333 | T59: 3090 | U59: 19715969 | V59: =IF(T59=0,0,U59/T59) -> 6380.5725 | W59: =N59+Q59+T59 -> 7700 | X59: =O59+R59+U59 -> 48482919 | Y59: =IF(W59=0,0,X59/W59) -> 6296.483 | Z59: 3330 | AA59: 21344128 | AB59: =IF(Z59=0,0,AA59/Z59) -> 6409.648 | AC59: 2417 | AD59: 15367460 | AE59: =IF(AC59=0,0,AD59/AC59) -> 6358.072 | AH59: =IF(AF59=0,0,AG59/AF59) -> 0 | AI59: =Z59+AC59+AF59 -> 5747 | AJ59: =AA59+AD59+AG59 -> 36711588 | AK59: =IF(AI59=0,0,AJ59/AI59) -> 6387.9568 | AN59: =IF(AL59=0,0,AM59/AL59) -> 0 | AQ59: =IF(AO59=0,0,AP59/AO59) -> 0 | AT59: =IF(AR59=0,0,AS59/AR59) -> 0 | AU59: =AL59+AO59+AR59 -> 0 | AV59: =AM59+AP59+AS59 -> 0 | AW59: =IF(AU59=0,0,AV59/AU59) -> 0 | AX59: =K59+W59+AI59+AU59 -> 19598 | AY59: =L59+X59+AJ59+AV59 -> 125494904 | AZ59: =IF(AX59=0,0,AY59/AX59) -> 6403.4546
A60: YUNO-MB-I3 | B60: 480 | C60: 5325635 | D60: =IF(B60=0,0,C60/B60) -> 11095.073 | E60: 440 | F60: 4744059 | G60: =IF(E60=0,0,F60/E60) -> 10781.952 | H60: 430 | I60: 4592034 | J60: =IF(H60=0,0,I60/H60) -> 10679.149 | K60: =B60+E60+H60 -> 1350 | L60: =C60+F60+I60 -> 14661728 | M60: =IF(K60=0,0,L60/K60) -> 10860.539 | N60: 645 | O60: 6813127 | P60: =IF(N60=0,0,O60/N60) -> 10562.988 | Q60: 430 | R60: 4101956 | S60: =IF(Q60=0,0,R60/Q60) -> 9539.4326 | T60: 970 | U60: 10139623 | V60: =IF(T60=0,0,U60/T60) -> 10453.22 | W60: =N60+Q60+T60 -> 2045 | X60: =O60+R60+U60 -> 21054706 | Y60: =IF(W60=0,0,X60/W60) -> 10295.7 | Z60: 1480 | AA60: 15789563 | AB60: =IF(Z60=0,0,AA60/Z60) -> 10668.624 | AC60: 1230 | AD60: 13030942 | AE60: =IF(AC60=0,0,AD60/AC60) -> 10594.262 | AH60: =IF(AF60=0,0,AG60/AF60) -> 0 | AI60: =Z60+AC60+AF60 -> 2710 | AJ60: =AA60+AD60+AG60 -> 28820505 | AK60: =IF(AI60=0,0,AJ60/AI60) -> 10634.873 | AN60: =IF(AL60=0,0,AM60/AL60) -> 0 | AQ60: =IF(AO60=0,0,AP60/AO60) -> 0 | AT60: =IF(AR60=0,0,AS60/AR60) -> 0 | AU60: =AL60+AO60+AR60 -> 0 | AV60: =AM60+AP60+AS60 -> 0 | AW60: =IF(AU60=0,0,AV60/AU60) -> 0 | AX60: =K60+W60+AI60+AU60 -> 6105 | AY60: =L60+X60+AJ60+AV60 -> 64536939 | AZ60: =IF(AX60=0,0,AY60/AX60) -> 10571.161
A61: YUNO-KIOSK-MB | B61: 100 | C61: 675538 | D61: =IF(B61=0,0,C61/B61) -> 6755.38 | E61: 100 | F61: 651052 | G61: =IF(E61=0,0,F61/E61) -> 6510.52 | H61: 96 | I61: 626638 | J61: =IF(H61=0,0,I61/H61) -> 6527.4792 | K61: =B61+E61+H61 -> 296 | L61: =C61+F61+I61 -> 1953228 | M61: =IF(K61=0,0,L61/K61) -> 6598.7432 | P61: =IF(N61=0,0,O61/N61) -> 0 | Q61: 200 | R61: 1277512 | S61: =IF(Q61=0,0,R61/Q61) -> 6387.56 | V61: =IF(T61=0,0,U61/T61) -> 0 | W61: =N61+Q61+T61 -> 200 | X61: =O61+R61+U61 -> 1277512 | Y61: =IF(W61=0,0,X61/W61) -> 6387.56 | AB61: =IF(Z61=0,0,AA61/Z61) -> 0 | AE61: =IF(AC61=0,0,AD61/AC61) -> 0 | AH61: =IF(AF61=0,0,AG61/AF61) -> 0 | AI61: =Z61+AC61+AF61 -> 0 | AJ61: =AA61+AD61+AG61 -> 0 | AK61: =IF(AI61=0,0,AJ61/AI61) -> 0 | AN61: =IF(AL61=0,0,AM61/AL61) -> 0 | AQ61: =IF(AO61=0,0,AP61/AO61) -> 0 | AT61: =IF(AR61=0,0,AS61/AR61) -> 0 | AU61: =AL61+AO61+AR61 -> 0 | AV61: =AM61+AP61+AS61 -> 0 | AW61: =IF(AU61=0,0,AV61/AU61) -> 0 | AX61: =K61+W61+AI61+AU61 -> 496 | AY61: =L61+X61+AJ61+AV61 -> 3230740 | AZ61: =IF(AX61=0,0,AY61/AX61) -> 6513.5887
A62: YUNO-KIOSK-MB-I3 | Q62: 50 | R62: 524262 | S62: =IF(Q62=0,0,R62/Q62) -> 10485.24
A63: YUNO-COVER | B63: 1680 | C63: 536626 | D63: =IF(B63=0,0,C63/B63) -> 319.42024 | E63: 1210 | F63: 375542 | G63: =IF(E63=0,0,F63/E63) -> 310.36529 | H63: 1377 | I63: 395470 | J63: =IF(H63=0,0,I63/H63) -> 287.1968 | K63: =B63+E63+H63 -> 4267 | L63: =C63+F63+I63 -> 1307638 | M63: =IF(K63=0,0,L63/K63) -> 306.45371 | N63: 2821 | O63: 856311 | P63: =IF(N63=0,0,O63/N63) -> 303.54874 | Q63: 1660 | R63: 500017 | S63: =IF(Q63=0,0,R63/Q63) -> 301.21506 | T63: 2450 | U63: 737042 | V63: =IF(T63=0,0,U63/T63) -> 300.83347 | W63: =N63+Q63+T63 -> 6931 | X63: =O63+R63+U63 -> 2093370 | Y63: =IF(W63=0,0,X63/W63) -> 302.03001 | Z63: 2550 | AA63: 774676 | AB63: =IF(Z63=0,0,AA63/Z63) -> 303.79451 | AC63: 1290 | AD63: 393774 | AE63: =IF(AC63=0,0,AD63/AC63) -> 305.25116 | AH63: =IF(AF63=0,0,AG63/AF63) -> 0 | AI63: =Z63+AC63+AF63 -> 3840 | AJ63: =AA63+AD63+AG63 -> 1168450 | AK63: =IF(AI63=0,0,AJ63/AI63) -> 304.28385 | AN63: =IF(AL63=0,0,AM63/AL63) -> 0 | AQ63: =IF(AO63=0,0,AP63/AO63) -> 0 | AT63: =IF(AR63=0,0,AS63/AR63) -> 0 | AU63: =AL63+AO63+AR63 -> 0 | AV63: =AM63+AP63+AS63 -> 0 | AW63: =IF(AU63=0,0,AV63/AU63) -> 0 | AX63: =K63+W63+AI63+AU63 -> 15038 | AY63: =L63+X63+AJ63+AV63 -> 4569458 | AZ63: =IF(AX63=0,0,AY63/AX63) -> 303.86075
A64: YUNO-VFD | B64: 630 | C64: 861220 | D64: =IF(B64=0,0,C64/B64) -> 1367.0159 | E64: 600 | F64: 793384 | G64: =IF(E64=0,0,F64/E64) -> 1322.3067 | H64: 220 | I64: 290056 | J64: =IF(H64=0,0,I64/H64) -> 1318.4364 | K64: =B64+E64+H64 -> 1450 | L64: =C64+F64+I64 -> 1944660 | M64: =IF(K64=0,0,L64/K64) -> 1341.1448 | N64: 950 | O64: 1233732 | P64: =IF(N64=0,0,O64/N64) -> 1298.6653 | Q64: 830 | R64: 1070173 | S64: =IF(Q64=0,0,R64/Q64) -> 1289.3651 | T64: 1900 | U64: 2443045 | V64: =IF(T64=0,0,U64/T64) -> 1285.8132 | W64: =N64+Q64+T64 -> 3680 | X64: =O64+R64+U64 -> 4746950 | Y64: =IF(W64=0,0,X64/W64) -> 1289.9321 | Z64: 450 | AA64: 586370 | AB64: =IF(Z64=0,0,AA64/Z64) -> 1303.0444 | AC64: 1150 | AD64: 1490092 | AE64: =IF(AC64=0,0,AD64/AC64) -> 1295.7322 | AH64: =IF(AF64=0,0,AG64/AF64) -> 0 | AI64: =Z64+AC64+AF64 -> 1600 | AJ64: =AA64+AD64+AG64 -> 2076462 | AK64: =IF(AI64=0,0,AJ64/AI64) -> 1297.7887 | AN64: =IF(AL64=0,0,AM64/AL64) -> 0 | AQ64: =IF(AO64=0,0,AP64/AO64) -> 0 | AT64: =IF(AR64=0,0,AS64/AR64) -> 0 | AU64: =AL64+AO64+AR64 -> 0 | AV64: =AM64+AP64+AS64 -> 0 | AW64: =IF(AU64=0,0,AV64/AU64) -> 0 | AX64: =K64+W64+AI64+AU64 -> 6730 | AY64: =L64+X64+AJ64+AV64 -> 8768072 | AZ64: =IF(AX64=0,0,AY64/AX64) -> 1302.8339
A65: YUNO+VFD-COVER | B65: 1620 | C65: 516779 | D65: =IF(B65=0,0,C65/B65) -> 318.99938 | E65: 1520 | F65: 470891 | G65: =IF(E65=0,0,F65/E65) -> 309.79671 | H65: 428 | I65: 39962 | J65: =IF(H65=0,0,I65/H65) -> 93.369159 | K65: =B65+E65+H65 -> 3568 | L65: =C65+F65+I65 -> 1027632 | M65: =IF(K65=0,0,L65/K65) -> 288.01345 | N65: 1310 | O65: 397894 | P65: =IF(N65=0,0,O65/N65) -> 303.73588 | Q65: 1260 | R65: 379600 | S65: =IF(Q65=0,0,R65/Q65) -> 301.26984 | T65: 1350 | U65: 405715 | V65: =IF(T65=0,0,U65/T65) -> 300.52963 | W65: =N65+Q65+T65 -> 3920 | X65: =O65+R65+U65 -> 1183209 | Y65: =IF(W65=0,0,X65/W65) -> 301.83903 | Z65: 977 | AA65: 297094 | AB65: =IF(Z65=0,0,AA65/Z65) -> 304.08802 | AC65: 960 | AD65: 293748 | AE65: =IF(AC65=0,0,AD65/AC65) -> 305.9875 | AH65: =IF(AF65=0,0,AG65/AF65) -> 0 | AI65: =Z65+AC65+AF65 -> 1937 | AJ65: =AA65+AD65+AG65 -> 590842 | AK65: =IF(AI65=0,0,AJ65/AI65) -> 305.02943 | AN65: =IF(AL65=0,0,AM65/AL65) -> 0 | AQ65: =IF(AO65=0,0,AP65/AO65) -> 0 | AT65: =IF(AR65=0,0,AS65/AR65) -> 0 | AU65: =AL65+AO65+AR65 -> 0 | AV65: =AM65+AP65+AS65 -> 0 | AW65: =IF(AU65=0,0,AV65/AU65) -> 0 | AX65: =K65+W65+AI65+AU65 -> 9425 | AY65: =L65+X65+AJ65+AV65 -> 2801683 | AZ65: =IF(AX65=0,0,AY65/AX65) -> 297.2608
A66: YUNO-VESA | D66: =IF(B66=0,0,C66/B66) -> 0 | G66: =IF(E66=0,0,F66/E66) -> 0 | J66: =IF(H66=0,0,I66/H66) -> 0 | K66: =B66+E66+H66 -> 0 | L66: =C66+F66+I66 -> 0 | M66: =IF(K66=0,0,L66/K66) -> 0 | P66: =IF(N66=0,0,O66/N66) -> 0 | S66: =IF(Q66=0,0,R66/Q66) -> 0 | T66: 50 | U66: 9009 | V66: =IF(T66=0,0,U66/T66) -> 180.18 | W66: =N66+Q66+T66 -> 50 | X66: =O66+R66+U66 -> 9009 | Y66: =IF(W66=0,0,X66/W66) -> 180.18 | Z66: 150 | AA66: 27307 | AB66: =IF(Z66=0,0,AA66/Z66) -> 182.04667 | AC66: 100 | AD66: 18081 | AE66: =IF(AC66=0,0,AD66/AC66) -> 180.81 | AH66: =IF(AF66=0,0,AG66/AF66) -> 0 | AI66: =Z66+AC66+AF66 -> 250 | AJ66: =AA66+AD66+AG66 -> 45388 | AK66: =IF(AI66=0,0,AJ66/AI66) -> 181.552 | AN66: =IF(AL66=0,0,AM66/AL66) -> 0 | AQ66: =IF(AO66=0,0,AP66/AO66) -> 0 | AT66: =IF(AR66=0,0,AS66/AR66) -> 0 | AU66: =AL66+AO66+AR66 -> 0 | AV66: =AM66+AP66+AS66 -> 0 | AW66: =IF(AU66=0,0,AV66/AU66) -> 0 | AX66: =K66+W66+AI66+AU66 -> 300 | AY66: =L66+X66+AJ66+AV66 -> 54397 | AZ66: =IF(AX66=0,0,AY66/AX66) -> 181.32333
A67: YUNO151-VESA-COVER | B67: 200 | C67: 17976 | D67: =IF(B67=0,0,C67/B67) -> 89.88 | E67: 30 | F67: 2580 | G67: =IF(E67=0,0,F67/E67) -> 86 | H67: 370 | I67: 31986 | J67: =IF(H67=0,0,I67/H67) -> 86.448649 | K67: =B67+E67+H67 -> 600 | L67: =C67+F67+I67 -> 52542 | M67: =IF(K67=0,0,L67/K67) -> 87.57 | N67: 570 | O67: 48435 | P67: =IF(N67=0,0,O67/N67) -> 84.973684 | Q67: 100 | R67: 8437 | S67: =IF(Q67=0,0,R67/Q67) -> 84.37 | T67: 50 | U67: 4204 | V67: =IF(T67=0,0,U67/T67) -> 84.08 | W67: =N67+Q67+T67 -> 720 | X67: =O67+R67+U67 -> 61076 | Y67: =IF(W67=0,0,X67/W67) -> 84.827778 | AB67: =IF(Z67=0,0,AA67/Z67) -> 0 | AC67: 150 | AD67: 12685 | AE67: =IF(AC67=0,0,AD67/AC67) -> 84.566667 | AH67: =IF(AF67=0,0,AG67/AF67) -> 0 | AI67: =Z67+AC67+AF67 -> 150 | AJ67: =AA67+AD67+AG67 -> 12685 | AK67: =IF(AI67=0,0,AJ67/AI67) -> 84.566667 | AN67: =IF(AL67=0,0,AM67/AL67) -> 0 | AQ67: =IF(AO67=0,0,AP67/AO67) -> 0 | AT67: =IF(AR67=0,0,AS67/AR67) -> 0 | AU67: =AL67+AO67+AR67 -> 0 | AV67: =AM67+AP67+AS67 -> 0 | AW67: =IF(AU67=0,0,AV67/AU67) -> 0 | AX67: =K67+W67+AI67+AU67 -> 1470 | AY67: =L67+X67+AJ67+AV67 -> 126303 | AZ67: =IF(AX67=0,0,AY67/AX67) -> 85.920408
A68: YUNO156-VESA-COVER | B68: 10 | C68: 899 | D68: =IF(B68=0,0,C68/B68) -> 89.9 | G68: =IF(E68=0,0,F68/E68) -> 0 | J68: =IF(H68=0,0,I68/H68) -> 0 | K68: =B68+E68+H68 -> 10 | L68: =C68+F68+I68 -> 899 | M68: =IF(K68=0,0,L68/K68) -> 89.9 | P68: =IF(N68=0,0,O68/N68) -> 0 | Q68: 20 | R68: 1686 | S68: =IF(Q68=0,0,R68/Q68) -> 84.3 | V68: =IF(T68=0,0,U68/T68) -> 0 | W68: =N68+Q68+T68 -> 20 | X68: =O68+R68+U68 -> 1686 | Y68: =IF(W68=0,0,X68/W68) -> 84.3 | AB68: =IF(Z68=0,0,AA68/Z68) -> 0 | AE68: =IF(AC68=0,0,AD68/AC68) -> 0 | AH68: =IF(AF68=0,0,AG68/AF68) -> 0 | AI68: =Z68+AC68+AF68 -> 0 | AJ68: =AA68+AD68+AG68 -> 0 | AK68: =IF(AI68=0,0,AJ68/AI68) -> 0 | AN68: =IF(AL68=0,0,AM68/AL68) -> 0 | AQ68: =IF(AO68=0,0,AP68/AO68) -> 0 | AT68: =IF(AR68=0,0,AS68/AR68) -> 0 | AU68: =AL68+AO68+AR68 -> 0 | AV68: =AM68+AP68+AS68 -> 0 | AW68: =IF(AU68=0,0,AV68/AU68) -> 0 | AX68: =K68+W68+AI68+AU68 -> 30 | AY68: =L68+X68+AJ68+AV68 -> 2585 | AZ68: =IF(AX68=0,0,AY68/AX68) -> 86.166667
A69: YUNO-2NDLCD10.1 | B69: 510 | C69: 2329701 | D69: =IF(B69=0,0,C69/B69) -> 4568.0412 | E69: 400 | F69: 1615022 | G69: =IF(E69=0,0,F69/E69) -> 4037.555 | H69: 70 | I69: 281632 | J69: =IF(H69=0,0,I69/H69) -> 4023.3143 | K69: =B69+E69+H69 -> 980 | L69: =C69+F69+I69 -> 4226355 | M69: =IF(K69=0,0,L69/K69) -> 4312.6071 | N69: 255 | O69: 1006213 | P69: =IF(N69=0,0,O69/N69) -> 3945.9333 | Q69: 275 | R69: 1077148 | S69: =IF(Q69=0,0,R69/Q69) -> 3916.9018 | T69: 400 | U69: 1598213 | V69: =IF(T69=0,0,U69/T69) -> 3995.5325 | W69: =N69+Q69+T69 -> 930 | X69: =O69+R69+U69 -> 3681574 | Y69: =IF(W69=0,0,X69/W69) -> 3958.6817 | Z69: 380 | AA69: 1564899 | AB69: =IF(Z69=0,0,AA69/Z69) -> 4118.1553 | AC69: 800 | AD69: 3511392 | AE69: =IF(AC69=0,0,AD69/AC69) -> 4389.24 | AH69: =IF(AF69=0,0,AG69/AF69) -> 0 | AI69: =Z69+AC69+AF69 -> 1180 | AJ69: =AA69+AD69+AG69 -> 5076291 | AK69: =IF(AI69=0,0,AJ69/AI69) -> 4301.9415 | AN69: =IF(AL69=0,0,AM69/AL69) -> 0 | AQ69: =IF(AO69=0,0,AP69/AO69) -> 0 | AT69: =IF(AR69=0,0,AS69/AR69) -> 0 | AU69: =AL69+AO69+AR69 -> 0 | AV69: =AM69+AP69+AS69 -> 0 | AW69: =IF(AU69=0,0,AV69/AU69) -> 0 | AX69: =K69+W69+AI69+AU69 -> 3090 | AY69: =L69+X69+AJ69+AV69 -> 12984220 | AZ69: =IF(AX69=0,0,AY69/AX69) -> 4202.0129
A70: YUNO-KIT-WIFI | B70: 100 | C70: 86036 | D70: =IF(B70=0,0,C70/B70) -> 860.36 | E70: 100 | F70: 84416 | G70: =IF(E70=0,0,F70/E70) -> 844.16 | H70: 410 | I70: 339563 | J70: =IF(H70=0,0,I70/H70) -> 828.20244 | K70: =B70+E70+H70 -> 610 | L70: =C70+F70+I70 -> 510015 | M70: =IF(K70=0,0,L70/K70) -> 836.09016 | N70: 310 | O70: 253871 | P70: =IF(N70=0,0,O70/N70) -> 818.93871 | Q70: 300 | R70: 243945 | S70: =IF(Q70=0,0,R70/Q70) -> 813.15 | T70: 200 | U70: 163026 | V70: =IF(T70=0,0,U70/T70) -> 815.13 | W70: =N70+Q70+T70 -> 810 | X70: =O70+R70+U70 -> 660842 | Y70: =IF(W70=0,0,X70/W70) -> 815.85432 | Z70: 200 | AA70: 163890 | AB70: =IF(Z70=0,0,AA70/Z70) -> 819.45 | AC70: 300 | AD70: 245309 | AE70: =IF(AC70=0,0,AD70/AC70) -> 817.69667 | AH70: =IF(AF70=0,0,AG70/AF70) -> 0 | AI70: =Z70+AC70+AF70 -> 500 | AJ70: =AA70+AD70+AG70 -> 409199 | AK70: =IF(AI70=0,0,AJ70/AI70) -> 818.398 | AN70: =IF(AL70=0,0,AM70/AL70) -> 0 | AQ70: =IF(AO70=0,0,AP70/AO70) -> 0 | AT70: =IF(AR70=0,0,AS70/AR70) -> 0 | AU70: =AL70+AO70+AR70 -> 0 | AV70: =AM70+AP70+AS70 -> 0 | AW70: =IF(AU70=0,0,AV70/AU70) -> 0 | AX70: =K70+W70+AI70+AU70 -> 1920 | AY70: =L70+X70+AJ70+AV70 -> 1580056 | AZ70: =IF(AX70=0,0,AY70/AX70) -> 822.94583
A71: YUNO-MSRLONG | D71: =IF(B71=0,0,C71/B71) -> 0 | G71: =IF(E71=0,0,F71/E71) -> 0 | J71: =IF(H71=0,0,I71/H71) -> 0 | K71: =B71+E71+H71 -> 0 | L71: =C71+F71+I71 -> 0 | M71: =IF(K71=0,0,L71/K71) -> 0 | N71: 601 | O71: 674529 | P71: =IF(N71=0,0,O71/N71) -> 1122.3444 | Q71: 930 | R71: 1043857 | S71: =IF(Q71=0,0,R71/Q71) -> 1122.4269 | T71: 350 | U71: 388778 | V71: =IF(T71=0,0,U71/T71) -> 1110.7943 | W71: =N71+Q71+T71 -> 1881 | X71: =O71+R71+U71 -> 2107164 | Y71: =IF(W71=0,0,X71/W71) -> 1120.236 | AB71: =IF(Z71=0,0,AA71/Z71) -> 0 | AC71: 200 | AD71: 224109 | AE71: =IF(AC71=0,0,AD71/AC71) -> 1120.545 | AH71: =IF(AF71=0,0,AG71/AF71) -> 0 | AI71: =Z71+AC71+AF71 -> 200 | AJ71: =AA71+AD71+AG71 -> 224109 | AK71: =IF(AI71=0,0,AJ71/AI71) -> 1120.545 | AN71: =IF(AL71=0,0,AM71/AL71) -> 0 | AQ71: =IF(AO71=0,0,AP71/AO71) -> 0 | AT71: =IF(AR71=0,0,AS71/AR71) -> 0 | AU71: =AL71+AO71+AR71 -> 0 | AV71: =AM71+AP71+AS71 -> 0 | AW71: =IF(AU71=0,0,AV71/AU71) -> 0 | AX71: =K71+W71+AI71+AU71 -> 2081 | AY71: =L71+X71+AJ71+AV71 -> 2331273 | AZ71: =IF(AX71=0,0,AY71/AX71) -> 1120.2657
A72: YUNO-MSRLONG2 | T72: 4 | U72: 31398 | V72: =IF(T72=0,0,U72/T72) -> 7849.5
A73: YUNO-SCANNER1D | B73: 0 | C73: 0 | D73: =IF(B73=0,0,C73/B73) -> 0 | E73: 0 | F73: 0 | G73: =IF(E73=0,0,F73/E73) -> 0 | H73: 0 | I73: 0 | J73: =IF(H73=0,0,I73/H73) -> 0 | K73: =B73+E73+H73 -> 0 | L73: =C73+F73+I73 -> 0 | M73: =IF(K73=0,0,L73/K73) -> 0 | N73: 5 | O73: 9857 | P73: =IF(N73=0,0,O73/N73) -> 1971.4 | Q73: 2 | R73: 3912 | S73: =IF(Q73=0,0,R73/Q73) -> 1956 | V73: =IF(T73=0,0,U73/T73) -> 0 | W73: =N73+Q73+T73 -> 7 | X73: =O73+R73+U73 -> 13769 | Y73: =IF(W73=0,0,X73/W73) -> 1967 | AB73: =IF(Z73=0,0,AA73/Z73) -> 0 | AE73: =IF(AC73=0,0,AD73/AC73) -> 0 | AH73: =IF(AF73=0,0,AG73/AF73) -> 0 | AI73: =Z73+AC73+AF73 -> 0 | AJ73: =AA73+AD73+AG73 -> 0 | AK73: =IF(AI73=0,0,AJ73/AI73) -> 0 | AN73: =IF(AL73=0,0,AM73/AL73) -> 0 | AQ73: =IF(AO73=0,0,AP73/AO73) -> 0 | AT73: =IF(AR73=0,0,AS73/AR73) -> 0 | AU73: =AL73+AO73+AR73 -> 0 | AV73: =AM73+AP73+AS73 -> 0 | AW73: =IF(AU73=0,0,AV73/AU73) -> 0 | AX73: =K73+W73+AI73+AU73 -> 7 | AY73: =L73+X73+AJ73+AV73 -> 13769 | AZ73: =IF(AX73=0,0,AY73/AX73) -> 1967
A74: YUNO-SCANNER2D | B74: 150 | C74: 718725 | D74: =IF(B74=0,0,C74/B74) -> 4791.5 | E74: 50 | F74: 234487 | G74: =IF(E74=0,0,F74/E74) -> 4689.74 | H74: 30 | I74: 138555 | J74: =IF(H74=0,0,I74/H74) -> 4618.5 | K74: =B74+E74+H74 -> 230 | L74: =C74+F74+I74 -> 1091767 | M74: =IF(K74=0,0,L74/K74) -> 4746.813 | N74: 1 | O74: 4550 | P74: =IF(N74=0,0,O74/N74) -> 4550 | Q74: 180 | R74: 813209 | S74: =IF(Q74=0,0,R74/Q74) -> 4517.8278 | V74: =IF(T74=0,0,U74/T74) -> 0 | W74: =N74+Q74+T74 -> 181 | X74: =O74+R74+U74 -> 817759 | Y74: =IF(W74=0,0,X74/W74) -> 4518.0055 | AB74: =IF(Z74=0,0,AA74/Z74) -> 0 | AC74: 30 | AD74: 136282 | AE74: =IF(AC74=0,0,AD74/AC74) -> 4542.7333 | AH74: =IF(AF74=0,0,AG74/AF74) -> 0 | AI74: =Z74+AC74+AF74 -> 30 | AJ74: =AA74+AD74+AG74 -> 136282 | AK74: =IF(AI74=0,0,AJ74/AI74) -> 4542.7333 | AN74: =IF(AL74=0,0,AM74/AL74) -> 0 | AQ74: =IF(AO74=0,0,AP74/AO74) -> 0 | AT74: =IF(AR74=0,0,AS74/AR74) -> 0 | AU74: =AL74+AO74+AR74 -> 0 | AV74: =AM74+AP74+AS74 -> 0 | AW74: =IF(AU74=0,0,AV74/AU74) -> 0 | AX74: =K74+W74+AI74+AU74 -> 441 | AY74: =L74+X74+AJ74+AV74 -> 2045808 | AZ74: =IF(AX74=0,0,AY74/AX74) -> 4639.0204
A75: YUNO-ADDIMAT | D75: =IF(B75=0,0,C75/B75) -> 0 | G75: =IF(E75=0,0,F75/E75) -> 0 | J75: =IF(H75=0,0,I75/H75) -> 0 | K75: =B75+E75+H75 -> 0 | L75: =C75+F75+I75 -> 0 | M75: =IF(K75=0,0,L75/K75) -> 0 | N75: 300 | O75: 289437 | P75: =IF(N75=0,0,O75/N75) -> 964.79 | S75: =IF(Q75=0,0,R75/Q75) -> 0 | V75: =IF(T75=0,0,U75/T75) -> 0 | W75: =N75+Q75+T75 -> 300 | X75: =O75+R75+U75 -> 289437 | Y75: =IF(W75=0,0,X75/W75) -> 964.79 | AB75: =IF(Z75=0,0,AA75/Z75) -> 0 | AE75: =IF(AC75=0,0,AD75/AC75) -> 0 | AH75: =IF(AF75=0,0,AG75/AF75) -> 0 | AI75: =Z75+AC75+AF75 -> 0 | AJ75: =AA75+AD75+AG75 -> 0 | AK75: =IF(AI75=0,0,AJ75/AI75) -> 0 | AN75: =IF(AL75=0,0,AM75/AL75) -> 0 | AQ75: =IF(AO75=0,0,AP75/AO75) -> 0 | AT75: =IF(AR75=0,0,AS75/AR75) -> 0 | AU75: =AL75+AO75+AR75 -> 0 | AV75: =AM75+AP75+AS75 -> 0 | AW75: =IF(AU75=0,0,AV75/AU75) -> 0 | AX75: =K75+W75+AI75+AU75 -> 300 | AY75: =L75+X75+AJ75+AV75 -> 289437 | AZ75: =IF(AX75=0,0,AY75/AX75) -> 964.79
A76: YUNO-DALLAS | B76: 50 | C76: 65323 | D76: =IF(B76=0,0,C76/B76) -> 1306.46 | G76: =IF(E76=0,0,F76/E76) -> 0 | J76: =IF(H76=0,0,I76/H76) -> 0 | K76: =B76+E76+H76 -> 50 | L76: =C76+F76+I76 -> 65323 | M76: =IF(K76=0,0,L76/K76) -> 1306.46 | N76: 200 | O76: 248726 | P76: =IF(N76=0,0,O76/N76) -> 1243.63 | Q76: 180 | R76: 222359 | S76: =IF(Q76=0,0,R76/Q76) -> 1235.3278 | T76: 50 | U76: 61562 | V76: =IF(T76=0,0,U76/T76) -> 1231.24 | W76: =N76+Q76+T76 -> 430 | X76: =O76+R76+U76 -> 532647 | Y76: =IF(W76=0,0,X76/W76) -> 1238.714 | AB76: =IF(Z76=0,0,AA76/Z76) -> 0 | AC76: 150 | AD76: 185534 | AE76: =IF(AC76=0,0,AD76/AC76) -> 1236.8933 | AH76: =IF(AF76=0,0,AG76/AF76) -> 0 | AI76: =Z76+AC76+AF76 -> 150 | AJ76: =AA76+AD76+AG76 -> 185534 | AK76: =IF(AI76=0,0,AJ76/AI76) -> 1236.8933 | AN76: =IF(AL76=0,0,AM76/AL76) -> 0 | AQ76: =IF(AO76=0,0,AP76/AO76) -> 0 | AT76: =IF(AR76=0,0,AS76/AR76) -> 0 | AU76: =AL76+AO76+AR76 -> 0 | AV76: =AM76+AP76+AS76 -> 0 | AW76: =IF(AU76=0,0,AV76/AU76) -> 0 | AX76: =K76+W76+AI76+AU76 -> 630 | AY76: =L76+X76+AJ76+AV76 -> 783504 | AZ76: =IF(AX76=0,0,AY76/AX76) -> 1243.6571
A77: YUNO-MPC | D77: =IF(B77=0,0,C77/B77) -> 0 | G77: =IF(E77=0,0,F77/E77) -> 0 | H77: 500 | I77: 3587035 | J77: =IF(H77=0,0,I77/H77) -> 7174.07 | K77: =B77+E77+H77 -> 500 | L77: =C77+F77+I77 -> 3587035 | M77: =IF(K77=0,0,L77/K77) -> 7174.07 | P77: =IF(N77=0,0,O77/N77) -> 0 | S77: =IF(Q77=0,0,R77/Q77) -> 0 | V77: =IF(T77=0,0,U77/T77) -> 0 | W77: =N77+Q77+T77 -> 0 | X77: =O77+R77+U77 -> 0 | Y77: =IF(W77=0,0,X77/W77) -> 0 | AB77: =IF(Z77=0,0,AA77/Z77) -> 0 | AE77: =IF(AC77=0,0,AD77/AC77) -> 0 | AH77: =IF(AF77=0,0,AG77/AF77) -> 0 | AI77: =Z77+AC77+AF77 -> 0 | AJ77: =AA77+AD77+AG77 -> 0 | AK77: =IF(AI77=0,0,AJ77/AI77) -> 0 | AN77: =IF(AL77=0,0,AM77/AL77) -> 0 | AQ77: =IF(AO77=0,0,AP77/AO77) -> 0 | AT77: =IF(AR77=0,0,AS77/AR77) -> 0 | AU77: =AL77+AO77+AR77 -> 0 | AV77: =AM77+AP77+AS77 -> 0 | AW77: =IF(AU77=0,0,AV77/AU77) -> 0 | AX77: =K77+W77+AI77+AU77 -> 500 | AY77: =L77+X77+AJ77+AV77 -> 3587035 | AZ77: =IF(AX77=0,0,AY77/AX77) -> 7174.07
A78: YUNO-UPS | D78: =IF(B78=0,0,C78/B78) -> 0 | G78: =IF(E78=0,0,F78/E78) -> 0 | J78: =IF(H78=0,0,I78/H78) -> 0 | K78: =B78+E78+H78 -> 0 | L78: =C78+F78+I78 -> 0 | M78: =IF(K78=0,0,L78/K78) -> 0 | P78: =IF(N78=0,0,O78/N78) -> 0 | S78: =IF(Q78=0,0,R78/Q78) -> 0 | V78: =IF(T78=0,0,U78/T78) -> 0 | W78: =N78+Q78+T78 -> 0 | X78: =O78+R78+U78 -> 0 | Y78: =IF(W78=0,0,X78/W78) -> 0 | AB78: =IF(Z78=0,0,AA78/Z78) -> 0 | AE78: =IF(AC78=0,0,AD78/AC78) -> 0 | AH78: =IF(AF78=0,0,AG78/AF78) -> 0 | AI78: =Z78+AC78+AF78 -> 0 | AJ78: =AA78+AD78+AG78 -> 0 | AK78: =IF(AI78=0,0,AJ78/AI78) -> 0 | AN78: =IF(AL78=0,0,AM78/AL78) -> 0 | AQ78: =IF(AO78=0,0,AP78/AO78) -> 0 | AT78: =IF(AR78=0,0,AS78/AR78) -> 0 | AU78: =AL78+AO78+AR78 -> 0 | AV78: =AM78+AP78+AS78 -> 0 | AW78: =IF(AU78=0,0,AV78/AU78) -> 0 | AX78: =K78+W78+AI78+AU78 -> 0 | AY78: =L78+X78+AJ78+AV78 -> 0 | AZ78: =IF(AX78=0,0,AY78/AX78) -> 0
A79: YUNO-101PT | B79: 1 | C79: 5714 | D79: =IF(B79=0,0,C79/B79) -> 5714 | G79: =IF(E79=0,0,F79/E79) -> 0 | H79: 1 | I79: 5481 | J79: =IF(H79=0,0,I79/H79) -> 5481 | K79: =B79+E79+H79 -> 2 | L79: =C79+F79+I79 -> 11195 | M79: =IF(K79=0,0,L79/K79) -> 5597.5 | P79: =IF(N79=0,0,O79/N79) -> 0 | S79: =IF(Q79=0,0,R79/Q79) -> 0 | V79: =IF(T79=0,0,U79/T79) -> 0 | W79: =N79+Q79+T79 -> 0 | X79: =O79+R79+U79 -> 0 | Y79: =IF(W79=0,0,X79/W79) -> 0 | AB79: =IF(Z79=0,0,AA79/Z79) -> 0 | AE79: =IF(AC79=0,0,AD79/AC79) -> 0 | AH79: =IF(AF79=0,0,AG79/AF79) -> 0 | AI79: =Z79+AC79+AF79 -> 0 | AJ79: =AA79+AD79+AG79 -> 0 | AK79: =IF(AI79=0,0,AJ79/AI79) -> 0 | AN79: =IF(AL79=0,0,AM79/AL79) -> 0 | AQ79: =IF(AO79=0,0,AP79/AO79) -> 0 | AT79: =IF(AR79=0,0,AS79/AR79) -> 0 | AU79: =AL79+AO79+AR79 -> 0 | AV79: =AM79+AP79+AS79 -> 0 | AW79: =IF(AU79=0,0,AV79/AU79) -> 0 | AX79: =K79+W79+AI79+AU79 -> 2 | AY79: =L79+X79+AJ79+AV79 -> 11195 | AZ79: =IF(AX79=0,0,AY79/AX79) -> 5597.5
A80: YUNO-RS232 | D80: =IF(B80=0,0,C80/B80) -> 0 | G80: =IF(E80=0,0,F80/E80) -> 0 | J80: =IF(H80=0,0,I80/H80) -> 0 | K80: =B80+E80+H80 -> 0 | L80: =C80+F80+I80 -> 0 | M80: =IF(K80=0,0,L80/K80) -> 0 | P80: =IF(N80=0,0,O80/N80) -> 0 | S80: =IF(Q80=0,0,R80/Q80) -> 0 | V80: =IF(T80=0,0,U80/T80) -> 0 | W80: =N80+Q80+T80 -> 0 | X80: =O80+R80+U80 -> 0 | Y80: =IF(W80=0,0,X80/W80) -> 0 | AB80: =IF(Z80=0,0,AA80/Z80) -> 0 | AE80: =IF(AC80=0,0,AD80/AC80) -> 0 | AH80: =IF(AF80=0,0,AG80/AF80) -> 0 | AI80: =Z80+AC80+AF80 -> 0 | AJ80: =AA80+AD80+AG80 -> 0 | AK80: =IF(AI80=0,0,AJ80/AI80) -> 0 | AN80: =IF(AL80=0,0,AM80/AL80) -> 0 | AQ80: =IF(AO80=0,0,AP80/AO80) -> 0 | AT80: =IF(AR80=0,0,AS80/AR80) -> 0 | AU80: =AL80+AO80+AR80 -> 0 | AV80: =AM80+AP80+AS80 -> 0 | AW80: =IF(AU80=0,0,AV80/AU80) -> 0 | AX80: =K80+W80+AI80+AU80 -> 0 | AY80: =L80+X80+AJ80+AV80 -> 0 | AZ80: =IF(AX80=0,0,AY80/AX80) -> 0
A81: SAMPLE:BD-156 | D81: =IF(B81=0,0,C81/B81) -> 0 | E81: 1 | F81: 12130 | G81: =IF(E81=0,0,F81/E81) -> 12130 | J81: =IF(H81=0,0,I81/H81) -> 0 | K81: =B81+E81+H81 -> 1 | L81: =C81+F81+I81 -> 12130 | M81: =IF(K81=0,0,L81/K81) -> 12130 | P81: =IF(N81=0,0,O81/N81) -> 0 | S81: =IF(Q81=0,0,R81/Q81) -> 0 | V81: =IF(T81=0,0,U81/T81) -> 0 | W81: =N81+Q81+T81 -> 0 | X81: =O81+R81+U81 -> 0 | Y81: =IF(W81=0,0,X81/W81) -> 0 | AB81: =IF(Z81=0,0,AA81/Z81) -> 0 | AE81: =IF(AC81=0,0,AD81/AC81) -> 0 | AH81: =IF(AF81=0,0,AG81/AF81) -> 0 | AI81: =Z81+AC81+AF81 -> 0 | AJ81: =AA81+AD81+AG81 -> 0 | AK81: =IF(AI81=0,0,AJ81/AI81) -> 0 | AN81: =IF(AL81=0,0,AM81/AL81) -> 0 | AQ81: =IF(AO81=0,0,AP81/AO81) -> 0 | AT81: =IF(AR81=0,0,AS81/AR81) -> 0 | AU81: =AL81+AO81+AR81 -> 0 | AV81: =AM81+AP81+AS81 -> 0 | AW81: =IF(AU81=0,0,AV81/AU81) -> 0 | AX81: =K81+W81+AI81+AU81 -> 1 | AY81: =L81+X81+AJ81+AV81 -> 12130 | AZ81: =IF(AX81=0,0,AY81/AX81) -> 12130
A82: YUNO-PUHe | D82: =IF(B82=0,0,C82/B82) -> 0 | G82: =IF(E82=0,0,F82/E82) -> 0 | H82: 6 | I82: 18211 | J82: =IF(H82=0,0,I82/H82) -> 3035.1667 | K82: =B82+E82+H82 -> 6 | L82: =C82+F82+I82 -> 18211 | M82: =IF(K82=0,0,L82/K82) -> 3035.1667 | P82: =IF(N82=0,0,O82/N82) -> 0 | S82: =IF(Q82=0,0,R82/Q82) -> 0 | V82: =IF(T82=0,0,U82/T82) -> 0 | W82: =N82+Q82+T82 -> 0 | X82: =O82+R82+U82 -> 0 | Y82: =IF(W82=0,0,X82/W82) -> 0 | AB82: =IF(Z82=0,0,AA82/Z82) -> 0 | AE82: =IF(AC82=0,0,AD82/AC82) -> 0 | AH82: =IF(AF82=0,0,AG82/AF82) -> 0 | AI82: =Z82+AC82+AF82 -> 0 | AJ82: =AA82+AD82+AG82 -> 0 | AK82: =IF(AI82=0,0,AJ82/AI82) -> 0 | AN82: =IF(AL82=0,0,AM82/AL82) -> 0 | AQ82: =IF(AO82=0,0,AP82/AO82) -> 0 | AT82: =IF(AR82=0,0,AS82/AR82) -> 0 | AU82: =AL82+AO82+AR82 -> 0 | AV82: =AM82+AP82+AS82 -> 0 | AW82: =IF(AU82=0,0,AV82/AU82) -> 0 | AX82: =K82+W82+AI82+AU82 -> 6 | AY82: =L82+X82+AJ82+AV82 -> 18211 | AZ82: =IF(AX82=0,0,AY82/AX82) -> 3035.1667
A83: YUNO-101P+5M | D83: =IF(B83=0,0,C83/B83) -> 0 | G83: =IF(E83=0,0,F83/E83) -> 0 | H83: 1 | I83: 4280 | J83: =IF(H83=0,0,I83/H83) -> 4280 | K83: =B83+E83+H83 -> 1 | L83: =C83+F83+I83 -> 4280 | M83: =IF(K83=0,0,L83/K83) -> 4280 | P83: =IF(N83=0,0,O83/N83) -> 0 | S83: =IF(Q83=0,0,R83/Q83) -> 0 | V83: =IF(T83=0,0,U83/T83) -> 0 | W83: =N83+Q83+T83 -> 0 | X83: =O83+R83+U83 -> 0 | Y83: =IF(W83=0,0,X83/W83) -> 0 | AB83: =IF(Z83=0,0,AA83/Z83) -> 0 | AE83: =IF(AC83=0,0,AD83/AC83) -> 0 | AH83: =IF(AF83=0,0,AG83/AF83) -> 0 | AI83: =Z83+AC83+AF83 -> 0 | AJ83: =AA83+AD83+AG83 -> 0 | AK83: =IF(AI83=0,0,AJ83/AI83) -> 0 | AN83: =IF(AL83=0,0,AM83/AL83) -> 0 | AQ83: =IF(AO83=0,0,AP83/AO83) -> 0 | AT83: =IF(AR83=0,0,AS83/AR83) -> 0 | AU83: =AL83+AO83+AR83 -> 0 | AV83: =AM83+AP83+AS83 -> 0 | AW83: =IF(AU83=0,0,AV83/AU83) -> 0 | AX83: =K83+W83+AI83+AU83 -> 1 | AY83: =L83+X83+AJ83+AV83 -> 4280 | AZ83: =IF(AX83=0,0,AY83/AX83) -> 4280
A84: YUNO-101PAG | D84: =IF(B84=0,0,C84/B84) -> 0 | G84: =IF(E84=0,0,F84/E84) -> 0 | H84: 1 | I84: 4280 | J84: =IF(H84=0,0,I84/H84) -> 4280 | K84: =B84+E84+H84 -> 1 | L84: =C84+F84+I84 -> 4280 | M84: =IF(K84=0,0,L84/K84) -> 4280 | N84: 1 | O84: 4280 | P84: =IF(N84=0,0,O84/N84) -> 4280 | S84: =IF(Q84=0,0,R84/Q84) -> 0 | V84: =IF(T84=0,0,U84/T84) -> 0 | W84: =N84+Q84+T84 -> 1 | X84: =O84+R84+U84 -> 4280 | Y84: =IF(W84=0,0,X84/W84) -> 4280 | AB84: =IF(Z84=0,0,AA84/Z84) -> 0 | AE84: =IF(AC84=0,0,AD84/AC84) -> 0 | AH84: =IF(AF84=0,0,AG84/AF84) -> 0 | AI84: =Z84+AC84+AF84 -> 0 | AJ84: =AA84+AD84+AG84 -> 0 | AK84: =IF(AI84=0,0,AJ84/AI84) -> 0 | AN84: =IF(AL84=0,0,AM84/AL84) -> 0 | AQ84: =IF(AO84=0,0,AP84/AO84) -> 0 | AT84: =IF(AR84=0,0,AS84/AR84) -> 0 | AU84: =AL84+AO84+AR84 -> 0 | AV84: =AM84+AP84+AS84 -> 0 | AW84: =IF(AU84=0,0,AV84/AU84) -> 0 | AX84: =K84+W84+AI84+AU84 -> 2 | AY84: =L84+X84+AJ84+AV84 -> 8560 | AZ84: =IF(AX84=0,0,AY84/AX84) -> 4280
A85: YUNO-HUB-USB | D85: =IF(B85=0,0,C85/B85) -> 0 | G85: =IF(E85=0,0,F85/E85) -> 0 | J85: =IF(H85=0,0,I85/H85) -> 0 | K85: =B85+E85+H85 -> 0 | L85: =C85+F85+I85 -> 0 | M85: =IF(K85=0,0,L85/K85) -> 0 | N85: 253 | O85: 756456 | P85: =IF(N85=0,0,O85/N85) -> 2989.9447 | Q85: 750 | R85: 2225073 | S85: =IF(Q85=0,0,R85/Q85) -> 2966.764 | T85: 800 | U85: 2380904 | V85: =IF(T85=0,0,U85/T85) -> 2976.13 | W85: =N85+Q85+T85 -> 1803 | X85: =O85+R85+U85 -> 5362433 | Y85: =IF(W85=0,0,X85/W85) -> 2974.1725 | AB85: =IF(Z85=0,0,AA85/Z85) -> 0 | AE85: =IF(AC85=0,0,AD85/AC85) -> 0 | AH85: =IF(AF85=0,0,AG85/AF85) -> 0 | AI85: =Z85+AC85+AF85 -> 0 | AJ85: =AA85+AD85+AG85 -> 0 | AK85: =IF(AI85=0,0,AJ85/AI85) -> 0 | AN85: =IF(AL85=0,0,AM85/AL85) -> 0 | AQ85: =IF(AO85=0,0,AP85/AO85) -> 0 | AT85: =IF(AR85=0,0,AS85/AR85) -> 0 | AU85: =AL85+AO85+AR85 -> 0 | AV85: =AM85+AP85+AS85 -> 0 | AW85: =IF(AU85=0,0,AV85/AU85) -> 0 | AX85: =K85+W85+AI85+AU85 -> 1803 | AY85: =L85+X85+AJ85+AV85 -> 5362433 | AZ85: =IF(AX85=0,0,AY85/AX85) -> 2974.1725
A86: HUB-RETAIL-KL17 | D86: =IF(B86=0,0,C86/B86) -> 0 | G86: =IF(E86=0,0,F86/E86) -> 0 | J86: =IF(H86=0,0,I86/H86) -> 0 | K86: =B86+E86+H86 -> 0 | L86: =C86+F86+I86 -> 0 | M86: =IF(K86=0,0,L86/K86) -> 0 | P86: =IF(N86=0,0,O86/N86) -> 0 | S86: =IF(Q86=0,0,R86/Q86) -> 0 | V86: =IF(T86=0,0,U86/T86) -> 0 | W86: =N86+Q86+T86 -> 0 | X86: =O86+R86+U86 -> 0 | Y86: =IF(W86=0,0,X86/W86) -> 0 | Z86: 1800 | AA86: 5385425 | AB86: =IF(Z86=0,0,AA86/Z86) -> 2991.9028 | AE86: =IF(AC86=0,0,AD86/AC86) -> 0 | AH86: =IF(AF86=0,0,AG86/AF86) -> 0 | AI86: =Z86+AC86+AF86 -> 1800 | AJ86: =AA86+AD86+AG86 -> 5385425 | AK86: =IF(AI86=0,0,AJ86/AI86) -> 2991.9028 | AN86: =IF(AL86=0,0,AM86/AL86) -> 0 | AQ86: =IF(AO86=0,0,AP86/AO86) -> 0 | AT86: =IF(AR86=0,0,AS86/AR86) -> 0 | AU86: =AL86+AO86+AR86 -> 0 | AV86: =AM86+AP86+AS86 -> 0 | AW86: =IF(AU86=0,0,AV86/AU86) -> 0 | AX86: =K86+W86+AI86+AU86 -> 1800 | AY86: =L86+X86+AJ86+AV86 -> 5385425 | AZ86: =IF(AX86=0,0,AY86/AX86) -> 2991.9028
A87: YUNO151-STAND-SP | D87: =IF(B87=0,0,C87/B87) -> 0 | G87: =IF(E87=0,0,F87/E87) -> 0 | J87: =IF(H87=0,0,I87/H87) -> 0 | K87: =B87+E87+H87 -> 0 | L87: =C87+F87+I87 -> 0 | M87: =IF(K87=0,0,L87/K87) -> 0 | P87: =IF(N87=0,0,O87/N87) -> 0 | S87: =IF(Q87=0,0,R87/Q87) -> 0 | V87: =IF(T87=0,0,U87/T87) -> 0 | W87: =N87+Q87+T87 -> 0 | X87: =O87+R87+U87 -> 0 | Y87: =IF(W87=0,0,X87/W87) -> 0 | AB87: =IF(Z87=0,0,AA87/Z87) -> 0 | AC87: 200 | AD87: 137872 | AE87: =IF(AC87=0,0,AD87/AC87) -> 689.36 | AH87: =IF(AF87=0,0,AG87/AF87) -> 0 | AI87: =Z87+AC87+AF87 -> 200 | AJ87: =AA87+AD87+AG87 -> 137872 | AK87: =IF(AI87=0,0,AJ87/AI87) -> 689.36 | AN87: =IF(AL87=0,0,AM87/AL87) -> 0 | AQ87: =IF(AO87=0,0,AP87/AO87) -> 0 | AT87: =IF(AR87=0,0,AS87/AR87) -> 0 | AU87: =AL87+AO87+AR87 -> 0 | AV87: =AM87+AP87+AS87 -> 0 | AW87: =IF(AU87=0,0,AV87/AU87) -> 0 | AX87: =K87+W87+AI87+AU87 -> 200 | AY87: =L87+X87+AJ87+AV87 -> 137872 | AZ87: =IF(AX87=0,0,AY87/AX87) -> 689.36
A88: YUNO-BASE151 ASSY | D88: =IF(B88=0,0,C88/B88) -> 0 | G88: =IF(E88=0,0,F88/E88) -> 0 | J88: =IF(H88=0,0,I88/H88) -> 0 | K88: =B88+E88+H88 -> 0 | L88: =C88+F88+I88 -> 0 | M88: =IF(K88=0,0,L88/K88) -> 0 | P88: =IF(N88=0,0,O88/N88) -> 0 | S88: =IF(Q88=0,0,R88/Q88) -> 0 | V88: =IF(T88=0,0,U88/T88) -> 0 | W88: =N88+Q88+T88 -> 0 | X88: =O88+R88+U88 -> 0 | Y88: =IF(W88=0,0,X88/W88) -> 0 | AB88: =IF(Z88=0,0,AA88/Z88) -> 0 | AC88: 150 | AD88: 19075 | AE88: =IF(AC88=0,0,AD88/AC88) -> 127.16667 | AH88: =IF(AF88=0,0,AG88/AF88) -> 0 | AI88: =Z88+AC88+AF88 -> 150 | AJ88: =AA88+AD88+AG88 -> 19075 | AK88: =IF(AI88=0,0,AJ88/AI88) -> 127.16667 | AN88: =IF(AL88=0,0,AM88/AL88) -> 0 | AQ88: =IF(AO88=0,0,AP88/AO88) -> 0 | AT88: =IF(AR88=0,0,AS88/AR88) -> 0 | AU88: =AL88+AO88+AR88 -> 0 | AV88: =AM88+AP88+AS88 -> 0 | AW88: =IF(AU88=0,0,AV88/AU88) -> 0 | AX88: =K88+W88+AI88+AU88 -> 150 | AY88: =L88+X88+AJ88+AV88 -> 19075 | AZ88: =IF(AX88=0,0,AY88/AX88) -> 127.16667
A89: YUNO-BASE156 ASSY | D89: =IF(B89=0,0,C89/B89) -> 0 | G89: =IF(E89=0,0,F89/E89) -> 0 | J89: =IF(H89=0,0,I89/H89) -> 0 | K89: =B89+E89+H89 -> 0 | L89: =C89+F89+I89 -> 0 | M89: =IF(K89=0,0,L89/K89) -> 0 | P89: =IF(N89=0,0,O89/N89) -> 0 | S89: =IF(Q89=0,0,R89/Q89) -> 0 | V89: =IF(T89=0,0,U89/T89) -> 0 | W89: =N89+Q89+T89 -> 0 | X89: =O89+R89+U89 -> 0 | Y89: =IF(W89=0,0,X89/W89) -> 0 | AB89: =IF(Z89=0,0,AA89/Z89) -> 0 | AC89: 250 | AD89: 28100 | AE89: =IF(AC89=0,0,AD89/AC89) -> 112.4 | AH89: =IF(AF89=0,0,AG89/AF89) -> 0 | AI89: =Z89+AC89+AF89 -> 250 | AJ89: =AA89+AD89+AG89 -> 28100 | AK89: =IF(AI89=0,0,AJ89/AI89) -> 112.4 | AN89: =IF(AL89=0,0,AM89/AL89) -> 0 | AQ89: =IF(AO89=0,0,AP89/AO89) -> 0 | AT89: =IF(AR89=0,0,AS89/AR89) -> 0 | AU89: =AL89+AO89+AR89 -> 0 | AV89: =AM89+AP89+AS89 -> 0 | AW89: =IF(AU89=0,0,AV89/AU89) -> 0 | AX89: =K89+W89+AI89+AU89 -> 250 | AY89: =L89+X89+AJ89+AV89 -> 28100 | AZ89: =IF(AX89=0,0,AY89/AX89) -> 112.4
D90: =IF(B90=0,0,C90/B90) -> 0 | G90: =IF(E90=0,0,F90/E90) -> 0 | J90: =IF(H90=0,0,I90/H90) -> 0 | K90: =B90+E90+H90 -> 0 | L90: =C90+F90+I90 -> 0 | M90: =IF(K90=0,0,L90/K90) -> 0 | P90: =IF(N90=0,0,O90/N90) -> 0 | S90: =IF(Q90=0,0,R90/Q90) -> 0 | V90: =IF(T90=0,0,U90/T90) -> 0 | W90: =N90+Q90+T90 -> 0 | X90: =O90+R90+U90 -> 0 | Y90: =IF(W90=0,0,X90/W90) -> 0 | AB90: =IF(Z90=0,0,AA90/Z90) -> 0 | AE90: =IF(AC90=0,0,AD90/AC90) -> 0 | AH90: =IF(AF90=0,0,AG90/AF90) -> 0 | AI90: =Z90+AC90+AF90 -> 0 | AJ90: =AA90+AD90+AG90 -> 0 | AK90: =IF(AI90=0,0,AJ90/AI90) -> 0 | AN90: =IF(AL90=0,0,AM90/AL90) -> 0 | AQ90: =IF(AO90=0,0,AP90/AO90) -> 0 | AT90: =IF(AR90=0,0,AS90/AR90) -> 0 | AU90: =AL90+AO90+AR90 -> 0 | AV90: =AM90+AP90+AS90 -> 0 | AW90: =IF(AU90=0,0,AV90/AU90) -> 0 | AX90: =K90+W90+AI90+AU90 -> 0 | AY90: =L90+X90+AJ90+AV90 -> 0 | AZ90: =IF(AX90=0,0,AY90/AX90) -> 0
A91: 其他 | B91: 1148 | C91: 1509068 | D91: =IF(B91=0,0,C91/B91) -> 1314.5192 | E91: 512 | F91: 1817169 | G91: =IF(E91=0,0,F91/E91) -> 3549.1582 | H91: 43044 | I91: 2208418 | J91: =IF(H91=0,0,I91/H91) -> 51.306059 | K91: =B91+E91+H91 -> 44704 | L91: =C91+F91+I91 -> 5534655 | M91: =IF(K91=0,0,L91/K91) -> 123.80671 | N91: 1564 | O91: 2678200 | P91: =IF(N91=0,0,O91/N91) -> 1712.4041 | Q91: 1048 | R91: 1187265 | S91: =IF(Q91=0,0,R91/Q91) -> 1132.8865 | T91: 166212 | U91: 5165326 | V91: =IF(T91=0,0,U91/T91) -> 31.076733 | W91: =N91+Q91+T91 -> 168824 | X91: =O91+R91+U91 -> 9030791 | Y91: =IF(W91=0,0,X91/W91) -> 53.492341 | Z91: 620376 | AA91: 999325 | AB91: =IF(Z91=0,0,AA91/Z91) -> 1.6108376 | AC91: 2168 | AD91: 6831284 | AE91: =IF(AC91=0,0,AD91/AC91) -> 3150.9613 | AH91: =IF(AF91=0,0,AG91/AF91) -> 0 | AI91: =Z91+AC91+AF91 -> 622544 | AJ91: =AA91+AD91+AG91 -> 7830609 | AK91: =IF(AI91=0,0,AJ91/AI91) -> 12.578402 | AN91: =IF(AL91=0,0,AM91/AL91) -> 0 | AQ91: =IF(AO91=0,0,AP91/AO91) -> 0 | AT91: =IF(AR91=0,0,AS91/AR91) -> 0 | AU91: =AL91+AO91+AR91 -> 0 | AV91: =AM91+AP91+AS91 -> 0 | AW91: =IF(AU91=0,0,AV91/AU91) -> 0 | AX91: =K91+W91+AI91+AU91 -> 836072 | AY91: =L91+X91+AJ91+AV91 -> 22396055 | AZ91: =IF(AX91=0,0,AY91/AX91) -> 26.787232
A92: QCI(buy & sell) | K92: =B92+E92+H92 -> 0 | L92: =C92+F92+I92 -> 0 | M92: =IF(K92=0,0,L92/K92) -> 0 | W92: =N92+Q92+T92 -> 0 | X92: =O92+R92+U92 -> 0 | Y92: =IF(W92=0,0,X92/W92) -> 0 | AI92: =Z92+AC92+AF92 -> 0 | AJ92: =AA92+AD92+AG92 -> 0 | AK92: =IF(AI92=0,0,AJ92/AI92) -> 0 | AU92: =AL92+AO92+AR92 -> 0 | AV92: =AM92+AP92+AS92 -> 0 | AW92: =IF(AU92=0,0,AV92/AU92) -> 0 | AX92: =K92+W92+AI92+AU92 -> 0 | AY92: =L92+X92+AJ92+AV92 -> 0 | AZ92: =IF(AX92=0,0,AY92/AX92) -> 0
A93: 維修收入/勞務收入 | C93: =IS明細!D20 -> 3959 | D93: =IF(B93=0,0,C93/B93) -> 0 | F93: =IS明細!F20 -> 43786 | G93: =IF(E93=0,0,F93/E93) -> 0 | I93: =IS明細!H20 -> 27522 | J93: =IF(H93=0,0,I93/H93) -> 0 | K93: =B93+E93+H93 -> 0 | L93: =C93+F93+I93 -> 75267 | M93: =IF(K93=0,0,L93/K93) -> 0 | N93: 0 | O93: =IS明細!J20 -> 20986 | P93: =IF(N93=0,0,O93/N93) -> 0 | R93: =IS明細!L20 -> 43107 | S93: =IF(Q93=0,0,R93/Q93) -> 0 | T93: 0 | U93: =IS明細!N20 -> 81879 | V93: =IF(T93=0,0,U93/T93) -> 0 | W93: =N93+Q93+T93 -> 0 | X93: =O93+R93+U93 -> 145972 | Y93: =IF(W93=0,0,X93/W93) -> 0 | AA93: =IS明細!P20 -> 3539 | AB93: =IF(Z93=0,0,AA93/Z93) -> 0 | AD93: =IS明細!R20 -> 3539 | AE93: =IF(AC93=0,0,AD93/AC93) -> 0 | AG93: =IS明細!T20 -> 0 | AH93: =IF(AF93=0,0,AG93/AF93) -> 0 | AI93: =Z93+AC93+AF93 -> 0 | AJ93: =AA93+AD93+AG93 -> 7078 | AK93: =IF(AI93=0,0,AJ93/AI93) -> 0 | AM93: =IS明細!V20 -> 0 | AN93: =IF(AL93=0,0,AM93/AL93) -> 0 | AP93: =IS明細!X20 -> 0 | AQ93: =IF(AO93=0,0,AP93/AO93) -> 0 | AS93: =IS明細!Z20 -> 0 | AT93: =IF(AR93=0,0,AS93/AR93) -> 0 | AU93: =AL93+AO93+AR93 -> 0 | AV93: =AM93+AP93+AS93 -> 0 | AW93: =IF(AU93=0,0,AV93/AU93) -> 0 | AX93: =K93+W93+AI93+AU93 -> 0 | AY93: =L93+X93+AJ93+AV93 -> 228317 | AZ93: =IF(AX93=0,0,AY93/AX93) -> 0
B94: =SUM(B52:B93) -> 12953 | C94: =SUM(C52:C93) -> 60246951 | E94: =SUM(E52:E93) -> 10556 | F94: =SUM(F52:F93) -> 53071500 | H94: =SUM(H52:H93) -> 51985 | I94: =SUM(I52:I93) -> 63731970 | K94: =B94+E94+H94 -> 75494 | L94: =C94+F94+I94 -> 177050421 | N94: =SUM(N52:N93) -> 17069 | O94: =SUM(O52:O93) -> 67365680 | Q94: =SUM(Q52:Q93) -> 12731 | R94: =SUM(R52:R93) -> 53281343 | T94: =SUM(T52:T93) -> 183128 | U94: =SUM(U52:U93) -> 87487966 | W94: =N94+Q94+T94 -> 212928 | X94: =O94+R94+U94 -> 208134989 | Z94: =SUM(Z52:Z93) -> 638872 | AA94: =SUM(AA52:AA93) -> 98241166 | AC94: =SUM(AC52:AC93) -> 16256 | AD94: =SUM(AD52:AD93) -> 82134915 | AF94: =SUM(AF52:AF93) -> 0 | AG94: =SUM(AG52:AG93) -> 0 | AI94: =Z94+AC94+AF94 -> 655128 | AJ94: =AA94+AD94+AG94 -> 180376081 | AL94: =SUM(AL52:AL93) -> 0 | AM94: =SUM(AM52:AM93) -> 0 | AN94: =AM94/AL94 -> #DIV/0! | AO94: =SUM(AO52:AO93) -> 0 | AP94: =SUM(AP52:AP93) -> 0 | AR94: =SUM(AR52:AR93) -> 0 | AS94: =SUM(AS52:AS93) -> 0 | AU94: =AL94+AO94+AR94 -> 0 | AV94: =AM94+AP94+AS94 -> 0 | AX94: =K94+W94+AI94+AU94 -> 943550 | AY94: =L94+X94+AJ94+AV94 -> 565561491 | AZ94: =IF(AX94=0,0,AY94/AX94) -> 599.39748
C95: =IS明細!D21 -> 60246951 | F95: =IS明細!F21 -> 53071500 | I95: =IS明細!H21 -> 63731970 | O95: =IS明細!J21 -> 67365680 | R95: =IS明細!L21 -> 53281343 | U95: =IS明細!N21 -> 87487966 | AA95: =IS明細!P21 -> 98241166 | AD95: =IS明細!R21 -> 82134915 | AG95: =IS明細!T21 -> 0 | AM95: =IS明細!V21 -> 0 | AP95: =IS明細!X21 -> 0 | AS95: =IS明細!Z21 -> 0

Sheet Summary
A1: 賀毅科技股份有限公司
A2: 2017.08 營業狀況說明
A4: ( I ) 本月總營業淨額為 NT$ 82,134,915，營業淨利為 NT$2,522,739 3,07%，重大項目說明如下：
A5: (A) 本月營業毛利為 NT$ 11,184,271， 毛利率為 13.62%
B6: 排除本月提列存貨呆滯及跌價損失評價及存貨盤損合計 NT$23,984，本月毛利率為 13.65%，平均MVA為 24.03%，加工成本率為 6.45%，製造費用率為 4.04%，本月產品毛利率由以下組合而致：(1) Aures銷售佔比為 78.17%， MVA %為 22.67%，平均毛利率 12.30%，本月MVA較上月減少 0.37%。 (2) 台灣東芝 銷售佔比為 8.38%， MVA %為 21.84%，平均毛利率 8.254%，本月MVA較上月減少 0.14%。(3)排除ODM外之其他客戶銷售佔比 13.45%，MVA%為 33.29%，平均毛利率 24.05%，主要來自客戶：Olivetti S.p.A. XPOS755P*359pcs 與SPARE PARTS*120PCS銷售佔比 6.73 %，MVA%為 34.43%，平均毛利率 23.75% 及 宇辰光電 XPOS755P*100pcs 銷售佔比 1.71 %，MVA%為 31.84%，平均毛利率 24.05%。
B7: 本月存貨總額計 NT$1.70億較上月增加約 NT$200萬，備抵金額約 NT$1,946萬，本月存貨淨額增加約NTD220萬，係因原料減少約 NT$420萬、製成品增加約NT$975萬及在製品增加約NT$130萬及在途存貨減少約400萬，本月提列存貨呆滯損失約 NT$2萬，庫齡異動詳後附工作表「Inventory+AR Aging」。
B8: 主要客戶貢獻率分別如下：
B9: 主要客戶貢獻 : | C9: 前10大客戶佔營收約 100.00% | I9: YUNO-BASE156-WHITE+GRAY,LG+eTurbo,US CORD,ART-03256
C10: % of sales | D10: sales(仟元) | E10: G/P % | F10: GP
B11: =TWN_前十大客戶!C3 -> AURES Technologies SA | C11: =TWN_前十大客戶!N3 -> 78.052483 | D11: =TWN_前十大客戶!O3 -> 64106 | E11: =TWN_前十大客戶!F3 -> 12.377903 | F11: =C11/100*E11/100 -> 0.096612603
B12: =TWN_前十大客戶!C4 -> Olivetti S.p.A. | C12: =TWN_前十大客戶!N4 -> 6.6816864 | D12: =TWN_前十大客戶!O4 -> 5488 | E12: =TWN_前十大客戶!F4 -> 23.749121 | F12: =C12/100*E12/100 -> 0.015868418
B13: =TWN_前十大客戶!C5 -> 台灣東芝國際採購股份有限公司 | C13: =TWN_前十大客戶!N5 -> 8.3300224 | D13: =TWN_前十大客戶!O5 -> 6842 | E13: =TWN_前十大客戶!F5 -> 8.2663579 | F13: =C13/100*E13/100 -> 0.0068858946
B14: =TWN_前十大客戶!C6 -> 宇辰光電(股)公司 eTurbotouch Technology Inc. | C14: =TWN_前十大客戶!N6 -> 1.6933967 | D14: =TWN_前十大客戶!O6 -> 1391 | E14: =TWN_前十大客戶!F6 -> 24.054688 | F14: =C14/100*E14/100 -> 0.0040734128
B15: =TWN_前十大客戶!C7 -> EET Group A/S | C15: =TWN_前十大客戶!N7 -> 0.92040952 | D15: =TWN_前十大客戶!O7 -> 756 | E15: =TWN_前十大客戶!F7 -> 25.562839 | F15: =C15/100*E15/100 -> 0.002352828
B16: =TWN_前十大客戶!C8 -> Comtecs Co.,Ltd | C16: =TWN_前十大客戶!N8 -> 0.70089779 | D16: =TWN_前十大客戶!O8 -> 576 | E16: =TWN_前十大客戶!F8 -> 33.390543 | F16: =C16/100*E16/100 -> 0.0023403358
B17: =TWN_前十大客戶!C9 -> ABDI Company JSC | C17: =TWN_前十大客戶!N9 -> 0.50426405 | D17: =TWN_前十大客戶!O9 -> 414 | E17: =TWN_前十大客戶!F9 -> 33.305808 | F17: =C17/100*E17/100 -> 0.0016794921
B18: =TWN_前十大客戶!C10 -> Logitec INA Solutions Co., Ltd | C18: =TWN_前十大客戶!N10 -> 0.35487778 | D18: =TWN_前十大客戶!O10 -> 291 | E18: =TWN_前十大客戶!F10 -> 37.996885 | F18: =C18/100*E18/100 -> 0.001348425
B19: =TWN_前十大客戶!C11 -> Aniluin Pty Ltd | C19: =TWN_前十大客戶!N11 -> 0.84389795 | D19: =TWN_前十大客戶!O11 -> 693 | E19: =TWN_前十大客戶!F11 -> 11.989958 | F19: =C19/100*E19/100 -> 0.0010118301
B20: =TWN_前十大客戶!C12 -> DATA Detection Technologies LTD. | C20: =TWN_前十大客戶!N12 -> 0.34420098 | D20: =TWN_前十大客戶!O12 -> 283 | E20: =TWN_前十大客戶!F12 -> 25.978344 | F20: =C20/100*E20/100 -> 0.00089417715
B21: others(FC0等） | D21: 1295 | F21: =C21/100*E21/100 -> 0
F22: =SUM(F11:F21) -> 0.13306742
A24: (B) 本月營業費用計NT $8,661,532，較上月減少 NT$1,696,653，主要費用說明如下:
B25: (1) 銷售費用計 NT$3,586,817，較上月減少 NT$107,897。主要異動係上月支付Christina 佣金 XPOS755 USD9680*30.36 NTD293,885及出口費用較上個月增加 NTD147,583 ，其餘無重大差異。
B26: (2) 管理費用計 NT$1,755,224，較上月減少 NT$1,742,895。主要異動係上月支付人員獎金NTD1,679,368，其餘無重大差異。
B27: (3) 研發費用計 NT$3,319,491，較上月增加 NT$154,139。主要明廣151R2 NRE費 NTD274,050，其餘無重大變動。
A28: ( II ) 本月產生淨營業外支出計 NT$232,899，主要原因係：
A29: 八月底新台幣兌換美元較上月升值，月底AR評價匯率30.13，本月外幣資產及負債評價產生淨兌換利益 NT$35,806，額度動撥 NT$ 81,147,909 動撥期間產生利息費用 NT$117,626，代收運費多收及出租員工車位與利息收入計 NT$265,588，另應收帳款轉讓、押匯及匯款手續費支出 NT$416,667。

Sheet TWN_BS
A1: 賀毅科技股份有限公司
A2: 資產負債表
O3: 幣別:NTD 單位:元
A4: 資 產 | C4: 2017.08.31 | D4: % | E4: 2017.07.31 | F4: % | G4: 差異金額 | I4: 負債及股東權益 | K4: =C4 -> 2017.08.31 | L4: % | M4: 2017.07.31 | N4: % | O4: 差異金額
A5: 流動資產: | I5: 流動負債:
B6: 現金及約當現金 | C6: =BS明細!D10 -> 58535504 | D6: =C6/$C$40*100 -> 12.004409 | E6: 95648386 | F6: 22.306066 | G6: =C6-E6 -> -37112882 | J6: 短期借款 | K6: =BS明細!I10 -> 81147909 | L6: =K6/$K$40*100 -> 16.641742 | M6: 75469492 | N6: 13.599163 | O6: =K6-M6 -> 5678417
B7: 交易目的金融資產 | C7: =BS明細!D156 -> 0 | D7: =C7/$C$40*100 -> 0 | E7: 0 | F7: 0 | G7: =C7-E7 -> 0 | J7: 應付票據 | K7: =BS明細!I20 -> 70000 | L7: =K7/$K$40*100 -> 0.014355538 | M7: 70000 | N7: 0.016700726 | O7: =K7-M7 -> 0
B8: 交易目的金融資產評價調整 | C8: =BS明細!D157 -> 0 | D8: =C8/$C$40*100 -> 0 | E8: 0 | F8: 0 | G8: =C8-E8 -> 0 | J8: 應付帳款 | K8: =BS明細!I25 -> 123723496 | L8: =K8/$K$40*100 -> 25.373105 | M8: 135260921 | N8: 22.257465 | O8: =K8-M8 -> -11537425
B9: 應收票據 | C9: =BS明細!D93 -> 0 | D9: =C9/$C$40*100 -> 0 | E9: 0 | F9: 0 | G9: =C9-E9 -> 0 | J9: 應付費用 | K9: =BS明細!I34 -> 19855600 | L9: =K9/$K$40*100 -> 4.0719689 | M9: 18009185 | N9: 4.1922657 | O9: =K9-M9 -> 1846415
B10: 應收帳款 | C10: =BS明細!D104 -> 2.2163455e+08 | D10: =C10/$C$40*100 -> 45.452618 | E10: 1.8662021e+08 | F10: 32.056868 | G10: =C10-E10 -> 35014339 | J10: 預收款項 | K10: =BS明細!I57 -> 964763 | L10: =K10/$K$40*100 -> 0.19785274 | M10: 1229067 | N10: 0.92593336 | O10: =K10-M10 -> -264304
B11: 減：備抵呆帳 | C11: =BS明細!D110 -> 0 | D11: =C11/$C$40*100 -> 0 | E11: 0 | F11: -0.037348312 | G11: =C11-E11 -> 0 | J11: 其他流動負債 | K11: =BS明細!I49+BS明細!I56+BS明細!I63 -> 15941279 | L11: =K11/$K$40*100 -> 3.2692234 | M11: 15527672 | N11: 2.2934451 | O11: =K11-M11 -> 413607
B12: 存貨 | C12: =BS明細!D124 -> 1.5045077e+08 | D12: =C12/$C$40*100 -> 30.854311 | E12: 1.4817848e+08 | F12: 27.780762 | G12: =C12-E12 -> 2272294
B13: 預付款項 | C13: =BS明細!D136+BS明細!D144 -> 485063 | D13: =C13/$C$40*100 -> 0.099476292 | E13: 462973 | F13: 0.15206155 | G13: =C13-E13 -> 22090 | I13: 流動負債合計: | K13: =SUM(K6:K11) -> 2.4170305e+08 | L13: =K13/$K$40*100 -> 49.568248 | M13: 2.4556634e+08 | N13: 43.284973 | O13: =K13-M13 -> -3863290
B14: 遞延所得稅資產-流動 | C14: =BS明細!D155 -> 4102327 | D14: =C14/$C$40*100 -> 0.8413016 | E14: 4102327 | F14: 1.0024749 | G14: =C14-E14 -> 0
B15: 其他流動資產 | C15: =BS明細!D114+BS明細!D148+BS明細!D149+BS明細!D150+BS明細!D152+BS明細!D153 -> 7642333 | D15: =C15/$C$40*100 -> 1.5672829 | E15: 8907684 | F15: 1.5732435 | G15: =C15-E15 -> -1265351 | I15: 其他負債:
A16: 流動資產合計: | C16: =SUM(C6:C15) -> 4.4285055e+08 | D16: =C16/$C$40*100 -> 90.819399 | E16: 4.4392006e+08 | F16: 84.834127 | G16: =C16-E16 -> -1069510 | J16: 應計退休金負債 | K16: =BS明細!I90 -> 445883 | L16: =K16/$K$40*100 -> 0.091441292 | M16: 434655 | N16: 0.090934978 | O16: =K16-M16 -> 11228
J17: 遞延貨項-聯屬公司間利益 | K17: =BS明細!I97 -> 0 | L17: =K17/$K$40*100 -> 0 | M17: 0 | N17: 0 | O17: =K17-M17 -> 0
I18: 其他負債合計: | K18: =SUM(K16:K17) -> 445883 | L18: =K18/$K$40*100 -> 0.091441292 | M18: 434655 | N18: 0.090934978 | O18: =K18-M18 -> 11228
A20: 固定資產: | I20: 長期負債 | K20: 0 | L20: =K20/$K$40*100 -> 0 | M20: 0 | N20: 0 | O20: =K20-M20 -> 0
B21: 土地 | C21: =BS明細!D189 -> 21000000 | D21: =C21/$C$40*100 -> 4.3066615 | E21: 21000000 | F21: 5.0102179 | G21: =C21-E21 -> 0
B22: 建築物 | C22: =BS明細!D190 -> 13333333 | D22: =C22/$C$40*100 -> 2.7343882 | E22: 13333333 | F22: 3.1810907 | G22: =C22-E22 -> 0 | I22: 負債合計: | K22: =K13+K18+K20 -> 2.4214893e+08 | L22: =K22/$K$40*100 -> 49.659689 | M22: 2.4600099e+08 | N22: 43.375908 | O22: =K22-M22 -> -3852062
B23: 機器設備 | C23: =BS明細!D192 -> 5211496 | D23: =C23/$C$40*100 -> 1.068769 | E23: 5211496 | F23: 1.2433681 | G23: =C23-E23 -> 0
B24: 其他設備 | C24: =BS明細!D202 -> 737608 | D24: =C24/$C$40*100 -> 0.151268 | E24: 737608 | F24: 0.16031528 | G24: =C24-E24 -> 0
B25: 模具設備 | C25: =BS明細!D194 -> 72214363 | D25: =C25/$C$40*100 -> 14.809658 | E25: 72124363 | F25: 16.350098 | G25: =C25-E25 -> 90000 | I25: 股東權益:
B26: 運輸設備 | C26: =BS明細!D197 -> 0 | D26: =C26/$C$40*100 -> 0 | E26: 0 | F26: 0 | G26: =C26-E26 -> 0 | J26: 股本 | K26: =BS明細!I107+BS明細!I108 -> 335040000 | L26: =K26/$K$40*100 -> 68.709708 | M26: 335040000 | N26: 79.934448 | O26: =K26-M26 -> 0
B27: 辦公設備 | C27: =BS明細!D198 -> 1921174 | D27: =C27/$C$40*100 -> 0.39399267 | E27: 1921174 | F27: 0.45835716 | G27: =C27-E27 -> 0 | J27: 預收股本 | K27: =BS明細!I109 -> 0 | L27: =K27/$K$40*100 -> 0 | M27: 0 | N27: 0 | O27: =K27-M27 -> 0
B28: 租賃改良物 | C28: =BS明細!D200 -> 23141 | D28: =C28/$C$40*100 -> 0.0047457359 | E28: 23141 | F28: 0.0055210216 | G28: =C28-E28 -> 0 | I28: 資本公積:
B29: 減：累計折舊 | C29: =BS明細!D191+BS明細!D193+BS明細!D195+BS明細!D197+BS明細!D199+BS明細!D201+BS明細!D203 -> -77089889 | D29: =C29/$C$40*100 -> -15.809526 | E29: -75950273 | F29: -13.365158 | G29: =C29-E29 -> -1139616 | J29: 資本公積-發行溢價 | K29: =BS明細!I113 -> 20000 | L29: =K29/$K$40*100 -> 0.0041015824 | M29: 20000 | N29: 0.0047716361 | O29: =K29-M29 -> 0
B30: 預付設備款 | C30: =BS明細!D204 -> 1211484 | D30: =C30/$C$40*100 -> 0.24845007 | E30: 1007484 | F30: 0.038650253 | G30: =C30-E30 -> 204000 | I30: 保留盈餘
A31: 固定資產合計: | C31: =SUM(C21:C30) -> 38562710 | D31: =C31/$C$40*100 -> 7.9084065 | E31: 39408326 | F31: 13.08246 | G31: =C31-E31 -> -845616 | J31: 未發行股本 | K31: 0 | L31: =K31/$K$40*100 -> 0 | M31: 0 | N31: 0 | O31: =K31-M31 -> 0
J32: 法定盈餘公積 | K32: 0 | L32: =K32/$K$40*100 -> 0 | M32: 0 | N32: 0 | O32: =K32-M32 -> 0
J33: 累積盈虧 | K33: =BS明細!I125 -> -75978391 | L33: =K33/$K$40*100 -> -15.581581 | M33: -75978391 | N33: -26.140394 | O33: =K33-M33 -> 0
A34: 其他資產 | J34: 本期損益 | K34: =BS明細!I127 -> -13613852 | L34: =K34/$K$40*100 -> -2.7919168 | M34: -15903692 | N34: 2.8252667 | O34: =K34-M34 -> 2289840
B35: 存出保證金 | C35: =BS明細!D213 -> 82500 | D35: =C35/$C$40*100 -> 0.016919027 | E35: 82500 | F35: 0.022784562 | G35: =C35-E35 -> 0 | J35: 前期損益調整 | K35: =BS明細!I126 -> 0 | L35: =K35/$K$40*100 -> 0 | M35: 0 | N35: 0 | O35: =K35-M35 -> 0
B36: 遞延費用 | C36: =BS明細!D214 -> 1376465 | D36: =C36/$C$40*100 -> 0.28228423 | E36: 1023561 | F36: 0.68900851 | G36: =C36-E36 -> 352904 | J36: 累積換算調整數 | K36: =BS明細!I129 -> 0 | L36: =K36/$K$40*100 -> 0 | M36: 0 | N36: 0 | O36: =K36-M36 -> 0
B37: 遞延所得稅資產─非流動 | C37: =BS明細!D222 -> 4744466 | D37: =C37/$C$40*100 -> 0.9729909 | E37: 4744466 | F37: 1.3716194 | G37: =C37-E37 -> 0 | I37: 股東權益合計: | K37: =SUM(K26:K36) -> 2.4546776e+08 | L37: =K37/$K$40*100 -> 50.340311 | M37: 2.4317792e+08 | N37: 56.624092 | O37: =K37-M37 -> 2289840
A38: 其他資產合計 | C38: =SUM(C35:C37) -> 6203431 | D38: =C38/$C$40*100 -> 1.2721942 | E38: 5850527 | F38: 2.0834125 | G38: =C38-E38 -> 352904
A40: 資產總計: | C40: =C16+C18+C31+C38 -> 4.8761669e+08 | D40: =C40/$C$40*100 -> 100 | E40: 4.8917891e+08 | F40: 100 | G40: =C40-E40 -> -1562222 | I40: 負債及股東權益合計: | K40: =K22+K37 -> 4.8761669e+08 | L40: =K40/$K$40*100 -> 100 | M40: 4.8917891e+08 | N40: 100 | O40: =K40-M40 -> -1562222
J42: 每股淨值 | K42: =K37/33504000 -> 7.3265209

Sheet TWN_IS
A1: 賀毅科技股份有限公司
A2: 年度 : 2017
A3: 多月份損益表 | Q3: <back to Summary>
A4: 項目 | D4: 2017/01 | E4: 2017/02 | F4: 2017/03 | G4: 2017/04 | H4: 2017/05 | I4: 2017/06 | J4: 2017/07 | K4: 2017/08 | L4: 2017/09 | M4: 2017/10 | N4: 2017/11 | O4: 2017/12 | P4: 2017/1~2017/12 | Q4: %
C5: 人數 | D5: =製造費用明細!E2+銷售費用!E2+管理費用!E2+研發費用!E2 -> 67 | E5: =製造費用明細!F2+銷售費用!F2+管理費用!F2+研發費用!F2 -> 69 | F5: =製造費用明細!G2+銷售費用!G2+管理費用!G2+研發費用!G2 -> 69 | G5: =製造費用明細!H2+銷售費用!H2+管理費用!H2+研發費用!H2 -> 68 | H5: =製造費用明細!I2+銷售費用!I2+管理費用!I2+研發費用!I2 -> 70 | I5: =製造費用明細!J2+銷售費用!J2+管理費用!J2+研發費用!J2 -> 71 | J5: =製造費用明細!K2+銷售費用!K2+管理費用!K2+研發費用!K2 -> 70 | K5: =製造費用明細!L2+銷售費用!L2+管理費用!L2+研發費用!L2 -> 70 | ... O5: =製造費用明細!P2+銷售費用!P2+管理費用!P2+研發費用!P2 -> 0
A6: 4000000 營業收入
B7: 4100000 銷貨收入淨額
B8: 4110000 銷貨收入 | D8: =IF(ISNA(VLOOKUP($B8,IS明細!$B:D,3,0)),0,VLOOKUP($B8,IS明細!$B:D,3,0)) -> 60242992 | E8: =IF(ISNA(VLOOKUP($B8,IS明細!$B:F,5,0)),0,VLOOKUP($B8,IS明細!$B:F,5,0)) -> 53027714 | F8: =IF(ISNA(VLOOKUP($B8,IS明細!$B:H,7,0)),0,VLOOKUP($B8,IS明細!$B:H,7,0)) -> 65197616 | G8: =IF(ISNA(VLOOKUP($B8,IS明細!$B:J,9,0)),0,VLOOKUP($B8,IS明細!$B:J,9,0)) -> 67460983 | H8: =IF(ISNA(VLOOKUP($B8,IS明細!$B:L,11,0)),0,VLOOKUP($B8,IS明細!$B:L,11,0)) -> 53238236 | I8: =IF(ISNA(VLOOKUP($B8,IS明細!$B:N,13,0)),0,VLOOKUP($B8,IS明細!$B:N,13,0)) -> 87451211 | J8: =IF(ISNA(VLOOKUP($B8,IS明細!$B:P,15,0)),0,VLOOKUP($B8,IS明細!$B:P,15,0)) -> 98237627 | K8: =IF(ISNA(VLOOKUP($B8,IS明細!$B:R,17,0)),0,VLOOKUP($B8,IS明細!$B:R,17,0)) -> 82131376 | L8: =IF(ISNA(VLOOKUP($B8,IS明細!$B:T,19,0)),0,VLOOKUP($B8,IS明細!$B:T,19,0)) -> 0 | M8: =IF(ISNA(VLOOKUP($B8,IS明細!$B:V,21,0)),0,VLOOKUP($B8,IS明細!$B:V,21,0)) -> 0 | N8: =IF(ISNA(VLOOKUP($B8,IS明細!$B:X,23,0)),0,VLOOKUP($B8,IS明細!$B:X,23,0)) -> 0 | O8: =IF(ISNA(VLOOKUP($B8,IS明細!$B:Z,25,0)),0,VLOOKUP($B8,IS明細!$B:Z,25,0)) -> 0 | P8: =SUM(D8:O8) -> 566987755 | Q8: =P8/$P$8 -> 1
B9: 4111000 銷貨收入-國內 | D9: =IF(ISNA(VLOOKUP($B9,IS明細!$B:D,3,0)),0,VLOOKUP($B9,IS明細!$B:D,3,0)) -> 6052118 | E9: =IF(ISNA(VLOOKUP($B9,IS明細!$B:F,5,0)),0,VLOOKUP($B9,IS明細!$B:F,5,0)) -> 6516828 | F9: =IF(ISNA(VLOOKUP($B9,IS明細!$B:H,7,0)),0,VLOOKUP($B9,IS明細!$B:H,7,0)) -> 4965549 | G9: =IF(ISNA(VLOOKUP($B9,IS明細!$B:J,9,0)),0,VLOOKUP($B9,IS明細!$B:J,9,0)) -> 3547544 | H9: =IF(ISNA(VLOOKUP($B9,IS明細!$B:L,11,0)),0,VLOOKUP($B9,IS明細!$B:L,11,0)) -> 4730748 | I9: =IF(ISNA(VLOOKUP($B9,IS明細!$B:N,13,0)),0,VLOOKUP($B9,IS明細!$B:N,13,0)) -> 10034944 | J9: =IF(ISNA(VLOOKUP($B9,IS明細!$B:P,15,0)),0,VLOOKUP($B9,IS明細!$B:P,15,0)) -> 8173236 | K9: =IF(ISNA(VLOOKUP($B9,IS明細!$B:R,17,0)),0,VLOOKUP($B9,IS明細!$B:R,17,0)) -> 8365372 | L9: =IF(ISNA(VLOOKUP($B9,IS明細!$B:T,19,0)),0,VLOOKUP($B9,IS明細!$B:T,19,0)) -> 0 | M9: =IF(ISNA(VLOOKUP($B9,IS明細!$B:V,21,0)),0,VLOOKUP($B9,IS明細!$B:V,21,0)) -> 0 | N9: =IF(ISNA(VLOOKUP($B9,IS明細!$B:X,23,0)),0,VLOOKUP($B9,IS明細!$B:X,23,0)) -> 0 | O9: =IF(ISNA(VLOOKUP($B9,IS明細!$B:Z,25,0)),0,VLOOKUP($B9,IS明細!$B:Z,25,0)) -> 0 | P9: =SUM(D9:O9) -> 52386339 | Q9: =P9/$P$8 -> 0.092394128
B10: 4112000 銷貨收入-國外 | D10: =IF(ISNA(VLOOKUP($B10,IS明細!$B:D,3,0)),0,VLOOKUP($B10,IS明細!$B:D,3,0)) -> 54190874 | E10: =IF(ISNA(VLOOKUP($B10,IS明細!$B:F,5,0)),0,VLOOKUP($B10,IS明細!$B:F,5,0)) -> 46510886 | F10: =IF(ISNA(VLOOKUP($B10,IS明細!$B:H,7,0)),0,VLOOKUP($B10,IS明細!$B:H,7,0)) -> 60232067 | G10: =IF(ISNA(VLOOKUP($B10,IS明細!$B:J,9,0)),0,VLOOKUP($B10,IS明細!$B:J,9,0)) -> 63913439 | H10: =IF(ISNA(VLOOKUP($B10,IS明細!$B:L,11,0)),0,VLOOKUP($B10,IS明細!$B:L,11,0)) -> 48507488 | I10: =IF(ISNA(VLOOKUP($B10,IS明細!$B:N,13,0)),0,VLOOKUP($B10,IS明細!$B:N,13,0)) -> 77416267 | J10: =IF(ISNA(VLOOKUP($B10,IS明細!$B:P,15,0)),0,VLOOKUP($B10,IS明細!$B:P,15,0)) -> 90064391 | K10: =IF(ISNA(VLOOKUP($B10,IS明細!$B:R,17,0)),0,VLOOKUP($B10,IS明細!$B:R,17,0)) -> 73766004 | L10: =IF(ISNA(VLOOKUP($B10,IS明細!$B:T,19,0)),0,VLOOKUP($B10,IS明細!$B:T,19,0)) -> 0 | M10: =IF(ISNA(VLOOKUP($B10,IS明細!$B:V,21,0)),0,VLOOKUP($B10,IS明細!$B:V,21,0)) -> 0 | N10: =IF(ISNA(VLOOKUP($B10,IS明細!$B:X,23,0)),0,VLOOKUP($B10,IS明細!$B:X,23,0)) -> 0 | O10: =IF(ISNA(VLOOKUP($B10,IS明細!$B:Z,25,0)),0,VLOOKUP($B10,IS明細!$B:Z,25,0)) -> 0 | P10: =SUM(D10:O10) -> 514601416 | Q10: =P10/$P$8 -> 0.90760587
B11: 4170000 銷貨退回 | D11: =IF(ISNA(VLOOKUP($B11,IS明細!$B:D,3,0)),0,VLOOKUP($B11,IS明細!$B:D,3,0)) -> 0 | E11: =IF(ISNA(VLOOKUP($B11,IS明細!$B:F,5,0)),0,VLOOKUP($B11,IS明細!$B:F,5,0)) -> 0 | F11: =IF(ISNA(VLOOKUP($B11,IS明細!$B:H,7,0)),0,VLOOKUP($B11,IS明細!$B:H,7,0)) -> 0 | G11: =IF(ISNA(VLOOKUP($B11,IS明細!$B:J,9,0)),0,VLOOKUP($B11,IS明細!$B:J,9,0)) -> 116289 | H11: =IF(ISNA(VLOOKUP($B11,IS明細!$B:L,11,0)),0,VLOOKUP($B11,IS明細!$B:L,11,0)) -> 0 | I11: =IF(ISNA(VLOOKUP($B11,IS明細!$B:N,13,0)),0,VLOOKUP($B11,IS明細!$B:N,13,0)) -> 13559 | J11: =IF(ISNA(VLOOKUP($B11,IS明細!$B:P,15,0)),0,VLOOKUP($B11,IS明細!$B:P,15,0)) -> 0 | K11: =IF(ISNA(VLOOKUP($B11,IS明細!$B:R,17,0)),0,VLOOKUP($B11,IS明細!$B:R,17,0)) -> 0 | L11: =IF(ISNA(VLOOKUP($B11,IS明細!$B:T,19,0)),0,VLOOKUP($B11,IS明細!$B:T,19,0)) -> 0 | M11: =IF(ISNA(VLOOKUP($B11,IS明細!$B:V,21,0)),0,VLOOKUP($B11,IS明細!$B:V,21,0)) -> 0 | N11: =IF(ISNA(VLOOKUP($B11,IS明細!$B:X,23,0)),0,VLOOKUP($B11,IS明細!$B:X,23,0)) -> 0 | O11: =IF(ISNA(VLOOKUP($B11,IS明細!$B:Z,25,0)),0,VLOOKUP($B11,IS明細!$B:Z,25,0)) -> 0 | P11: =SUM(D11:O11) -> 129848 | Q11: =P11/$P$8 -> 0.00022901376
B12: 4190000 銷貨折讓 | D12: =IF(ISNA(VLOOKUP($B12,IS明細!$B:D,3,0)),0,VLOOKUP($B12,IS明細!$B:D,3,0)) -> 0 | E12: =IF(ISNA(VLOOKUP($B12,IS明細!$B:F,5,0)),0,VLOOKUP($B12,IS明細!$B:F,5,0)) -> 0 | F12: =IF(ISNA(VLOOKUP($B12,IS明細!$B:H,7,0)),0,VLOOKUP($B12,IS明細!$B:H,7,0)) -> 1493168 | G12: =IF(ISNA(VLOOKUP($B12,IS明細!$B:J,9,0)),0,VLOOKUP($B12,IS明細!$B:J,9,0)) -> 0 | H12: =IF(ISNA(VLOOKUP($B12,IS明細!$B:L,11,0)),0,VLOOKUP($B12,IS明細!$B:L,11,0)) -> 0 | I12: =IF(ISNA(VLOOKUP($B12,IS明細!$B:N,13,0)),0,VLOOKUP($B12,IS明細!$B:N,13,0)) -> 31565 | J12: =IF(ISNA(VLOOKUP($B12,IS明細!$B:P,15,0)),0,VLOOKUP($B12,IS明細!$B:P,15,0)) -> 0 | K12: =IF(ISNA(VLOOKUP($B12,IS明細!$B:R,17,0)),0,VLOOKUP($B12,IS明細!$B:R,17,0)) -> 0 | L12: =IF(ISNA(VLOOKUP($B12,IS明細!$B:T,19,0)),0,VLOOKUP($B12,IS明細!$B:T,19,0)) -> 0 | M12: =IF(ISNA(VLOOKUP($B12,IS明細!$B:V,21,0)),0,VLOOKUP($B12,IS明細!$B:V,21,0)) -> 0 | N12: =IF(ISNA(VLOOKUP($B12,IS明細!$B:X,23,0)),0,VLOOKUP($B12,IS明細!$B:X,23,0)) -> 0 | O12: =IF(ISNA(VLOOKUP($B12,IS明細!$B:Z,25,0)),0,VLOOKUP($B12,IS明細!$B:Z,25,0)) -> 0 | P12: =SUM(D12:O12) -> 1524733 | Q12: =P12/$P$8 -> 0.0026891815
B13: 4199999 銷貨收入淨額合計 | D13: =IF(ISNA(VLOOKUP($B13,IS明細!$B:D,3,0)),0,VLOOKUP($B13,IS明細!$B:D,3,0)) -> 60242992 | E13: =IF(ISNA(VLOOKUP($B13,IS明細!$B:F,5,0)),0,VLOOKUP($B13,IS明細!$B:F,5,0)) -> 53027714 | F13: =IF(ISNA(VLOOKUP($B13,IS明細!$B:H,7,0)),0,VLOOKUP($B13,IS明細!$B:H,7,0)) -> 63704448 | G13: =IF(ISNA(VLOOKUP($B13,IS明細!$B:J,9,0)),0,VLOOKUP($B13,IS明細!$B:J,9,0)) -> 67344694 | H13: =IF(ISNA(VLOOKUP($B13,IS明細!$B:L,11,0)),0,VLOOKUP($B13,IS明細!$B:L,11,0)) -> 53238236 | I13: =IF(ISNA(VLOOKUP($B13,IS明細!$B:N,13,0)),0,VLOOKUP($B13,IS明細!$B:N,13,0)) -> 87406087 | J13: =IF(ISNA(VLOOKUP($B13,IS明細!$B:P,15,0)),0,VLOOKUP($B13,IS明細!$B:P,15,0)) -> 98237627 | K13: =IF(ISNA(VLOOKUP($B13,IS明細!$B:R,17,0)),0,VLOOKUP($B13,IS明細!$B:R,17,0)) -> 82131376 | L13: =IF(ISNA(VLOOKUP($B13,IS明細!$B:T,19,0)),0,VLOOKUP($B13,IS明細!$B:T,19,0)) -> 0 | M13: =IF(ISNA(VLOOKUP($B13,IS明細!$B:V,21,0)),0,VLOOKUP($B13,IS明細!$B:V,21,0)) -> 0 | N13: =IF(ISNA(VLOOKUP($B13,IS明細!$B:X,23,0)),0,VLOOKUP($B13,IS明細!$B:X,23,0)) -> 0 | O13: =IF(ISNA(VLOOKUP($B13,IS明細!$B:Z,25,0)),0,VLOOKUP($B13,IS明細!$B:Z,25,0)) -> 0 | P13: =SUM(D13:O13) -> 565333174 | Q13: =P13/$P$8 -> 0.9970818
B14: 4600000 勞務收入 | E14: =IF(ISNA(VLOOKUP($B14,IS明細!$B:F,5,0)),0,VLOOKUP($B14,IS明細!$B:F,5,0)) -> 0 | F14: =IF(ISNA(VLOOKUP($B14,IS明細!$B:H,7,0)),0,VLOOKUP($B14,IS明細!$B:H,7,0)) -> 0 | G14: =IF(ISNA(VLOOKUP($B14,IS明細!$B:J,9,0)),0,VLOOKUP($B14,IS明細!$B:J,9,0)) -> 0 | H14: =IF(ISNA(VLOOKUP($B14,IS明細!$B:L,11,0)),0,VLOOKUP($B14,IS明細!$B:L,11,0)) -> 0 | I14: =IF(ISNA(VLOOKUP($B14,IS明細!$B:N,13,0)),0,VLOOKUP($B14,IS明細!$B:N,13,0)) -> 0 | J14: =IF(ISNA(VLOOKUP($B14,IS明細!$B:P,15,0)),0,VLOOKUP($B14,IS明細!$B:P,15,0)) -> 0 | K14: =IF(ISNA(VLOOKUP($B14,IS明細!$B:R,17,0)),0,VLOOKUP($B14,IS明細!$B:R,17,0)) -> 0 | L14: =IF(ISNA(VLOOKUP($B14,IS明細!$B:T,19,0)),0,VLOOKUP($B14,IS明細!$B:T,19,0)) -> 0 | M14: =IF(ISNA(VLOOKUP($B14,IS明細!$B:V,21,0)),0,VLOOKUP($B14,IS明細!$B:V,21,0)) -> 0 | N14: =IF(ISNA(VLOOKUP($B14,IS明細!$B:X,23,0)),0,VLOOKUP($B14,IS明細!$B:X,23,0)) -> 0 | O14: =IF(ISNA(VLOOKUP($B14,IS明細!$B:Z,25,0)),0,VLOOKUP($B14,IS明細!$B:Z,25,0)) -> 0 | Q14: =P14/$P$8 -> 0
B15: 4610000 維修收入 | D15: =IF(ISNA(VLOOKUP($B15,IS明細!B:D,3,0)),0,VLOOKUP($B15,IS明細!B:D,3,0)) -> 3959 | E15: =IF(ISNA(VLOOKUP($B15,IS明細!$B:F,5,0)),0,VLOOKUP($B15,IS明細!$B:F,5,0)) -> 43786 | F15: =IF(ISNA(VLOOKUP($B15,IS明細!$B:H,7,0)),0,VLOOKUP($B15,IS明細!$B:H,7,0)) -> 27522 | G15: =IF(ISNA(VLOOKUP($B15,IS明細!$B:J,9,0)),0,VLOOKUP($B15,IS明細!$B:J,9,0)) -> 20986 | H15: =IF(ISNA(VLOOKUP($B15,IS明細!$B:L,11,0)),0,VLOOKUP($B15,IS明細!$B:L,11,0)) -> 43107 | I15: =IF(ISNA(VLOOKUP($B15,IS明細!$B:N,13,0)),0,VLOOKUP($B15,IS明細!$B:N,13,0)) -> 81879 | J15: =IF(ISNA(VLOOKUP($B15,IS明細!$B:P,15,0)),0,VLOOKUP($B15,IS明細!$B:P,15,0)) -> 3539 | K15: =IF(ISNA(VLOOKUP($B15,IS明細!$B:R,17,0)),0,VLOOKUP($B15,IS明細!$B:R,17,0)) -> 3539 | L15: =IF(ISNA(VLOOKUP($B15,IS明細!$B:T,19,0)),0,VLOOKUP($B15,IS明細!$B:T,19,0)) -> 0 | M15: =IF(ISNA(VLOOKUP($B15,IS明細!$B:V,21,0)),0,VLOOKUP($B15,IS明細!$B:V,21,0)) -> 0 | N15: =IF(ISNA(VLOOKUP($B15,IS明細!$B:X,23,0)),0,VLOOKUP($B15,IS明細!$B:X,23,0)) -> 0 | O15: =IF(ISNA(VLOOKUP($B15,IS明細!$B:Z,25,0)),0,VLOOKUP($B15,IS明細!$B:Z,25,0)) -> 0 | P15: =SUM(D15:O15) -> 228317 | Q15: =P15/$P$8 -> 0.00040268418
B16: 4611000 維修收入 | D16: =IF(ISNA(VLOOKUP($B16,IS明細!B:D,3,0)),0,VLOOKUP($B16,IS明細!B:D,3,0)) -> 3959 | E16: =IF(ISNA(VLOOKUP($B16,IS明細!$B:F,5,0)),0,VLOOKUP($B16,IS明細!$B:F,5,0)) -> 43786 | F16: =IF(ISNA(VLOOKUP($B16,IS明細!$B:H,7,0)),0,VLOOKUP($B16,IS明細!$B:H,7,0)) -> 27522 | G16: =IF(ISNA(VLOOKUP($B16,IS明細!$B:J,9,0)),0,VLOOKUP($B16,IS明細!$B:J,9,0)) -> 20986 | H16: =IF(ISNA(VLOOKUP($B16,IS明細!$B:L,11,0)),0,VLOOKUP($B16,IS明細!$B:L,11,0)) -> 43107 | I16: =IF(ISNA(VLOOKUP($B16,IS明細!$B:N,13,0)),0,VLOOKUP($B16,IS明細!$B:N,13,0)) -> 81879 | J16: =IF(ISNA(VLOOKUP($B16,IS明細!$B:P,15,0)),0,VLOOKUP($B16,IS明細!$B:P,15,0)) -> 3539 | K16: =IF(ISNA(VLOOKUP($B16,IS明細!$B:R,17,0)),0,VLOOKUP($B16,IS明細!$B:R,17,0)) -> 3539 | L16: =IF(ISNA(VLOOKUP($B16,IS明細!$B:T,19,0)),0,VLOOKUP($B16,IS明細!$B:T,19,0)) -> 0 | M16: =IF(ISNA(VLOOKUP($B16,IS明細!$B:V,21,0)),0,VLOOKUP($B16,IS明細!$B:V,21,0)) -> 0 | N16: =IF(ISNA(VLOOKUP($B16,IS明細!$B:X,23,0)),0,VLOOKUP($B16,IS明細!$B:X,23,0)) -> 0 | O16: =IF(ISNA(VLOOKUP($B16,IS明細!$B:Z,25,0)),0,VLOOKUP($B16,IS明細!$B:Z,25,0)) -> 0 | P16: =SUM(D16:O16) -> 228317 | Q16: =P16/$P$8 -> 0.00040268418
B17: 4619000 維修收入折讓 | D17: =IF(ISNA(VLOOKUP($B17,IS明細!B:D,3,0)),0,VLOOKUP($B17,IS明細!B:D,3,0)) -> 0 | E17: =IF(ISNA(VLOOKUP($B17,IS明細!$B:F,5,0)),0,VLOOKUP($B17,IS明細!$B:F,5,0)) -> 0 | F17: =IF(ISNA(VLOOKUP($B17,IS明細!$B:H,7,0)),0,VLOOKUP($B17,IS明細!$B:H,7,0)) -> 0 | G17: =IF(ISNA(VLOOKUP($B17,IS明細!$B:J,9,0)),0,VLOOKUP($B17,IS明細!$B:J,9,0)) -> 0 | H17: =IF(ISNA(VLOOKUP($B17,IS明細!$B:L,11,0)),0,VLOOKUP($B17,IS明細!$B:L,11,0)) -> 0 | I17: =IF(ISNA(VLOOKUP($B17,IS明細!$B:N,13,0)),0,VLOOKUP($B17,IS明細!$B:N,13,0)) -> 0 | J17: =IF(ISNA(VLOOKUP($B17,IS明細!$B:P,15,0)),0,VLOOKUP($B17,IS明細!$B:P,15,0)) -> 0 | K17: =IF(ISNA(VLOOKUP($B17,IS明細!$B:R,17,0)),0,VLOOKUP($B17,IS明細!$B:R,17,0)) -> 0 | L17: =IF(ISNA(VLOOKUP($B17,IS明細!$B:T,19,0)),0,VLOOKUP($B17,IS明細!$B:T,19,0)) -> 0 | M17: =IF(ISNA(VLOOKUP($B17,IS明細!$B:V,21,0)),0,VLOOKUP($B17,IS明細!$B:V,21,0)) -> 0 | N17: =IF(ISNA(VLOOKUP($B17,IS明細!$B:X,23,0)),0,VLOOKUP($B17,IS明細!$B:X,23,0)) -> 0 | O17: =IF(ISNA(VLOOKUP($B17,IS明細!$B:Z,25,0)),0,VLOOKUP($B17,IS明細!$B:Z,25,0)) -> 0 | P17: =SUM(D17:O17) -> 0 | Q17: =P17/$P$8 -> 0
B18: 4620000 勞務收入 | D18: =IF(ISNA(VLOOKUP($B18,IS明細!B:D,3,0)),0,VLOOKUP($B18,IS明細!B:D,3,0)) -> 0 | E18: =IF(ISNA(VLOOKUP($B18,IS明細!$B:F,5,0)),0,VLOOKUP($B18,IS明細!$B:F,5,0)) -> 0 | F18: =IF(ISNA(VLOOKUP($B18,IS明細!$B:H,7,0)),0,VLOOKUP($B18,IS明細!$B:H,7,0)) -> 0 | G18: =IF(ISNA(VLOOKUP($B18,IS明細!$B:J,9,0)),0,VLOOKUP($B18,IS明細!$B:J,9,0)) -> 0 | H18: =IF(ISNA(VLOOKUP($B18,IS明細!$B:L,11,0)),0,VLOOKUP($B18,IS明細!$B:L,11,0)) -> 0 | I18: =IF(ISNA(VLOOKUP($B18,IS明細!$B:N,13,0)),0,VLOOKUP($B18,IS明細!$B:N,13,0)) -> 0 | J18: =IF(ISNA(VLOOKUP($B18,IS明細!$B:P,15,0)),0,VLOOKUP($B18,IS明細!$B:P,15,0)) -> 0 | K18: =IF(ISNA(VLOOKUP($B18,IS明細!$B:R,17,0)),0,VLOOKUP($B18,IS明細!$B:R,17,0)) -> 0 | L18: =IF(ISNA(VLOOKUP($B18,IS明細!$B:T,19,0)),0,VLOOKUP($B18,IS明細!$B:T,19,0)) -> 0 | M18: =IF(ISNA(VLOOKUP($B18,IS明細!$B:V,21,0)),0,VLOOKUP($B18,IS明細!$B:V,21,0)) -> 0 | N18: =IF(ISNA(VLOOKUP($B18,IS明細!$B:X,23,0)),0,VLOOKUP($B18,IS明細!$B:X,23,0)) -> 0 | O18: =IF(ISNA(VLOOKUP($B18,IS明細!$B:Z,25,0)),0,VLOOKUP($B18,IS明細!$B:Z,25,0)) -> 0 | P18: =SUM(D18:O18) -> 0 | Q18: =P18/$P$8 -> 0
B19: 4621000 勞務收入 | D19: =IF(ISNA(VLOOKUP($B19,IS明細!B:D,3,0)),0,VLOOKUP($B19,IS明細!B:D,3,0)) -> 0 | E19: =IF(ISNA(VLOOKUP($B19,IS明細!$B:F,5,0)),0,VLOOKUP($B19,IS明細!$B:F,5,0)) -> 0 | F19: =IF(ISNA(VLOOKUP($B19,IS明細!$B:H,7,0)),0,VLOOKUP($B19,IS明細!$B:H,7,0)) -> 0 | G19: =IF(ISNA(VLOOKUP($B19,IS明細!$B:J,9,0)),0,VLOOKUP($B19,IS明細!$B:J,9,0)) -> 0 | H19: =IF(ISNA(VLOOKUP($B19,IS明細!$B:L,11,0)),0,VLOOKUP($B19,IS明細!$B:L,11,0)) -> 0 | I19: =IF(ISNA(VLOOKUP($B19,IS明細!$B:N,13,0)),0,VLOOKUP($B19,IS明細!$B:N,13,0)) -> 0 | J19: =IF(ISNA(VLOOKUP($B19,IS明細!$B:P,15,0)),0,VLOOKUP($B19,IS明細!$B:P,15,0)) -> 0 | K19: =IF(ISNA(VLOOKUP($B19,IS明細!$B:R,17,0)),0,VLOOKUP($B19,IS明細!$B:R,17,0)) -> 0 | L19: =IF(ISNA(VLOOKUP($B19,IS明細!$B:T,19,0)),0,VLOOKUP($B19,IS明細!$B:T,19,0)) -> 0 | M19: =IF(ISNA(VLOOKUP($B19,IS明細!$B:V,21,0)),0,VLOOKUP($B19,IS明細!$B:V,21,0)) -> 0 | N19: =IF(ISNA(VLOOKUP($B19,IS明細!$B:X,23,0)),0,VLOOKUP($B19,IS明細!$B:X,23,0)) -> 0 | O19: =IF(ISNA(VLOOKUP($B19,IS明細!$B:Z,25,0)),0,VLOOKUP($B19,IS明細!$B:Z,25,0)) -> 0 | P19: =SUM(D19:O19) -> 0 | Q19: =P19/$P$8 -> 0
B20: 4699999 勞務收入合計 | D20: =IF(ISNA(VLOOKUP($B20,IS明細!B:D,3,0)),0,VLOOKUP($B20,IS明細!B:D,3,0)) -> 3959 | E20: =IF(ISNA(VLOOKUP($B20,IS明細!$B:F,5,0)),0,VLOOKUP($B20,IS明細!$B:F,5,0)) -> 43786 | F20: =IF(ISNA(VLOOKUP($B20,IS明細!$B:H,7,0)),0,VLOOKUP($B20,IS明細!$B:H,7,0)) -> 27522 | G20: =IF(ISNA(VLOOKUP($B20,IS明細!$B:J,9,0)),0,VLOOKUP($B20,IS明細!$B:J,9,0)) -> 20986 | H20: =IF(ISNA(VLOOKUP($B20,IS明細!$B:L,11,0)),0,VLOOKUP($B20,IS明細!$B:L,11,0)) -> 43107 | I20: =IF(ISNA(VLOOKUP($B20,IS明細!$B:N,13,0)),0,VLOOKUP($B20,IS明細!$B:N,13,0)) -> 81879 | J20: =IF(ISNA(VLOOKUP($B20,IS明細!$B:P,15,0)),0,VLOOKUP($B20,IS明細!$B:P,15,0)) -> 3539 | K20: =IF(ISNA(VLOOKUP($B20,IS明細!$B:R,17,0)),0,VLOOKUP($B20,IS明細!$B:R,17,0)) -> 3539 | L20: =IF(ISNA(VLOOKUP($B20,IS明細!$B:T,19,0)),0,VLOOKUP($B20,IS明細!$B:T,19,0)) -> 0 | M20: =IF(ISNA(VLOOKUP($B20,IS明細!$B:V,21,0)),0,VLOOKUP($B20,IS明細!$B:V,21,0)) -> 0 | N20: =IF(ISNA(VLOOKUP($B20,IS明細!$B:X,23,0)),0,VLOOKUP($B20,IS明細!$B:X,23,0)) -> 0 | O20: =IF(ISNA(VLOOKUP($B20,IS明細!$B:Z,25,0)),0,VLOOKUP($B20,IS明細!$B:Z,25,0)) -> 0 | P20: =SUM(D20:O20) -> 228317 | Q20: =P20/$P$8 -> 0.00040268418
A21: 4999999 營業收入合計 | D21: =IF(ISNA(VLOOKUP($A21,IS明細!A:D,4,0)),0,VLOOKUP($A21,IS明細!A:D,4,0)) -> 60246951 | E21: =IF(ISNA(VLOOKUP($A21,IS明細!$A:F,6,0)),0,VLOOKUP($A21,IS明細!$A:F,6,0)) -> 53071500 | F21: =IF(ISNA(VLOOKUP($A21,IS明細!$A:H,8,0)),0,VLOOKUP($A21,IS明細!$A:H,8,0)) -> 63731970 | G21: =IF(ISNA(VLOOKUP($A21,IS明細!$A:J,10,0)),0,VLOOKUP($A21,IS明細!$A:J,10,0)) -> 67365680 | H21: =IF(ISNA(VLOOKUP($A21,IS明細!$A:L,12,0)),0,VLOOKUP($A21,IS明細!$A:L,12,0)) -> 53281343 | I21: =IF(ISNA(VLOOKUP($A21,IS明細!$A:N,14,0)),0,VLOOKUP($A21,IS明細!$A:N,14,0)) -> 87487966 | J21: =IF(ISNA(VLOOKUP($A21,IS明細!$A:P,16,0)),0,VLOOKUP($A21,IS明細!$A:P,16,0)) -> 98241166 | K21: =IF(ISNA(VLOOKUP($A21,IS明細!$A:R,18,0)),0,VLOOKUP($A21,IS明細!$A:R,18,0)) -> 82134915 | L21: =IF(ISNA(VLOOKUP($A21,IS明細!$A:T,20,0)),0,VLOOKUP($A21,IS明細!$A:T,20,0)) -> 0 | M21: =IF(ISNA(VLOOKUP($A21,IS明細!$A:V,22,0)),0,VLOOKUP($A21,IS明細!$A:V,22,0)) -> 0 | N21: =IF(ISNA(VLOOKUP($A21,IS明細!$A:X,24,0)),0,VLOOKUP($A21,IS明細!$A:X,24,0)) -> 0 | O21: =IF(ISNA(VLOOKUP($A21,IS明細!$A:Z,26,0)),0,VLOOKUP($A21,IS明細!$A:Z,26,0)) -> 0 | P21: =SUM(D21:O21) -> 565561491 | Q21: =P21/$P$21 -> 1
A22: 5000000 營業成本
B23: 5100000 進銷成本
B24: 5110000 進銷成本 | D24: =IF(ISNA(VLOOKUP($B24,IS明細!B:D,3,0)),0,VLOOKUP($B24,IS明細!B:D,3,0)) -> 0 | E24: =IF(ISNA(VLOOKUP($B24,IS明細!$B:F,5,0)),0,VLOOKUP($B24,IS明細!$B:F,5,0)) -> 0 | F24: =IF(ISNA(VLOOKUP($B24,IS明細!$B:H,7,0)),0,VLOOKUP($B24,IS明細!$B:H,7,0)) -> 205528 | G24: =IF(ISNA(VLOOKUP($B24,IS明細!$B:J,9,0)),0,VLOOKUP($B24,IS明細!$B:J,9,0)) -> 24730 | H24: =IF(ISNA(VLOOKUP($B24,IS明細!$B:L,11,0)),0,VLOOKUP($B24,IS明細!$B:L,11,0)) -> -13892 | I24: =IF(ISNA(VLOOKUP($B24,IS明細!$B:N,13,0)),0,VLOOKUP($B24,IS明細!$B:N,13,0)) -> 21297 | J24: =IF(ISNA(VLOOKUP($B24,IS明細!$B:P,15,0)),0,VLOOKUP($B24,IS明細!$B:P,15,0)) -> 21992 | K24: =IF(ISNA(VLOOKUP($B24,IS明細!$B:R,17,0)),0,VLOOKUP($B24,IS明細!$B:R,17,0)) -> 0 | L24: =IF(ISNA(VLOOKUP($B24,IS明細!$B:T,19,0)),0,VLOOKUP($B24,IS明細!$B:T,19,0)) -> 0 | M24: =IF(ISNA(VLOOKUP($B24,IS明細!$B:V,21,0)),0,VLOOKUP($B24,IS明細!$B:V,21,0)) -> 0 | N24: =IF(ISNA(VLOOKUP($B24,IS明細!$B:X,23,0)),0,VLOOKUP($B24,IS明細!$B:X,23,0)) -> 0 | O24: =IF(ISNA(VLOOKUP($B24,IS明細!$B:Z,25,0)),0,VLOOKUP($B24,IS明細!$B:Z,25,0)) -> 0 | P24: =SUM(D24:O24) -> 259655 | Q24: =P24/$P$8 -> 0.00045795522
B25: 5120000 產銷成本 | D25: =IF(ISNA(VLOOKUP($B25,IS明細!B:D,3,0)),0,VLOOKUP($B25,IS明細!B:D,3,0)) -> 52605395 | E25: =IF(ISNA(VLOOKUP($B25,IS明細!$B:F,5,0)),0,VLOOKUP($B25,IS明細!$B:F,5,0)) -> 49188788 | F25: =IF(ISNA(VLOOKUP($B25,IS明細!$B:H,7,0)),0,VLOOKUP($B25,IS明細!$B:H,7,0)) -> 54845750 | G25: =IF(ISNA(VLOOKUP($B25,IS明細!$B:J,9,0)),0,VLOOKUP($B25,IS明細!$B:J,9,0)) -> 59713244 | H25: =IF(ISNA(VLOOKUP($B25,IS明細!$B:L,11,0)),0,VLOOKUP($B25,IS明細!$B:L,11,0)) -> 45764439 | I25: =IF(ISNA(VLOOKUP($B25,IS明細!$B:N,13,0)),0,VLOOKUP($B25,IS明細!$B:N,13,0)) -> 74659138 | J25: =IF(ISNA(VLOOKUP($B25,IS明細!$B:P,15,0)),0,VLOOKUP($B25,IS明細!$B:P,15,0)) -> 84930497 | K25: =IF(ISNA(VLOOKUP($B25,IS明細!$B:R,17,0)),0,VLOOKUP($B25,IS明細!$B:R,17,0)) -> 70526211 | L25: =IF(ISNA(VLOOKUP($B25,IS明細!$B:T,19,0)),0,VLOOKUP($B25,IS明細!$B:T,19,0)) -> 0 | M25: =IF(ISNA(VLOOKUP($B25,IS明細!$B:V,21,0)),0,VLOOKUP($B25,IS明細!$B:V,21,0)) -> 0 | N25: =IF(ISNA(VLOOKUP($B25,IS明細!$B:X,23,0)),0,VLOOKUP($B25,IS明細!$B:X,23,0)) -> 0 | O25: =IF(ISNA(VLOOKUP($B25,IS明細!$B:Z,25,0)),0,VLOOKUP($B25,IS明細!$B:Z,25,0)) -> 0 | P25: =SUM(D25:O25) -> 492233462 | Q25: =P25/$P$8 -> 0.86815537
B26: 5121000 產銷成本 | D26: =IF(ISNA(VLOOKUP($B26,IS明細!B:D,3,0)),0,VLOOKUP($B26,IS明細!B:D,3,0)) -> 52737740 | E26: =IF(ISNA(VLOOKUP($B26,IS明細!$B:F,5,0)),0,VLOOKUP($B26,IS明細!$B:F,5,0)) -> 49056975 | F26: =IF(ISNA(VLOOKUP($B26,IS明細!$B:H,7,0)),0,VLOOKUP($B26,IS明細!$B:H,7,0)) -> 54832535 | G26: =IF(ISNA(VLOOKUP($B26,IS明細!$B:J,9,0)),0,VLOOKUP($B26,IS明細!$B:J,9,0)) -> 59713260 | H26: =IF(ISNA(VLOOKUP($B26,IS明細!$B:L,11,0)),0,VLOOKUP($B26,IS明細!$B:L,11,0)) -> 45764439 | I26: =IF(ISNA(VLOOKUP($B26,IS明細!$B:N,13,0)),0,VLOOKUP($B26,IS明細!$B:N,13,0)) -> 74659138 | J26: =IF(ISNA(VLOOKUP($B26,IS明細!$B:P,15,0)),0,VLOOKUP($B26,IS明細!$B:P,15,0)) -> 84930497 | K26: =IF(ISNA(VLOOKUP($B26,IS明細!$B:R,17,0)),0,VLOOKUP($B26,IS明細!$B:R,17,0)) -> 70526211 | L26: =IF(ISNA(VLOOKUP($B26,IS明細!$B:T,19,0)),0,VLOOKUP($B26,IS明細!$B:T,19,0)) -> 0 | M26: =IF(ISNA(VLOOKUP($B26,IS明細!$B:V,21,0)),0,VLOOKUP($B26,IS明細!$B:V,21,0)) -> 0 | N26: =IF(ISNA(VLOOKUP($B26,IS明細!$B:X,23,0)),0,VLOOKUP($B26,IS明細!$B:X,23,0)) -> 0 | O26: =IF(ISNA(VLOOKUP($B26,IS明細!$B:Z,25,0)),0,VLOOKUP($B26,IS明細!$B:Z,25,0)) -> 0 | P26: =SUM(D26:O26) -> 492220795 | Q26: =P26/$P$8 -> 0.86813303
B27: 5121100 產銷成本-拆解 | D27: =IF(ISNA(VLOOKUP($B27,IS明細!B:D,3,0)),0,VLOOKUP($B27,IS明細!B:D,3,0)) -> 0 | E27: =IF(ISNA(VLOOKUP($B27,IS明細!$B:F,5,0)),0,VLOOKUP($B27,IS明細!$B:F,5,0)) -> 0 | F27: =IF(ISNA(VLOOKUP($B27,IS明細!$B:H,7,0)),0,VLOOKUP($B27,IS明細!$B:H,7,0)) -> 12667 | G27: =IF(ISNA(VLOOKUP($B27,IS明細!$B:J,9,0)),0,VLOOKUP($B27,IS明細!$B:J,9,0)) -> 0 | H27: =IF(ISNA(VLOOKUP($B27,IS明細!$B:L,11,0)),0,VLOOKUP($B27,IS明細!$B:L,11,0)) -> 0 | I27: =IF(ISNA(VLOOKUP($B27,IS明細!$B:N,13,0)),0,VLOOKUP($B27,IS明細!$B:N,13,0)) -> 0 | J27: =IF(ISNA(VLOOKUP($B27,IS明細!$B:P,15,0)),0,VLOOKUP($B27,IS明細!$B:P,15,0)) -> 0 | K27: =IF(ISNA(VLOOKUP($B27,IS明細!$B:R,17,0)),0,VLOOKUP($B27,IS明細!$B:R,17,0)) -> 0 | L27: =IF(ISNA(VLOOKUP($B27,IS明細!$B:T,19,0)),0,VLOOKUP($B27,IS明細!$B:T,19,0)) -> 0 | M27: =IF(ISNA(VLOOKUP($B27,IS明細!$B:V,21,0)),0,VLOOKUP($B27,IS明細!$B:V,21,0)) -> 0 | N27: =IF(ISNA(VLOOKUP($B27,IS明細!$B:X,23,0)),0,VLOOKUP($B27,IS明細!$B:X,23,0)) -> 0 | O27: =IF(ISNA(VLOOKUP($B27,IS明細!$B:Z,25,0)),0,VLOOKUP($B27,IS明細!$B:Z,25,0)) -> 0 | P27: =SUM(D27:O27) -> 12667 | Q27: =P27/$P$8 -> 2.234087e-05
B28: 5122000 直接人工 | D28: =IF(ISNA(VLOOKUP($B28,IS明細!B:D,3,0)),0,VLOOKUP($B28,IS明細!B:D,3,0)) -> 0 | E28: =IF(ISNA(VLOOKUP($B28,IS明細!$B:F,5,0)),0,VLOOKUP($B28,IS明細!$B:F,5,0)) -> 0 | F28: =IF(ISNA(VLOOKUP($B28,IS明細!$B:H,7,0)),0,VLOOKUP($B28,IS明細!$B:H,7,0)) -> 0 | G28: =IF(ISNA(VLOOKUP($B28,IS明細!$B:J,9,0)),0,VLOOKUP($B28,IS明細!$B:J,9,0)) -> 0 | H28: =IF(ISNA(VLOOKUP($B28,IS明細!$B:L,11,0)),0,VLOOKUP($B28,IS明細!$B:L,11,0)) -> 0 | I28: =IF(ISNA(VLOOKUP($B28,IS明細!$B:N,13,0)),0,VLOOKUP($B28,IS明細!$B:N,13,0)) -> 0 | J28: =IF(ISNA(VLOOKUP($B28,IS明細!$B:P,15,0)),0,VLOOKUP($B28,IS明細!$B:P,15,0)) -> 0 | K28: =IF(ISNA(VLOOKUP($B28,IS明細!$B:R,17,0)),0,VLOOKUP($B28,IS明細!$B:R,17,0)) -> 0 | L28: =IF(ISNA(VLOOKUP($B28,IS明細!$B:T,19,0)),0,VLOOKUP($B28,IS明細!$B:T,19,0)) -> 0 | M28: =IF(ISNA(VLOOKUP($B28,IS明細!$B:V,21,0)),0,VLOOKUP($B28,IS明細!$B:V,21,0)) -> 0 | N28: =IF(ISNA(VLOOKUP($B28,IS明細!$B:X,23,0)),0,VLOOKUP($B28,IS明細!$B:X,23,0)) -> 0 | O28: =IF(ISNA(VLOOKUP($B28,IS明細!$B:Z,25,0)),0,VLOOKUP($B28,IS明細!$B:Z,25,0)) -> 0 | P28: =SUM(D28:O28) -> 0 | Q28: =P28/$P$8 -> 0
B29: 5122100 直接人工-本薪 | D29: =IF(ISNA(VLOOKUP($B29,IS明細!B:D,3,0)),0,VLOOKUP($B29,IS明細!B:D,3,0)) -> 0 | E29: =IF(ISNA(VLOOKUP($B29,IS明細!$B:F,5,0)),0,VLOOKUP($B29,IS明細!$B:F,5,0)) -> 0 | F29: =IF(ISNA(VLOOKUP($B29,IS明細!$B:H,7,0)),0,VLOOKUP($B29,IS明細!$B:H,7,0)) -> 0 | G29: =IF(ISNA(VLOOKUP($B29,IS明細!$B:J,9,0)),0,VLOOKUP($B29,IS明細!$B:J,9,0)) -> 0 | H29: =IF(ISNA(VLOOKUP($B29,IS明細!$B:L,11,0)),0,VLOOKUP($B29,IS明細!$B:L,11,0)) -> 0 | I29: =IF(ISNA(VLOOKUP($B29,IS明細!$B:N,13,0)),0,VLOOKUP($B29,IS明細!$B:N,13,0)) -> 0 | J29: =IF(ISNA(VLOOKUP($B29,IS明細!$B:P,15,0)),0,VLOOKUP($B29,IS明細!$B:P,15,0)) -> 0 | K29: =IF(ISNA(VLOOKUP($B29,IS明細!$B:R,17,0)),0,VLOOKUP($B29,IS明細!$B:R,17,0)) -> 0 | L29: =IF(ISNA(VLOOKUP($B29,IS明細!$B:T,19,0)),0,VLOOKUP($B29,IS明細!$B:T,19,0)) -> 0 | M29: =IF(ISNA(VLOOKUP($B29,IS明細!$B:V,21,0)),0,VLOOKUP($B29,IS明細!$B:V,21,0)) -> 0 | N29: =IF(ISNA(VLOOKUP($B29,IS明細!$B:X,23,0)),0,VLOOKUP($B29,IS明細!$B:X,23,0)) -> 0 | O29: =IF(ISNA(VLOOKUP($B29,IS明細!$B:Z,25,0)),0,VLOOKUP($B29,IS明細!$B:Z,25,0)) -> 0 | P29: =SUM(D29:O29) -> 0 | Q29: =P29/$P$8 -> 0
B30: 5122200 直接人工-加班費 | D30: =IF(ISNA(VLOOKUP($B30,IS明細!B:D,3,0)),0,VLOOKUP($B30,IS明細!B:D,3,0)) -> 0 | E30: =IF(ISNA(VLOOKUP($B30,IS明細!$B:F,5,0)),0,VLOOKUP($B30,IS明細!$B:F,5,0)) -> 0 | F30: =IF(ISNA(VLOOKUP($B30,IS明細!$B:H,7,0)),0,VLOOKUP($B30,IS明細!$B:H,7,0)) -> 0 | G30: =IF(ISNA(VLOOKUP($B30,IS明細!$B:J,9,0)),0,VLOOKUP($B30,IS明細!$B:J,9,0)) -> 0 | H30: =IF(ISNA(VLOOKUP($B30,IS明細!$B:L,11,0)),0,VLOOKUP($B30,IS明細!$B:L,11,0)) -> 0 | I30: =IF(ISNA(VLOOKUP($B30,IS明細!$B:N,13,0)),0,VLOOKUP($B30,IS明細!$B:N,13,0)) -> 0 | J30: =IF(ISNA(VLOOKUP($B30,IS明細!$B:P,15,0)),0,VLOOKUP($B30,IS明細!$B:P,15,0)) -> 0 | K30: =IF(ISNA(VLOOKUP($B30,IS明細!$B:R,17,0)),0,VLOOKUP($B30,IS明細!$B:R,17,0)) -> 0 | L30: =IF(ISNA(VLOOKUP($B30,IS明細!$B:T,19,0)),0,VLOOKUP($B30,IS明細!$B:T,19,0)) -> 0 | M30: =IF(ISNA(VLOOKUP($B30,IS明細!$B:V,21,0)),0,VLOOKUP($B30,IS明細!$B:V,21,0)) -> 0 | N30: =IF(ISNA(VLOOKUP($B30,IS明細!$B:X,23,0)),0,VLOOKUP($B30,IS明細!$B:X,23,0)) -> 0 | O30: =IF(ISNA(VLOOKUP($B30,IS明細!$B:Z,25,0)),0,VLOOKUP($B30,IS明細!$B:Z,25,0)) -> 0 | P30: =SUM(D30:O30) -> 0 | Q30: =P30/$P$8 -> 0
B31: 5122210 直接人工-加班費-應稅 | D31: =IF(ISNA(VLOOKUP($B31,IS明細!B:D,3,0)),0,VLOOKUP($B31,IS明細!B:D,3,0)) -> 0 | E31: =IF(ISNA(VLOOKUP($B31,IS明細!$B:F,5,0)),0,VLOOKUP($B31,IS明細!$B:F,5,0)) -> 0 | F31: =IF(ISNA(VLOOKUP($B31,IS明細!$B:H,7,0)),0,VLOOKUP($B31,IS明細!$B:H,7,0)) -> 0 | G31: =IF(ISNA(VLOOKUP($B31,IS明細!$B:J,9,0)),0,VLOOKUP($B31,IS明細!$B:J,9,0)) -> 0 | H31: =IF(ISNA(VLOOKUP($B31,IS明細!$B:L,11,0)),0,VLOOKUP($B31,IS明細!$B:L,11,0)) -> 0 | I31: =IF(ISNA(VLOOKUP($B31,IS明細!$B:N,13,0)),0,VLOOKUP($B31,IS明細!$B:N,13,0)) -> 0 | J31: =IF(ISNA(VLOOKUP($B31,IS明細!$B:P,15,0)),0,VLOOKUP($B31,IS明細!$B:P,15,0)) -> 0 | K31: =IF(ISNA(VLOOKUP($B31,IS明細!$B:R,17,0)),0,VLOOKUP($B31,IS明細!$B:R,17,0)) -> 0 | L31: =IF(ISNA(VLOOKUP($B31,IS明細!$B:T,19,0)),0,VLOOKUP($B31,IS明細!$B:T,19,0)) -> 0 | M31: =IF(ISNA(VLOOKUP($B31,IS明細!$B:V,21,0)),0,VLOOKUP($B31,IS明細!$B:V,21,0)) -> 0 | N31: =IF(ISNA(VLOOKUP($B31,IS明細!$B:X,23,0)),0,VLOOKUP($B31,IS明細!$B:X,23,0)) -> 0 | O31: =IF(ISNA(VLOOKUP($B31,IS明細!$B:Z,25,0)),0,VLOOKUP($B31,IS明細!$B:Z,25,0)) -> 0 | P31: =SUM(D31:O31) -> 0 | Q31: =P31/$P$8 -> 0
B32: 5122220 直接人工-加班費-免稅 | D32: =IF(ISNA(VLOOKUP($B32,IS明細!B:D,3,0)),0,VLOOKUP($B32,IS明細!B:D,3,0)) -> 0 | E32: =IF(ISNA(VLOOKUP($B32,IS明細!$B:F,5,0)),0,VLOOKUP($B32,IS明細!$B:F,5,0)) -> 0 | F32: =IF(ISNA(VLOOKUP($B32,IS明細!$B:H,7,0)),0,VLOOKUP($B32,IS明細!$B:H,7,0)) -> 0 | G32: =IF(ISNA(VLOOKUP($B32,IS明細!$B:J,9,0)),0,VLOOKUP($B32,IS明細!$B:J,9,0)) -> 0 | H32: =IF(ISNA(VLOOKUP($B32,IS明細!$B:L,11,0)),0,VLOOKUP($B32,IS明細!$B:L,11,0)) -> 0 | I32: =IF(ISNA(VLOOKUP($B32,IS明細!$B:N,13,0)),0,VLOOKUP($B32,IS明細!$B:N,13,0)) -> 0 | J32: =IF(ISNA(VLOOKUP($B32,IS明細!$B:P,15,0)),0,VLOOKUP($B32,IS明細!$B:P,15,0)) -> 0 | K32: =IF(ISNA(VLOOKUP($B32,IS明細!$B:R,17,0)),0,VLOOKUP($B32,IS明細!$B:R,17,0)) -> 0 | L32: =IF(ISNA(VLOOKUP($B32,IS明細!$B:T,19,0)),0,VLOOKUP($B32,IS明細!$B:T,19,0)) -> 0 | M32: =IF(ISNA(VLOOKUP($B32,IS明細!$B:V,21,0)),0,VLOOKUP($B32,IS明細!$B:V,21,0)) -> 0 | N32: =IF(ISNA(VLOOKUP($B32,IS明細!$B:X,23,0)),0,VLOOKUP($B32,IS明細!$B:X,23,0)) -> 0 | O32: =IF(ISNA(VLOOKUP($B32,IS明細!$B:Z,25,0)),0,VLOOKUP($B32,IS明細!$B:Z,25,0)) -> 0 | P32: =SUM(D32:O32) -> 0 | Q32: =P32/$P$8 -> 0
B33: 5122300 直接人工-伙食費 | D33: =IF(ISNA(VLOOKUP($B33,IS明細!B:D,3,0)),0,VLOOKUP($B33,IS明細!B:D,3,0)) -> 0 | E33: =IF(ISNA(VLOOKUP($B33,IS明細!$B:F,5,0)),0,VLOOKUP($B33,IS明細!$B:F,5,0)) -> 0 | F33: =IF(ISNA(VLOOKUP($B33,IS明細!$B:H,7,0)),0,VLOOKUP($B33,IS明細!$B:H,7,0)) -> 0 | G33: =IF(ISNA(VLOOKUP($B33,IS明細!$B:J,9,0)),0,VLOOKUP($B33,IS明細!$B:J,9,0)) -> 0 | H33: =IF(ISNA(VLOOKUP($B33,IS明細!$B:L,11,0)),0,VLOOKUP($B33,IS明細!$B:L,11,0)) -> 0 | I33: =IF(ISNA(VLOOKUP($B33,IS明細!$B:N,13,0)),0,VLOOKUP($B33,IS明細!$B:N,13,0)) -> 0 | J33: =IF(ISNA(VLOOKUP($B33,IS明細!$B:P,15,0)),0,VLOOKUP($B33,IS明細!$B:P,15,0)) -> 0 | K33: =IF(ISNA(VLOOKUP($B33,IS明細!$B:R,17,0)),0,VLOOKUP($B33,IS明細!$B:R,17,0)) -> 0 | L33: =IF(ISNA(VLOOKUP($B33,IS明細!$B:T,19,0)),0,VLOOKUP($B33,IS明細!$B:T,19,0)) -> 0 | M33: =IF(ISNA(VLOOKUP($B33,IS明細!$B:V,21,0)),0,VLOOKUP($B33,IS明細!$B:V,21,0)) -> 0 | N33: =IF(ISNA(VLOOKUP($B33,IS明細!$B:X,23,0)),0,VLOOKUP($B33,IS明細!$B:X,23,0)) -> 0 | O33: =IF(ISNA(VLOOKUP($B33,IS明細!$B:Z,25,0)),0,VLOOKUP($B33,IS明細!$B:Z,25,0)) -> 0 | P33: =SUM(D33:O33) -> 0 | Q33: =P33/$P$8 -> 0
B34: 5122400 直接人工-獎金 | D34: =IF(ISNA(VLOOKUP($B34,IS明細!B:D,3,0)),0,VLOOKUP($B34,IS明細!B:D,3,0)) -> 0 | E34: =IF(ISNA(VLOOKUP($B34,IS明細!$B:F,5,0)),0,VLOOKUP($B34,IS明細!$B:F,5,0)) -> 0 | F34: =IF(ISNA(VLOOKUP($B34,IS明細!$B:H,7,0)),0,VLOOKUP($B34,IS明細!$B:H,7,0)) -> 0 | G34: =IF(ISNA(VLOOKUP($B34,IS明細!$B:J,9,0)),0,VLOOKUP($B34,IS明細!$B:J,9,0)) -> 0 | H34: =IF(ISNA(VLOOKUP($B34,IS明細!$B:L,11,0)),0,VLOOKUP($B34,IS明細!$B:L,11,0)) -> 0 | I34: =IF(ISNA(VLOOKUP($B34,IS明細!$B:N,13,0)),0,VLOOKUP($B34,IS明細!$B:N,13,0)) -> 0 | J34: =IF(ISNA(VLOOKUP($B34,IS明細!$B:P,15,0)),0,VLOOKUP($B34,IS明細!$B:P,15,0)) -> 0 | K34: =IF(ISNA(VLOOKUP($B34,IS明細!$B:R,17,0)),0,VLOOKUP($B34,IS明細!$B:R,17,0)) -> 0 | L34: =IF(ISNA(VLOOKUP($B34,IS明細!$B:T,19,0)),0,VLOOKUP($B34,IS明細!$B:T,19,0)) -> 0 | M34: =IF(ISNA(VLOOKUP($B34,IS明細!$B:V,21,0)),0,VLOOKUP($B34,IS明細!$B:V,21,0)) -> 0 | N34: =IF(ISNA(VLOOKUP($B34,IS明細!$B:X,23,0)),0,VLOOKUP($B34,IS明細!$B:X,23,0)) -> 0 | O34: =IF(ISNA(VLOOKUP($B34,IS明細!$B:Z,25,0)),0,VLOOKUP($B34,IS明細!$B:Z,25,0)) -> 0 | P34: =SUM(D34:O34) -> 0 | Q34: =P34/$P$8 -> 0
B35: 5122500 直接人工-退休金 | D35: =IF(ISNA(VLOOKUP($B35,IS明細!B:D,3,0)),0,VLOOKUP($B35,IS明細!B:D,3,0)) -> 0 | E35: =IF(ISNA(VLOOKUP($B35,IS明細!$B:F,5,0)),0,VLOOKUP($B35,IS明細!$B:F,5,0)) -> 0 | F35: =IF(ISNA(VLOOKUP($B35,IS明細!$B:H,7,0)),0,VLOOKUP($B35,IS明細!$B:H,7,0)) -> 0 | G35: =IF(ISNA(VLOOKUP($B35,IS明細!$B:J,9,0)),0,VLOOKUP($B35,IS明細!$B:J,9,0)) -> 0 | H35: =IF(ISNA(VLOOKUP($B35,IS明細!$B:L,11,0)),0,VLOOKUP($B35,IS明細!$B:L,11,0)) -> 0 | I35: =IF(ISNA(VLOOKUP($B35,IS明細!$B:N,13,0)),0,VLOOKUP($B35,IS明細!$B:N,13,0)) -> 0 | J35: =IF(ISNA(VLOOKUP($B35,IS明細!$B:P,15,0)),0,VLOOKUP($B35,IS明細!$B:P,15,0)) -> 0 | K35: =IF(ISNA(VLOOKUP($B35,IS明細!$B:R,17,0)),0,VLOOKUP($B35,IS明細!$B:R,17,0)) -> 0 | L35: =IF(ISNA(VLOOKUP($B35,IS明細!$B:T,19,0)),0,VLOOKUP($B35,IS明細!$B:T,19,0)) -> 0 | M35: =IF(ISNA(VLOOKUP($B35,IS明細!$B:V,21,0)),0,VLOOKUP($B35,IS明細!$B:V,21,0)) -> 0 | N35: =IF(ISNA(VLOOKUP($B35,IS明細!$B:X,23,0)),0,VLOOKUP($B35,IS明細!$B:X,23,0)) -> 0 | O35: =IF(ISNA(VLOOKUP($B35,IS明細!$B:Z,25,0)),0,VLOOKUP($B35,IS明細!$B:Z,25,0)) -> 0 | P35: =SUM(D35:O35) -> 0 | Q35: =P35/$P$8 -> 0
